Workbook

Sheet Wage Detail Linked
A1: B&W PRODUCTIONS — WAGE DETAIL LINKED (master)
A2: Payroll week 2026-09-19 to 2026-09-25. One row per paid shift, including missed shifts from the previous payroll (real date shown). Edit only the yellow cells; Auditor Trail, Auditor Summary and Missed Shifts recalculate from this tab.
A4: Shift ID | B4: Employee | C4: Date | D4: Day | E4: Missed shift? | F4: Venue / Outlet | G4: Area | H4: Description | I4: Work type | J4: Start | K4: End | L4: Claimed hours | M4: Approved hours (system) | N4: Override hours (edit) | O4: Effective hours | P4: Amount (system) | Q4: Override amount (edit) | R4: Effective amount | S4: Rate used | T4: Breakdown (how the amount was worked out) | U4: Override reason (edit) | V4: Review # | W4: System note | X4: Review decision
A5: 9812 | B5: Bhekizitha Maphosa | C5: 2026-09-17 | D5: Thursday | E5: YES | F5: Botanical garden Pretoria | G5: Pretoria | H5: Break down | I5: Normal | J5: 06:00 | K5: 07:00 | L5: 1 | M5: 1 | O5: =IF(N5<>"",N5,M5) | P5: 95 | R5: =IF(Q5<>"",Q5,IF(N5<>"",IF(M5>0,ROUND(P5*N5/M5,2),0),P5)) | S5: 95 | T5: Venue/event: 1 h × R95 | W5: CLEAR: worked 07:00–16:00 that day (paid in payroll n/a); these hours are outside those times. | X5: No review needed
A6: 9811 | B6: Bhekizitha Maphosa | C6: 2026-09-17 | D6: Thursday | E6: YES | F6: FNB Stadium | G6: Johannesburg | H6: Setup fnb stadium Scorpion kings concert | I6: Normal | J6: 16:00 | K6: 18:00 | L6: 2 | M6: 2 | O6: =IF(N6<>"",N6,M6) | P6: 190 | R6: =IF(Q6<>"",Q6,IF(N6<>"",IF(M6>0,ROUND(P6*N6/M6,2),0),P6)) | S6: 95 | T6: Venue/event: 2 h × R95 | W6: CLEAR: worked 07:00–16:00 that day (paid in payroll n/a); these hours are outside those times. | X6: No review needed
A7: 9809 | B7: Bhekizitha Maphosa | C7: 2026-09-21 | D7: Monday | F7: FNB Stadium | G7: Fnb stadium | H7: Break down | I7: Normal | J7: 07:00 | K7: 16:00 | L7: 9 | M7: 9 | O7: =IF(N7<>"",N7,M7) | P7: 855 | R7: =IF(Q7<>"",Q7,IF(N7<>"",IF(M7>0,ROUND(P7*N7/M7,2),0),P7)) | S7: 95 | T7: Venue/event: 9 h × R95
A8: 9808 | B8: Bhekizitha Maphosa | C8: 2026-09-22 | D8: Tuesday | F8: Warehouse loading | G8: Henley on Klip, Meyerton | H8: Loading and cleaning | I8: Normal | J8: 07:00 | K8: 16:00 | L8: 9 | M8: 9 | O8: =IF(N8<>"",N8,M8) | P8: 690.63 | R8: =IF(Q8<>"",Q8,IF(N8<>"",IF(M8>0,ROUND(P8*N8/M8,2),0),P8)) | S8: 81.25 | T8: Warehouse: 9 h − 0.5 h staff meeting 07:00–07:30 (unpaid, R40,63) = 8.5 h × R81,25 | V8: #10027
A9: 9807 | B9: Bhekizitha Maphosa | C9: 2026-09-23 | D9: Wednesday | F9: Warehouse | G9: Henley on Klip, Meyerton | H9: Loading and cleaning | I9: Normal | J9: 07:00 | K9: 16:00 | L9: 9 | M9: 9 | O9: =IF(N9<>"",N9,M9) | P9: 690.63 | R9: =IF(Q9<>"",Q9,IF(N9<>"",IF(M9>0,ROUND(P9*N9/M9,2),0),P9)) | S9: 81.25 | T9: Warehouse: 9 h − 0.5 h staff meeting 07:00–07:30 (unpaid, R40,63) = 8.5 h × R81,25 | V9: #10025
A10: 9806 | B10: Bhekizitha Maphosa | C10: 2026-09-24 | D10: Thursday | F10: Warehouse | G10: Henley on Klip, Meyerton | H10: Loading and cleaning | I10: Warehouse Team | J10: 07:00 | K10: 15:00 | L10: 8 | M10: 8 | O10: =IF(N10<>"",N10,M10) | P10: 1218.75 | R10: =IF(Q10<>"",Q10,IF(N10<>"",IF(M10>0,ROUND(P10*N10/M10,2),0),P10)) | S10: 162.5 | T10: OWNER CORRECTION: Owner 23 Sep: Heritage Day — warehouse, hours set to 07:00–15:00 (no set-ups). 7.5 h × R162,50 = R1218.75 | V10: #10023 | W10: #10137 Public holiday (Heritage Day) — owner to approve or decline: PUBLIC HOLIDAY — Heritage Day (24 Sep 2026): Bhekizitha Maphosa worked 07:00–16:00. Held for owner approval. | X10: #10137 DECIDED 7.50 h by Bernie Burness 2026-09-23 10:28: Public holiday (Heritage Day) approved by Bernie Burness 23 Sep — hours set to 07:00–15:00 (no set-ups): Warehouse public holiday (Heritage Day), owner set hours 07:00–15:00: 8.0 h − 0.5 h staff meeting 07:00–07:30 (unpaid) = 7.5 h × R162,50 (R81,25 × 2) = R1218.75
A11: 9805 | B11: Bhekizitha Maphosa | C11: 2026-09-25 | D11: Friday | F11: The Capital Sandton and Bonitical Emmarentia | G11: Johannesburg | H11: Setup | I11: Normal | J11: 07:00 | K11: 16:00 | L11: 9 | M11: 9 | O11: =IF(N11<>"",N11,M11) | P11: 855 | R11: =IF(Q11<>"",Q11,IF(N11<>"",IF(M11>0,ROUND(P11*N11/M11,2),0),P11)) | S11: 95 | T11: Venue/event: 9 h × R95
A12: 9788 | B12: Daniel Motaung | C12: 2026-09-21 | D12: Monday | F12: FNB Stadium | G12: Johannesburg | H12: Breakdown | I12: Normal | J12: 07:00 | K12: 16:00 | L12: 9 | M12: 9 | O12: =IF(N12<>"",N12,M12) | P12: 855 | R12: =IF(Q12<>"",Q12,IF(N12<>"",IF(M12>0,ROUND(P12*N12/M12,2),0),P12)) | S12: 95 | T12: Venue/event: 9 h × R95
A13: 9787 | B13: Daniel Motaung | C13: 2026-09-22 | D13: Tuesday | F13: Warehouse loading | G13: Henley on Klip | H13: Warehouse | I13: Normal | J13: 07:00 | K13: 16:00 | L13: 9 | M13: 9 | O13: =IF(N13<>"",N13,M13) | P13: 690.63 | R13: =IF(Q13<>"",Q13,IF(N13<>"",IF(M13>0,ROUND(P13*N13/M13,2),0),P13)) | S13: 81.25 | T13: Warehouse: 9 h − 0.5 h staff meeting 07:00–07:30 (unpaid, R40,63) = 8.5 h × R81,25 | V13: #9990
A14: 9786 | B14: Daniel Motaung | C14: 2026-09-23 | D14: Wednesday | F14: Set up vaal Boating | G14: Vandrebilpark | H14: Set Up | I14: Normal | J14: 07:00 | K14: 16:00 | L14: 9 | M14: 9 | O14: =IF(N14<>"",N14,M14) | P14: 855 | R14: =IF(Q14<>"",Q14,IF(N14<>"",IF(M14>0,ROUND(P14*N14/M14,2),0),P14)) | S14: 95 | T14: Venue/event: 9 h × R95
A15: 9785 | B15: Daniel Motaung | C15: 2026-09-24 | D15: Thursday | F15: Warehouse | G15: Henley on Klip | H15: Warehouse | I15: Warehouse Team | J15: 07:00 | K15: 15:00 | L15: 8 | M15: 8 | O15: =IF(N15<>"",N15,M15) | P15: 1218.75 | R15: =IF(Q15<>"",Q15,IF(N15<>"",IF(M15>0,ROUND(P15*N15/M15,2),0),P15)) | S15: 162.5 | T15: OWNER CORRECTION: Owner 23 Sep: Heritage Day — warehouse, hours set to 07:00–15:00 (no set-ups). 7.5 h × R162,50 = R1218.75 | V15: #9987 | W15: #10138 Public holiday (Heritage Day) — owner to approve or decline: PUBLIC HOLIDAY — Heritage Day (24 Sep 2026): Daniel Motaung worked 07:00–16:00. Held for owner approval. | X15: #10138 DECIDED 7.50 h by Bernie Burness 2026-09-23 10:28: Public holiday (Heritage Day) approved by Bernie Burness 23 Sep — hours set to 07:00–15:00 (no set-ups): Warehouse public holiday (Heritage Day), owner set hours 07:00–15:00: 8.0 h − 0.5 h staff meeting 07:00–07:30 (unpaid) = 7.5 h × R162,50 (R81,25 × 2) = R1218.75
A16: 9784 | B16: Daniel Motaung | C16: 2026-09-25 | D16: Friday | F16: Vaal Boating | G16: Vandrebilpark | H16: Breakdown | I16: Normal | J16: 07:00 | K16: 16:00 | L16: 9 | M16: 9 | O16: =IF(N16<>"",N16,M16) | P16: 855 | R16: =IF(Q16<>"",Q16,IF(N16<>"",IF(M16>0,ROUND(P16*N16/M16,2),0),P16)) | S16: 95 | T16: Venue/event: 9 h × R95
A17: 9822 | B17: Erence Mngomezulu | C17: 2026-09-16 | D17: Wednesday | E17: YES | F17: Parys golf & country Estate | G17: Parys | H17: Setup | I17: Normal | J17: 16:00 | K17: 18:00 | L17: 2 | M17: 2 | O17: =IF(N17<>"",N17,M17) | P17: 190 | R17: =IF(Q17<>"",Q17,IF(N17<>"",IF(M17>0,ROUND(P17*N17/M17,2),0),P17)) | S17: 95 | T17: Venue/event: 2 h × R95 | W17: CLEAR: worked 07:00–16:00 that day (paid in payroll n/a); these hours are outside those times. | X17: No review needed
A18: 9823 | B18: Erence Mngomezulu | C18: 2026-09-17 | D18: Thursday | E18: YES | F18: Parys golf & country Estate | G18: Parys | H18: Setup | I18: Normal | J18: 06:00 | K18: 07:00 | L18: 1 | M18: 1 | O18: =IF(N18<>"",N18,M18) | P18: 95 | R18: =IF(Q18<>"",Q18,IF(N18<>"",IF(M18>0,ROUND(P18*N18/M18,2),0),P18)) | S18: 95 | T18: Venue/event: 1 h × R95 | W18: CLEAR: worked 07:00–16:00 that day (paid in payroll n/a); these hours are outside those times. | X18: No review needed
A19: 9824 | B19: Erence Mngomezulu | C19: 2026-09-17 | D19: Thursday | E19: YES | F19: Parys golf & country Estate | G19: Parys | H19: Strike down | I19: Normal | J19: 16:00 | K19: 20:00 | L19: 4 | M19: 4 | O19: =IF(N19<>"",N19,M19) | P19: 380 | R19: =IF(Q19<>"",Q19,IF(N19<>"",IF(M19>0,ROUND(P19*N19/M19,2),0),P19)) | S19: 95 | T19: Venue/event: 4 h × R95 | W19: CLEAR: worked 07:00–16:00 that day (paid in payroll n/a); these hours are outside those times. | X19: No review needed
A20: 9825 | B20: Erence Mngomezulu | C20: 2026-09-21 | D20: Monday | F20: FNB Stadium | G20: Johannesburg | H20: Strike down | I20: Normal | J20: 07:00 | K20: 16:00 | L20: 9 | M20: 9 | O20: =IF(N20<>"",N20,M20) | P20: 855 | R20: =IF(Q20<>"",Q20,IF(N20<>"",IF(M20>0,ROUND(P20*N20/M20,2),0),P20)) | S20: 95 | T20: Venue/event: 9 h × R95
A21: 9826 | B21: Erence Mngomezulu | C21: 2026-09-22 | D21: Tuesday | F21: Warehouse | G21: Meyerton | H21: Loading/offloading/cleaning and packing | I21: Normal | J21: 07:00 | K21: 16:00 | L21: 9 | M21: 9 | O21: =IF(N21<>"",N21,M21) | P21: 690.63 | R21: =IF(Q21<>"",Q21,IF(N21<>"",IF(M21>0,ROUND(P21*N21/M21,2),0),P21)) | S21: 81.25 | T21: Warehouse: 9 h − 0.5 h staff meeting 07:00–07:30 (unpaid, R40,63) = 8.5 h × R81,25 | V21: #10048
A22: 9827 | B22: Erence Mngomezulu | C22: 2026-09-23 | D22: Wednesday | F22: Warehouse | G22: Meyerton | H22: Loading/offloading/cleaning and packing | I22: Normal | J22: 07:00 | K22: 16:00 | L22: 9 | M22: 9 | O22: =IF(N22<>"",N22,M22) | P22: 690.63 | R22: =IF(Q22<>"",Q22,IF(N22<>"",IF(M22>0,ROUND(P22*N22/M22,2),0),P22)) | S22: 81.25 | T22: Warehouse: 9 h − 0.5 h staff meeting 07:00–07:30 (unpaid, R40,63) = 8.5 h × R81,25 | V22: #10050
A23: 9829 | B23: Erence Mngomezulu | C23: 2026-09-24 | D23: Thursday | F23: Warehouse | G23: Meyerton | H23: Loading/offloading/cleaning and packing | I23: Warehouse Team | J23: 07:00 | K23: 15:00 | L23: 8 | M23: 8 | O23: =IF(N23<>"",N23,M23) | P23: 1218.75 | R23: =IF(Q23<>"",Q23,IF(N23<>"",IF(M23>0,ROUND(P23*N23/M23,2),0),P23)) | S23: 162.5 | T23: OWNER CORRECTION: Owner 23 Sep: Heritage Day — warehouse, hours set to 07:00–15:00 (no set-ups). 7.5 h × R162,50 = R1218.75 | V23: #10053 | W23: #10139 Public holiday (Heritage Day) — owner to approve or decline: PUBLIC HOLIDAY — Heritage Day (24 Sep 2026): Erence Mngomezulu worked 07:00–16:00. Held for owner approval. | X23: #10139 DECIDED 7.50 h by Bernie Burness 2026-09-23 10:28: Public holiday (Heritage Day) approved by Bernie Burness 23 Sep — hours set to 07:00–15:00 (no set-ups): Warehouse public holiday (Heritage Day), owner set hours 07:00–15:00: 8.0 h − 0.5 h staff meeting 07:00–07:30 (unpaid) = 7.5 h × R162,50 (R81,25 × 2) = R1218.75
A24: 9828 | B24: Erence Mngomezulu | C24: 2026-09-25 | D24: Friday | F24: Pretoria country club | G24: Pretoria | H24: Setup/standby | I24: Normal | J24: 07:00 | K24: 16:00 | L24: 9 | M24: 9 | O24: =IF(N24<>"",N24,M24) | P24: 855 | R24: =IF(Q24<>"",Q24,IF(N24<>"",IF(M24>0,ROUND(P24*N24/M24,2),0),P24)) | S24: 95 | T24: Venue/event: 9 h × R95
A25: 9801 | B25: Erick Mpho Molefe | C25: 2026-09-17 | D25: Thursday | E25: YES | F25: FNB Stadium | G25: Johannesburg | H25: Setup FNB Stadium Scorpion Kings concert (extra hours after Clarens 07–16) | I25: Normal | J25: 16:00 | K25: 18:00 | L25: 2 | M25: 2 | O25: =IF(N25<>"",N25,M25) | P25: 190 | R25: =IF(Q25<>"",Q25,IF(N25<>"",IF(M25>0,ROUND(P25*N25/M25,2),0),P25)) | S25: 95 | T25: OWNER CORRECTION: Owner 23 Sep: worker entered this as Mon 21 Sep FNB strike down 07–16 — it was Thu 17 Sep 16:00–18:00 FNB Stadium (same as Bhekizitha #9811). 2 h × R95 = R190 | W25: CLEAR: worked 07:00–16:00 that day (paid in payroll n/a); these hours are outside those times. | X25: No review needed
A26: 9859 | B26: Erick Mpho Molefe | C26: 2026-09-21 | D26: Monday | F26: Warehouse | G26: Henley | H26: Loading (office-entered: worker put FNB on this date by mistake) | I26: Warehouse Team | J26: 07:00 | K26: 16:00 | L26: 9 | M26: 9 | O26: =IF(N26<>"",N26,M26) | P26: 690.63 | R26: =IF(Q26<>"",Q26,IF(N26<>"",IF(M26>0,ROUND(P26*N26/M26,2),0),P26)) | S26: 81.25 | T26: OWNER CORRECTION: Owner 23 Sep: Erick was in the warehouse Mon 21 Sep; his FNB entry on this date was really Thu 17 Sep 16–18. 9 h − 0.5 h meeting = 8.5 h × R81,25 = R690,63
A27: 9800 | B27: Erick Mpho Molefe | C27: 2026-09-22 | D27: Tuesday | F27: warehouse | G27: henley | H27: loading | I27: Normal | J27: 07:00 | K27: 16:00 | L27: 9 | M27: 9 | O27: =IF(N27<>"",N27,M27) | P27: 690.63 | R27: =IF(Q27<>"",Q27,IF(N27<>"",IF(M27>0,ROUND(P27*N27/M27,2),0),P27)) | S27: 81.25 | T27: Warehouse: 9 h − 0.5 h staff meeting 07:00–07:30 (unpaid, R40,63) = 8.5 h × R81,25 | V27: #10015
A28: 9799 | B28: Erick Mpho Molefe | C28: 2026-09-23 | D28: Wednesday | F28: wharehouse | G28: henley | H28: loading | I28: Normal | J28: 07:00 | K28: 16:00 | L28: 9 | M28: 9 | O28: =IF(N28<>"",N28,M28) | P28: 690.63 | R28: =IF(Q28<>"",Q28,IF(N28<>"",IF(M28>0,ROUND(P28*N28/M28,2),0),P28)) | S28: 81.25 | T28: OWNER CORRECTION: Warehouse (owner 23 Sep): 8.5 h × R81,25 = R690,63
A29: 9798 | B29: Erick Mpho Molefe | C29: 2026-09-24 | D29: Thursday | F29: wharehouse | G29: Henley | H29: loading | I29: Warehouse Team | J29: 07:00 | K29: 15:00 | L29: 8 | M29: 8 | O29: =IF(N29<>"",N29,M29) | P29: 1218.75 | R29: =IF(Q29<>"",Q29,IF(N29<>"",IF(M29>0,ROUND(P29*N29/M29,2),0),P29)) | S29: 162.5 | T29: OWNER CORRECTION: Owner 23 Sep: Heritage Day — warehouse, hours set to 07:00–15:00 (no set-ups). 7.5 h × R162,50 = R1218.75 | W29: #10010 Public holiday (Heritage Day) — owner to approve or decline: PUBLIC HOLIDAY — OWNER APPROVAL NEEDED: Erick Mpho Molefe worked 07:00–16:00 on 2026-09-24 (Heritage Day) at wharehouse (Normal). Public-holiday work is not paid automatically. Recommended: Venue/event public holiday (Heritage Day): 9 h × R190 (R95 × 2) = R1 710,00. R0 is paid until the owner approves or declines. | X29: #10010 DECIDED 7.50 h by Bernie Burness 2026-09-23 10:29: Public holiday (Heritage Day) approved by Bernie Burness 23 Sep — hours set to 07:00–15:00 (no set-ups): Warehouse public holiday (Heritage Day), owner set hours 07:00–15:00: 8.0 h − 0.5 h staff meeting 07:00–07:30 (unpaid) = 7.5 h × R162,50 (R81,25 × 2) = R1218.75
A30: 9797 | B30: Erick Mpho Molefe | C30: 2026-09-25 | D30: Friday | F30: Botanical | G30: johannessburg | H30: set up | I30: Normal | J30: 07:00 | K30: 16:00 | L30: 9 | M30: 9 | O30: =IF(N30<>"",N30,M30) | P30: 855 | R30: =IF(Q30<>"",Q30,IF(N30<>"",IF(M30>0,ROUND(P30*N30/M30,2),0),P30)) | S30: 95 | T30: Venue/event: 9 h × R95
A31: 9789 | B31: Givemore Chifetete Kuziwa | C31: 2026-09-17 | D31: Thursday | E31: YES | F31: Warehouse | G31: Pretoria and fnb | H31: Strike down and set up | I31: Warehouse Team | J31: 06:00 | K31: 18:00 | L31: 12 | M31: 12 | O31: =IF(N31<>"",N31,M31) | P31: 640 | R31: =IF(Q31<>"",Q31,IF(N31<>"",IF(M31>0,ROUND(P31*N31/M31,2),0),P31)) | S31: 95 | T31: DIFFERENCE ONLY (Venue R95/h chosen by Bernie Burness, #10073): Paid last week 08:00–16:00 House/Garden 8.00 h × R62,50 = R500,00 (shift #9705, payroll earlier); 06:00–18:00 at a venue = R1 140,00 (R95,00/h); less the House/Garden already paid R500,00; TO PAY THIS WEEK R640,00 | W31: OVERLAP: already paid 08:00–16:00 (Garden, R500,00, payroll n/a) on this day. | #10073 Warehouse claimed — but area says “Pretoria and fnb”: WAREHOUSE CLAIMED BUT AREA SAYS “Pretoria and fnb”: Givemore Chifetete Kuziwa selected Warehouse Team at “Warehouse” for 12.00 h on Thu 17 Sep 2026, but wrote the area as “Pretoria and fnb” — that is a venue, not the warehouse. Other workers were at Botanical garden Pretoria that day. If he was at “Pretoria and fnb”, he is due the venue rate (R95/h); if he was really in the warehouse, R81,25/h. Choose below. | X31: #10073 DECIDED by Bernie Burness 2026-09-23 08:58: Event/Venue rate chosen — shift #9789 R934,38 → R640,00 (Venue/event: 12 h × R95 → DIFFERENCE ONLY: Paid last week 08:00–16:00 House/Garden 8.00 h × R62,50 = R500,00 (shift #9705, payroll earlier); 06:00–18:00 at a venue = R1 140,00 (R95,00/h); less the House/Garden already paid R500,00; TO PAY THIS WEEK R640,00)
A32: 9790 | B32: Givemore Chifetete Kuziwa | C32: 2026-09-19 | D32: Saturday | F32: Garden | G32: Henley on klip | H32: Cleaning | I32: House/Garden | J32: 08:00 | K32: 14:00 | L32: 6 | M32: 6 | O32: =IF(N32<>"",N32,M32) | P32: 375 | R32: =IF(Q32<>"",Q32,IF(N32<>"",IF(M32>0,ROUND(P32*N32/M32,2),0),P32)) | S32: 62.5 | T32: Gardener House work: 6 h × R62,50
A33: 9791 | B33: Givemore Chifetete Kuziwa | C33: 2026-09-21 | D33: Monday | F33: Garden | G33: Henley on klip | H33: Cleaning | I33: House/Garden | J33: 08:00 | K33: 16:00 | L33: 8 | M33: 8 | O33: =IF(N33<>"",N33,M33) | P33: 500 | R33: =IF(Q33<>"",Q33,IF(N33<>"",IF(M33>0,ROUND(P33*N33/M33,2),0),P33)) | S33: 62.5 | T33: Gardener House work: 8 h × R62,50
A34: 9792 | B34: Givemore Chifetete Kuziwa | C34: 2026-09-22 | D34: Tuesday | F34: Garden | G34: Henley on klip | H34: Cleaning | I34: House/Garden | J34: 08:00 | K34: 16:00 | L34: 8 | M34: 8 | O34: =IF(N34<>"",N34,M34) | P34: 500 | R34: =IF(Q34<>"",Q34,IF(N34<>"",IF(M34>0,ROUND(P34*N34/M34,2),0),P34)) | S34: 62.5 | T34: Gardener House work: 8 h × R62,50
A35: 9793 | B35: Givemore Chifetete Kuziwa | C35: 2026-09-23 | D35: Wednesday | F35: Garden | G35: Henley on klip | H35: Cleaning | I35: House/Garden | J35: 08:00 | K35: 16:00 | L35: 8 | M35: 8 | O35: =IF(N35<>"",N35,M35) | P35: 500 | R35: =IF(Q35<>"",Q35,IF(N35<>"",IF(M35>0,ROUND(P35*N35/M35,2),0),P35)) | S35: 62.5 | T35: Gardener House work: 8 h × R62,50
A36: 9794 | B36: Givemore Chifetete Kuziwa | C36: 2026-09-24 | D36: Thursday | F36: Garden | G36: Henley on klip | H36: Cleaning | I36: House/Garden | J36: 08:00 | K36: 15:00 | L36: 7 | M36: 7 | O36: =IF(N36<>"",N36,M36) | P36: 875 | R36: =IF(Q36<>"",Q36,IF(N36<>"",IF(M36>0,ROUND(P36*N36/M36,2),0),P36)) | S36: 125 | T36: OWNER CORRECTION: Owner 23 Sep: Heritage Day — gardener hours set to 08:00–15:00; 7 h × R62,50 × 2 = R875 | W36: #10140 Public holiday (Heritage Day) — Givemore — approved R1 000,00 — CHECK HOURS NEXT WEEK: PUBLIC HOLIDAY — Heritage Day: Givemore (gardener) claimed 08:00–16:00. Owner: double the day = R1 000. VERIFY NEXT WEEK whether he actually worked 8 h or 4 h. | X36: #10140 DECIDED 7.00 h by Bernie Burness 2026-09-23 10:31: Public holiday (Heritage Day) approved by Bernie Burness 23 Sep — gardener, hours set to 08:00–15:00: 7 h × R62,50 × 2 = R875,00. CHECK NEXT WEEK what time he really worked until.
A37: 9795 | B37: Givemore Chifetete Kuziwa | C37: 2026-09-25 | D37: Friday | F37: Garden | G37: Henley on klip | H37: Cleaning | I37: House/Garden | J37: 08:00 | K37: 16:00 | L37: 8 | M37: 8 | O37: =IF(N37<>"",N37,M37) | P37: 500 | R37: =IF(Q37<>"",Q37,IF(N37<>"",IF(M37>0,ROUND(P37*N37/M37,2),0),P37)) | S37: 62.5 | T37: Gardener House work: 8 h × R62,50
A38: 9850 | B38: Isaac Mbele | C38: 2026-09-21 | D38: Monday | F38: Warehouse | G38: Randvaal, Gauteng, South Africa | H38: Off Loading | I38: Normal | J38: 07:00 | K38: 16:00 | L38: 9 | M38: 9 | O38: =IF(N38<>"",N38,M38) | P38: 690.63 | R38: =IF(Q38<>"",Q38,IF(N38<>"",IF(M38>0,ROUND(P38*N38/M38,2),0),P38)) | S38: 81.25 | T38: Warehouse: 9 h − 0.5 h staff meeting 07:00–07:30 (unpaid, R40,63) = 8.5 h × R81,25 | V38: #10104
A39: 9851 | B39: Isaac Mbele | C39: 2026-09-22 | D39: Tuesday | F39: Warehouse | G39: Randvaal, Gauteng, South Africa | H39: Loading | I39: Normal | J39: 07:00 | K39: 16:00 | L39: 9 | M39: 9 | O39: =IF(N39<>"",N39,M39) | P39: 690.63 | R39: =IF(Q39<>"",Q39,IF(N39<>"",IF(M39>0,ROUND(P39*N39/M39,2),0),P39)) | S39: 81.25 | T39: Warehouse: 9 h − 0.5 h staff meeting 07:00–07:30 (unpaid, R40,63) = 8.5 h × R81,25 | V39: #10106
A40: 9854 | B40: Isaac Mbele | C40: 2026-09-23 | D40: Wednesday | F40: Warehouse | G40: Randvaal, Gauteng, South Africa | H40: Loading | I40: Normal | J40: 07:00 | K40: 16:00 | L40: 9 | M40: 9 | O40: =IF(N40<>"",N40,M40) | P40: 690.63 | R40: =IF(Q40<>"",Q40,IF(N40<>"",IF(M40>0,ROUND(P40*N40/M40,2),0),P40)) | S40: 81.25 | T40: Warehouse: 9 h − 0.5 h staff meeting 07:00–07:30 (unpaid, R40,63) = 8.5 h × R81,25 | V40: #10118
A41: 9856 | B41: Isaac Mbele | C41: 2026-09-24 | D41: Thursday | F41: Warehouse | G41: Randvaal, Gauteng, South Africa | H41: Loading | I41: Warehouse Team | J41: 07:00 | K41: 15:00 | L41: 8 | M41: 8 | O41: =IF(N41<>"",N41,M41) | P41: 1218.75 | R41: =IF(Q41<>"",Q41,IF(N41<>"",IF(M41>0,ROUND(P41*N41/M41,2),0),P41)) | S41: 162.5 | T41: OWNER CORRECTION: Owner 23 Sep: Heritage Day — warehouse, hours set to 07:00–15:00 (no set-ups). 7.5 h × R162,50 = R1218.75 | V41: #10125 | W41: #10141 Public holiday (Heritage Day) — owner to approve or decline: PUBLIC HOLIDAY — Heritage Day (24 Sep 2026): Isaac Mbele worked 07:00–15:00. Held for owner approval. | X41: #10141 DECIDED 7.50 h by Bernie Burness 2026-09-23 10:32: Public holiday (Heritage Day) approved by Bernie Burness 23 Sep — hours set to 07:00–15:00 (no set-ups): Warehouse public holiday (Heritage Day), owner set hours 07:00–15:00: 8.0 h − 0.5 h staff meeting 07:00–07:30 (unpaid) = 7.5 h × R162,50 (R81,25 × 2) = R1218.75
A42: 9858 | B42: Isaac Mbele | C42: 2026-09-25 | D42: Friday | F42: Warehouse | G42: Randvaal, Gauteng, South Africa | H42: Loading | I42: Normal | J42: 07:00 | K42: 16:00 | L42: 9 | M42: 9 | O42: =IF(N42<>"",N42,M42) | P42: 690.63 | R42: =IF(Q42<>"",Q42,IF(N42<>"",IF(M42>0,ROUND(P42*N42/M42,2),0),P42)) | S42: 81.25 | T42: Warehouse: 9 h − 0.5 h staff meeting 07:00–07:30 (unpaid, R40,63) = 8.5 h × R81,25 | V42: #10129
A43: 9855 | B43: John Simbarashe Mhlanga | C43: 2026-09-16 | D43: Wednesday | E43: YES | F43: Botanical gardens event day | G43: Pretoria | H43: Running the event at botanical Gardens | I43: Normal | J43: 07:00 | K43: 16:00 | L43: 9 | M43: 0 | O43: =IF(N43<>"",N43,M43) | P43: 105 | R43: =IF(Q43<>"",Q43,IF(N43<>"",IF(M43>0,ROUND(P43*N43/M43,2),0),P43)) | S43: 95 | T43: OWNER CORRECTION: Owner 23 Sep: Wed 16 Sep Botanical 07–16 already paid R750 in payroll 12–18 Sep (shift #9766). Only the rate correction to venue R95 is due: 9 h × R95 = R855 − R750 = R105 | V43: #10132 | W43: OVERLAP: already paid 07:00–16:00 (Botanical gardens event day, R750,00, payroll n/a) on this day. | #10122 Manual overlap review: the same employee has another overlapping entry on 2026-09-16 for 07:00-16:00. | #10132 ALREADY PAID — WRONG RATE: John was paid Wed 16 Sep 2026 07:00–16:00 · Botanical gardens event day (Pretoria) · Normal · "Running the event at botanical Gardens" · 9.00 h × R90,00 = R750,00 (payroll 2026-09-12). He now claims 07:00–16:00 · Botanical gardens event day (Pretoria) · Normal · "Running the event at botanical Gardens" · 9.00 h for the same day. Same work type, but the rate paid (R90,00/h) differs from the rule (R95,00/h). • Rate correction on the paid hours 07:00–16:00: 9.00 h — worth R855,00 at the correct rule, R750,00 was paid → +R105,00 Still due: R105,00 (full day 9.00 h at the correct rule = R855,00 − R750,00 already paid). Hours from Wednesday onwards are estimated for the auditor run; this entry corrects them. Bernie to approve — nothing has been changed. System recommended 0.00 h. | X43: #10122 DECIDED 0.00 h by Bernie Burness 2026-09-23 08:53: ALREADY BILLED Wednesday 2026-09-16 · 07:00–16:00 · 9.00 h Normal · Botanical gardens event day · Running the event at botanical Gardens R750,00 · shift #9766 · PAID in payroll 2026-09-12 → 2026-09-18 (closed) | #10132 DECIDED 0.00 h by Bernie Burness 2026-09-23 08:56: Already paid — WRONG RATE — R105,00 still due — approved amount R105,00
A44: 9779 | B44: John Simbarashe Mhlanga | C44: 2026-09-17 | D44: Thursday | E44: YES | F44: Music Bus | G44: Thembisa | H44: Missed shifts from Thursday doing music bus in Thembisa where there was a trade visit | I44: Music Bus | J44: 15:00 | K44: 20:00 | L44: 5 | M44: 4 | O44: =IF(N44<>"",N44,M44) | P44: 480 | R44: =IF(Q44<>"",Q44,IF(N44<>"",IF(M44>0,ROUND(P44*N44/M44,2),0),P44)) | S44: 120 | T44: OWNER CORRECTION: Already paid 07:00–16:00 (FNB, shift #9767). Only 16:00–20:00 = 4 h × R120 Music Bus = R480,00 | V44: #10069 | W44: OVERLAP: already paid 07:00–16:00 (FNB Stadium, R750,00, payroll n/a) on this day. | #9972 Manual overlap review: the same employee has another overlapping entry on 2026-09-17 for 15:00-20:00. | #10069 ALREADY PAID — EXTRA HOURS: John was paid Thu 17 Sep 2026 07:00–16:00 · FNB Stadium (Jhb) · Normal · "Setting up" · 9.00 h × R90,00 = R750,00 (payroll 2026-09-12). He now claims 15:00–20:00 · Music Bus (Thembisa) · Music Bus · "Missed shifts from Thursday doing music bus in Thembisa where there was a trade visit" · 5.00 h for the same day. Work type changed: Normal → Music Bus (rate R90,00 → R120,00). • Extra hours 16:00–20:00: 4.00 h → R480,00 Still due: R480,00 (full day 5.00 h at the correct rule = R1 230,00 − R750,00 already paid). Hours from Wednesday onwards are estimated for the auditor run; this entry corrects them. Bernie to approve — nothing has been changed. System recommended 4.00 h. | X44: #9972 DECIDED 4.00 h by Bernie Burness 2026-09-23 08:56: ALREADY BILLED Thursday 2026-09-17 · 07:00–16:00 · 9.00 h Normal · FNB Stadium · Setting up R750,00 · shift #9767 · PAID in payroll 2026-09-12 → 2026-09-18 (closed) | #10069 DECIDED 4.00 h by Bernie Burness 2026-09-23 09:03: Already paid — EXTRA HOURS — R480,00 still due — approved amount R480,00
A45: 9781 | B45: John Simbarashe Mhlanga | C45: 2026-09-21 | D45: Monday | F45: FNB Stadium | G45: Soweto jhb | H45: Strike down | I45: Normal | J45: 07:00 | K45: 16:00 | L45: 9 | M45: 0 | O45: =IF(N45<>"",N45,M45) | P45: 855 | R45: =IF(Q45<>"",Q45,IF(N45<>"",IF(M45>0,ROUND(P45*N45/M45,2),0),P45)) | S45: 95 | T45: OWNER CORRECTION: Owner 23 Sep: Mon 21 Sep FNB Stadium 07–16 — the ONE shift he worked; the second copy (#9857) is zeroed. 9 h × R95 = R855 | V45: #10131 | W45: #10131 ALREADY PAID — SAME SHIFT AGAIN (duplicate): John was paid Mon 21 Sep 2026 07:00–16:00 · FNB Stadium (Soweto jhb) · Normal · "Strike down" · 9.00 h × R95,00 = R855,00 (payroll 2026-09-19). He now claims 07:00–16:00 · FNB Stadium (Soweto jhb) · Normal · "Strike down" · 9.00 h for the same day. Every hour of this claim is already paid. Nothing is due: R0,00. Hours from Wednesday onwards are estimated for the auditor run; this entry corrects them. Bernie to approve — nothing has been changed. System recommended 0.00 h. | X45: #10131 DECIDED 0.00 h by Bernie Burness 2026-09-23 09:03: Already paid — SAME SHIFT AGAIN (duplicate) — R0,00 still due — approved amount R0,00
A46: 9857 | B46: John Simbarashe Mhlanga | C46: 2026-09-21 | D46: Monday | F46: FNB Stadium | G46: Soweto jhb | H46: Strike down | I46: Normal | J46: 07:00 | K46: 16:00 | L46: 9 | M46: 0 | O46: =IF(N46<>"",N46,M46) | P46: 0 | R46: =IF(Q46<>"",Q46,IF(N46<>"",IF(M46>0,ROUND(P46*N46/M46,2),0),P46)) | S46: 95 | T46: OWNER CORRECTION: Duplicate of #9781 (Mon 21 Sep FNB 07–16) — R0 | V46: #10126 | W46: #10072 ALREADY PAID — SAME SHIFT AGAIN (duplicate): John was paid Mon 21 Sep 2026 07:00–16:00 · FNB Stadium (Soweto jhb) · Normal · "Strike down" · 9.00 h × R95,00 = R855,00 (payroll 2026-09-19). He now claims 07:00–16:00 · FNB Stadium (Soweto jhb) · Normal · "Strike down" · 9.00 h for the same day. Every hour of this claim is already paid. Nothing is due: R0,00. Hours from Wednesday onwards are estimated for the auditor run; this entry corrects them. Bernie to approve — nothing has been changed. System recommended 0.00 h. | #10126 Manual overlap review: the same employee has another overlapping entry on 2026-09-21 for 07:00-16:00. | X46: #10072 DECIDED 0.00 h by Bernie Burness 2026-09-23 09:01: Already paid — SAME SHIFT AGAIN (duplicate) — R0,00 still due — approved amount R0,00 | #10126 DECIDED 0.00 h by Bernie Burness 2026-09-23 09:06: ALREADY BILLED Monday 2026-09-21 · 07:00–16:00 · 9.00 h Normal · FNB Stadium · Strike down R855,00 · shift #9857 · in THIS payroll (2026-09-19 → 2026-09-25, not yet paid)
A47: 9783 | B47: John Simbarashe Mhlanga | C47: 2026-09-22 | D47: Tuesday | F47: Warehouse | G47: Henly on klip meyerton | H47: Loading and cleaning the warehouse | I47: Normal | J47: 07:00 | K47: 16:00 | L47: 9 | M47: 9 | O47: =IF(N47<>"",N47,M47) | P47: 690.63 | R47: =IF(Q47<>"",Q47,IF(N47<>"",IF(M47>0,ROUND(P47*N47/M47,2),0),P47)) | S47: 81.25 | T47: Warehouse: 9 h − 0.5 h staff meeting 07:00–07:30 (unpaid, R40,63) = 8.5 h × R81,25 | V47: #9983
A48: 9845 | B48: John Simbarashe Mhlanga | C48: 2026-09-23 | D48: Wednesday | F48: Work with the Team | G48: Sandton | H48: Went to fetch prizes at waltloo depot in pretoria and went to assist the team in setting up Victor’s event | I48: Normal | J48: 07:00 | K48: 16:00 | L48: 9 | M48: 9 | O48: =IF(N48<>"",N48,M48) | P48: 855 | R48: =IF(Q48<>"",Q48,IF(N48<>"",IF(M48>0,ROUND(P48*N48/M48,2),0),P48)) | S48: 95 | T48: Venue/event: 9 h × R95
A49: 9846 | B49: John Simbarashe Mhlanga | C49: 2026-09-24 | D49: Thursday | F49: Warehouse | G49: Henly on klip meyerton | H49: Loading the trucks | I49: Normal | J49: 07:00 | K49: 12:00 | L49: 5 | M49: 5 | O49: =IF(N49<>"",N49,M49) | P49: 731.25 | R49: =IF(Q49<>"",Q49,IF(N49<>"",IF(M49>0,ROUND(P49*N49/M49,2),0),P49)) | S49: 162.5 | T49: Public holiday (Heritage Day) approved R731,25 by Bernie Burness (#10144) — Warehouse public holiday (Heritage Day): 5 h − 0.5 h staff meeting 07:00–07:30 (unpaid) = 4.5 h × R162,50 (R81,25 × 2) = R731,25 | V49: #10092 | W49: #10144 Public holiday (Heritage Day) — owner to approve or decline: PUBLIC HOLIDAY — Heritage Day (24 Sep 2026): John Simbarashe Mhlanga worked 07:00–12:00. Held for owner approval. | X49: #10144 DECIDED 4.50 h by Bernie Burness 2026-09-23 10:31: Public holiday (Heritage Day) approved by Bernie Burness 23 Sep at the holiday rate: Warehouse public holiday (Heritage Day): 5 h − 0.5 h staff meeting 07:00–07:30 (unpaid) = 4.5 h × R162,50 (R81,25 × 2) = R731,25
A50: 9847 | B50: John Simbarashe Mhlanga | C50: 2026-09-24 | D50: Thursday | F50: Music Bus | G50: Soweto | H50: Doing activations around Soweto area amd Randfontein | I50: Music Bus | J50: 12:00 | K50: 18:00 | L50: 6 | M50: 6 | O50: =IF(N50<>"",N50,M50) | P50: 1110 | R50: =IF(Q50<>"",Q50,IF(N50<>"",IF(M50>0,ROUND(P50*N50/M50,2),0),P50)) | S50: 180 | T50: Public holiday (Heritage Day) approved R1 110,00 by Bernie Burness (#10095) — Music Bus public holiday (Heritage Day): R750 fixed 07–16 + 2 h outside 07–16 × R180 = R1 110,00 | W50: #10095 Public holiday (Heritage Day) — owner to approve or decline: PUBLIC HOLIDAY — OWNER APPROVAL NEEDED: John Simbarashe Mhlanga worked 12:00–18:00 on 2026-09-24 (Heritage Day) at Music Bus (Music Bus). Public-holiday work is not paid automatically. Recommended: Music Bus public holiday (Heritage Day): R750 fixed 07–16 + 2 h outside 07–16 × R180 = R1 110,00. R0 is paid until the owner approves or declines. | X50: #10095 DECIDED 6.00 h by Bernie Burness 2026-09-23 09:05: Public holiday (Heritage Day) approved — R1 110,00 (as recommended)
A51: 9848 | B51: John Simbarashe Mhlanga | C51: 2026-09-25 | D51: Friday | F51: Warehouse | G51: Henly on klip | H51: Working with the team | I51: Normal | J51: 07:00 | K51: 11:00 | L51: 4 | M51: 4 | O51: =IF(N51<>"",N51,M51) | P51: 284.38 | R51: =IF(Q51<>"",Q51,IF(N51<>"",IF(M51>0,ROUND(P51*N51/M51,2),0),P51)) | S51: 81.25 | T51: Warehouse: 4 h − 0.5 h staff meeting 07:00–07:30 (unpaid, R40,63) = 3.5 h × R81,25 | V51: #10098
A52: 9849 | B52: John Simbarashe Mhlanga | C52: 2026-09-25 | D52: Friday | F52: Music Bus | G52: Soweto | H52: Music bus activations | I52: Music Bus | J52: 11:00 | K52: 21:00 | L52: 10 | M52: 10 | O52: =IF(N52<>"",N52,M52) | P52: 1350 | R52: =IF(Q52<>"",Q52,IF(N52<>"",IF(M52>0,ROUND(P52*N52/M52,2),0),P52)) | S52: 120 | T52: Music Bus: R750 fixed 07–16 + 5 h outside × R120
A53: 9852 | B53: Joshua Motsamai Nteo | C53: 2026-09-13 | D53: Sunday | E53: YES | F53: Pastdal pretoria | G53: Pretoria | H53: Break down | I53: Normal | J53: 07:00 | K53: 13:00 | L53: 6 | M53: 0 | O53: =IF(N53<>"",N53,M53) | P53: 0 | R53: =IF(Q53<>"",Q53,IF(N53<>"",IF(M53>0,ROUND(P53*N53/M53,2),0),P53)) | S53: 114 | T53: OWNER CORRECTION: Already paid last week (shift #9638 R720). R0. | V53: #10113 | W53: OVERLAP: already paid 07:00–13:00 (Pastdal pub, R720,00, payroll n/a) on this day. | #10109 Manual overlap review: the same employee has another overlapping entry on 2026-09-13 for 07:00-13:00. | #10113 ALREADY PAID — this claim is covered by what was paid: Joshua was paid Sun 13 Sep 2026 07:00–13:00 · Pastdal pub (Pretoria) · Normal · "Strikedown" · 6.00 h × R120,00 = R720,00 (payroll 2026-09-12). He now claims 07:00–13:00 · Pastdal pretoria (Pretoria) · Normal · "Break down" · 6.00 h for the same day. Same work type, but the rate paid (R120,00/h) differs from the rule (R114,00/h). • Rate correction on the paid hours 07:00–13:00: 6.00 h — worth R684,00 at the correct rule, R720,00 was paid → −R36,00 What was paid (R720,00) already covers this claim (R684,00 at the correct rule). Nothing more is due: R0,00. Hours from Wednesday onwards are estimated for the auditor run; this entry corrects them. Bernie to approve — nothing has been changed. System recommended 0.00 h. | X53: #10109 DECIDED 0.00 h by Bernie Burness 2026-09-23 09:08: ALREADY BILLED Sunday 2026-09-13 · 07:00–13:00 · 6.00 h Normal · Pastdal pub · Strikedown R720,00 · shift #9638 · PAID in payroll 2026-09-12 → 2026-09-18 (closed) | #10113 DECIDED 0.00 h by Bernie Burness 2026-09-23 09:21: Already paid — this claim is covered by what was paid — R0,00 still due — approved amount R0,00
A54: 9777 | B54: Joshua Motsamai Nteo | C54: 2026-09-17 | D54: Thursday | E54: YES | F54: Botanical gardens | G54: Pretoria | H54: Breakdown | I54: Normal | J54: 05:00 | K54: 07:00 | L54: 2 | M54: 2 | O54: =IF(N54<>"",N54,M54) | P54: 190 | R54: =IF(Q54<>"",Q54,IF(N54<>"",IF(M54>0,ROUND(P54*N54/M54,2),0),P54)) | S54: 95 | T54: Venue/event: 2 h × R95 | W54: CLEAR: worked 07:00–16:00 that day (paid in payroll n/a); these hours are outside those times. | X54: No review needed
A55: 9776 | B55: Joshua Motsamai Nteo | C55: 2026-09-17 | D55: Thursday | E55: YES | F55: Fnb stadium | G55: JHB | H55: Setup | I55: Normal | J55: 16:00 | K55: 18:30 | L55: 2.5 | M55: 2.5 | O55: =IF(N55<>"",N55,M55) | P55: 237.5 | R55: =IF(Q55<>"",Q55,IF(N55<>"",IF(M55>0,ROUND(P55*N55/M55,2),0),P55)) | S55: 95 | T55: Venue/event: 2.5 h × R95 | W55: CLEAR: worked 07:00–16:00 that day (paid in payroll n/a); these hours are outside those times. | X55: No review needed
A56: 9775 | B56: Joshua Motsamai Nteo | C56: 2026-09-21 | D56: Monday | F56: Fnb stadium | G56: JHB | H56: Breakdown/collection | I56: Normal | J56: 07:00 | K56: 16:00 | L56: 9 | M56: 9 | O56: =IF(N56<>"",N56,M56) | P56: 855 | R56: =IF(Q56<>"",Q56,IF(N56<>"",IF(M56>0,ROUND(P56*N56/M56,2),0),P56)) | S56: 95 | T56: Venue/event: 9 h × R95
A57: 9774 | B57: Joshua Motsamai Nteo | C57: 2026-09-22 | D57: Tuesday | F57: Warehouse | G57: Meyerton | H57: Loading for events | I57: Normal | J57: 07:00 | K57: 16:00 | L57: 9 | M57: 9 | O57: =IF(N57<>"",N57,M57) | P57: 690.63 | R57: =IF(Q57<>"",Q57,IF(N57<>"",IF(M57>0,ROUND(P57*N57/M57,2),0),P57)) | S57: 81.25 | T57: Warehouse: 9 h − 0.5 h staff meeting 07:00–07:30 (unpaid, R40,63) = 8.5 h × R81,25 | V57: #9959
A58: 9778 | B58: Joshua Motsamai Nteo | C58: 2026-09-23 | D58: Wednesday | F58: Warehouse | G58: Meyerton | H58: Cleaning warehouse | I58: Normal | J58: 07:00 | K58: 16:00 | L58: 9 | M58: 9 | O58: =IF(N58<>"",N58,M58) | P58: 690.63 | R58: =IF(Q58<>"",Q58,IF(N58<>"",IF(M58>0,ROUND(P58*N58/M58,2),0),P58)) | S58: 81.25 | T58: Warehouse: 9 h − 0.5 h staff meeting 07:00–07:30 (unpaid, R40,63) = 8.5 h × R81,25 | V58: #9964
A59: 9853 | B59: Joshua Motsamai Nteo | C59: 2026-09-23 | D59: Wednesday | F59: Warehouse | G59: Meyerton | H59: Cleaning warehouse | I59: Normal | J59: 07:00 | K59: 16:00 | L59: 9 | M59: 0 | O59: =IF(N59<>"",N59,M59) | P59: 0 | R59: =IF(Q59<>"",Q59,IF(N59<>"",IF(M59>0,ROUND(P59*N59/M59,2),0),P59)) | S59: 81.25 | T59: OWNER CORRECTION: Duplicate of #9778 — R0. | V59: #10110 | W59: #10110 Manual overlap review: the same employee has another overlapping entry on 2026-09-23 for 07:00-16:00. | X59: #10110 DECIDED 0.00 h by Bernie Burness 2026-09-23 09:20: already billed
A60: 9780 | B60: Joshua Motsamai Nteo | C60: 2026-09-24 | D60: Thursday | F60: Warehouse | G60: Meyerton | H60: Cleaning warehouse | I60: Warehouse Team | J60: 07:00 | K60: 15:00 | L60: 8 | M60: 8 | O60: =IF(N60<>"",N60,M60) | P60: 1218.75 | R60: =IF(Q60<>"",Q60,IF(N60<>"",IF(M60>0,ROUND(P60*N60/M60,2),0),P60)) | S60: 162.5 | T60: OWNER CORRECTION: Owner 23 Sep: Heritage Day — warehouse, hours set to 07:00–15:00 (no set-ups). 7.5 h × R162,50 = R1218.75 | V60: #9977 | W60: #10135 Public holiday (Heritage Day) — owner to approve or decline: PUBLIC HOLIDAY — Heritage Day (24 Sep 2026): Joshua Motsamai Nteo worked 07:00–16:00 at Warehouse (Meyerton), Cleaning warehouse. Held for owner approval. | X60: #10135 DECIDED 7.50 h by Bernie Burness 2026-09-23 10:29: Public holiday (Heritage Day) approved by Bernie Burness 23 Sep — hours set to 07:00–15:00 (no set-ups): Warehouse public holiday (Heritage Day), owner set hours 07:00–15:00: 8.0 h − 0.5 h staff meeting 07:00–07:30 (unpaid) = 7.5 h × R162,50 (R81,25 × 2) = R1218.75
A61: 9782 | B61: Joshua Motsamai Nteo | C61: 2026-09-25 | D61: Friday | F61: Capital hotel / botanical gardens JHB | G61: Sandton / JHB | H61: Setup for events | I61: Normal | J61: 07:00 | K61: 16:00 | L61: 9 | M61: 9 | O61: =IF(N61<>"",N61,M61) | P61: 855 | R61: =IF(Q61<>"",Q61,IF(N61<>"",IF(M61>0,ROUND(P61*N61/M61,2),0),P61)) | S61: 95 | T61: Venue/event: 9 h × R95
A62: 9861 | B62: Lebo Lebo | C62: 2026-09-24 | D62: Thursday | F62: Warehouse | G62: Highbury | H62: Offloading + Loading | I62: Normal | J62: 07:00 | K62: 13:25 | L62: 6.42 | M62: 6.42 | O62: =IF(N62<>"",N62,M62) | P62: 0 | R62: =IF(Q62<>"",Q62,IF(N62<>"",IF(M62>0,ROUND(P62*N62/M62,2),0),P62)) | S62: 190 | T62: PUBLIC HOLIDAY — HELD for owner approval — recommended Venue/event public holiday (Heritage Day): 6.42 h × R190 (R95 × 2) = R1 219,17; R0 until approved | V62: #10149
A63: 9862 | B63: Lebo Lebo | C63: 2026-09-25 | D63: Friday | F63: Riverside sun + stonehaven + amstel arena | G63: Vanderbiljpark + Soweto | H63: Collections + drop off | I63: Normal | J63: 07:00 | K63: 16:00 | L63: 9 | M63: 9 | O63: =IF(N63<>"",N63,M63) | P63: 855 | R63: =IF(Q63<>"",Q63,IF(N63<>"",IF(M63>0,ROUND(P63*N63/M63,2),0),P63)) | S63: 95 | T63: Venue/event: 9 h × R95
A64: 9770 | B64: Patrick Ngozo | C64: 2026-09-16 | D64: Wednesday | E64: YES | F64: Parys | G64: Free state | H64: Golf day Set up | I64: Normal | J64: 16:00 | K64: 18:00 | L64: 2 | M64: 2 | O64: =IF(N64<>"",N64,M64) | P64: 190 | R64: =IF(Q64<>"",Q64,IF(N64<>"",IF(M64>0,ROUND(P64*N64/M64,2),0),P64)) | S64: 95 | T64: Venue/event: 2 h × R95 | W64: CLEAR: worked 06:30–16:00 that day (paid in payroll n/a); these hours are outside those times. | X64: No review needed
A65: 9771 | B65: Patrick Ngozo | C65: 2026-09-17 | D65: Thursday | E65: YES | F65: Parys | G65: Free state | H65: Golf day set up | I65: Normal | J65: 06:00 | K65: 07:00 | L65: 1 | M65: 1 | O65: =IF(N65<>"",N65,M65) | P65: 95 | R65: =IF(Q65<>"",Q65,IF(N65<>"",IF(M65>0,ROUND(P65*N65/M65,2),0),P65)) | S65: 95 | T65: Venue/event: 1 h × R95 | W65: CLEAR: worked 07:00–16:00 that day (paid in payroll n/a); these hours are outside those times. | X65: No review needed
A66: 9772 | B66: Patrick Ngozo | C66: 2026-09-17 | D66: Thursday | E66: YES | F66: Parys | G66: Free state | H66: Breakdown | I66: Normal | J66: 16:00 | K66: 20:00 | L66: 4 | M66: 4 | O66: =IF(N66<>"",N66,M66) | P66: 380 | R66: =IF(Q66<>"",Q66,IF(N66<>"",IF(M66>0,ROUND(P66*N66/M66,2),0),P66)) | S66: 95 | T66: Venue/event: 4 h × R95 | W66: CLEAR: worked 07:00–16:00 that day (paid in payroll n/a); these hours are outside those times. | X66: No review needed
A67: 9769 | B67: Patrick Ngozo | C67: 2026-09-21 | D67: Monday | F67: FNB Stadium | G67: Johannesburg | H67: Breakdown | I67: Normal | J67: 06:30 | K67: 16:00 | L67: 9.5 | M67: 9.5 | O67: =IF(N67<>"",N67,M67) | P67: 902.5 | R67: =IF(Q67<>"",Q67,IF(N67<>"",IF(M67>0,ROUND(P67*N67/M67,2),0),P67)) | S67: 95 | T67: Venue/event: 9.5 h × R95
A68: 9773 | B68: Patrick Ngozo | C68: 2026-09-22 | D68: Tuesday | F68: Wearhouse | G68: Meyerton | H68: Loading | I68: Normal | J68: 06:30 | K68: 16:00 | L68: 9.5 | M68: 9.5 | O68: =IF(N68<>"",N68,M68) | P68: 731.25 | R68: =IF(Q68<>"",Q68,IF(N68<>"",IF(M68>0,ROUND(P68*N68/M68,2),0),P68)) | S68: 81.25 | T68: Warehouse: 9.5 h − 0.5 h staff meeting 07:00–07:30 (unpaid, R40,63) = 9 h × R81,25 | V68: #9954
A69: 9837 | B69: Patrick Ngozo | C69: 2026-09-23 | D69: Wednesday | F69: Vaal Boating Season | G69: Vereeniging | H69: Set up | I69: Normal | J69: 06:30 | K69: 16:00 | L69: 9.5 | M69: 9.5 | O69: =IF(N69<>"",N69,M69) | P69: 902.5 | R69: =IF(Q69<>"",Q69,IF(N69<>"",IF(M69>0,ROUND(P69*N69/M69,2),0),P69)) | S69: 95 | T69: Venue/event: 9.5 h × R95
A70: 9838 | B70: Patrick Ngozo | C70: 2026-09-24 | D70: Thursday | F70: Wearhouse | G70: Meyerton | H70: Loading | I70: Warehouse Team | J70: 06:30 | K70: 15:00 | L70: 8.5 | M70: 8.5 | O70: =IF(N70<>"",N70,M70) | P70: 1300 | R70: =IF(Q70<>"",Q70,IF(N70<>"",IF(M70>0,ROUND(P70*N70/M70,2),0),P70)) | S70: 162.5 | T70: OWNER CORRECTION: Owner 23 Sep: Heritage Day — warehouse, hours set to 06:30–15:00 (no set-ups). 8 h × R162,50 = R1300 | W70: #10143 Public holiday (Heritage Day) — owner to approve or decline: PUBLIC HOLIDAY — Heritage Day (24 Sep 2026): Patrick Ngozo worked 06:30–15:00. Held for owner approval. | X70: #10143 DECIDED 8.00 h by Bernie Burness 2026-09-23 10:30: Public holiday (Heritage Day) approved by Bernie Burness 23 Sep at the holiday rate: Warehouse public holiday (Heritage Day), owner set hours 06:30–15:00: 8.5 h − 0.5 h staff meeting = 8 h × R162,50 = R1 300,00
A71: 9839 | B71: Patrick Ngozo | C71: 2026-09-25 | D71: Friday | F71: Pretoria Country Club | G71: Pretoria | H71: Set up Golf ⛳️ course | I71: Normal | J71: 06:30 | K71: 16:00 | L71: 9.5 | M71: 9.5 | O71: =IF(N71<>"",N71,M71) | P71: 902.5 | R71: =IF(Q71<>"",Q71,IF(N71<>"",IF(M71>0,ROUND(P71*N71/M71,2),0),P71)) | S71: 95 | T71: Venue/event: 9.5 h × R95
A72: 9831 | B72: Solomon Moyo | C72: 2026-09-16 | D72: Wednesday | E72: YES | F72: Parys Country Club | G72: Free State | H72: Set up | I72: Normal | J72: 16:00 | K72: 18:00 | L72: 2 | M72: 2 | O72: =IF(N72<>"",N72,M72) | P72: 190 | R72: =IF(Q72<>"",Q72,IF(N72<>"",IF(M72>0,ROUND(P72*N72/M72,2),0),P72)) | S72: 95 | T72: Venue/event: 2 h × R95 | W72: CLEAR: worked 07:00–16:00 that day (paid in payroll n/a); these hours are outside those times. | X72: No review needed
A73: 9830 | B73: Solomon Moyo | C73: 2026-09-17 | D73: Thursday | E73: YES | F73: Parys Country Club | G73: Free State | H73: Breakdown | I73: Normal | J73: 16:00 | K73: 21:00 | L73: 5 | M73: 5 | O73: =IF(N73<>"",N73,M73) | P73: 475 | R73: =IF(Q73<>"",Q73,IF(N73<>"",IF(M73>0,ROUND(P73*N73/M73,2),0),P73)) | S73: 95 | T73: Venue/event: 5 h × R95 | W73: CLEAR: worked 07:00–16:00 that day (paid in payroll n/a); these hours are outside those times. | X73: No review needed
A74: 9836 | B74: Solomon Moyo | C74: 2026-09-21 | D74: Monday | F74: FNB Stadium | G74: Johannesburg | H74: Breakdown | I74: Normal | J74: 07:00 | K74: 16:00 | L74: 9 | M74: 9 | O74: =IF(N74<>"",N74,M74) | P74: 855 | R74: =IF(Q74<>"",Q74,IF(N74<>"",IF(M74>0,ROUND(P74*N74/M74,2),0),P74)) | S74: 95 | T74: Venue/event: 9 h × R95
A75: 9835 | B75: Solomon Moyo | C75: 2026-09-22 | D75: Tuesday | F75: Warehouse | G75: Midvaal | H75: Loading | I75: Normal | J75: 07:00 | K75: 16:00 | L75: 9 | M75: 9 | O75: =IF(N75<>"",N75,M75) | P75: 690.63 | R75: =IF(Q75<>"",Q75,IF(N75<>"",IF(M75>0,ROUND(P75*N75/M75,2),0),P75)) | S75: 81.25 | T75: Warehouse: 9 h − 0.5 h staff meeting 07:00–07:30 (unpaid, R40,63) = 8.5 h × R81,25 | V75: #10063
A76: 9834 | B76: Solomon Moyo | C76: 2026-09-23 | D76: Wednesday | F76: Riverside sun | G76: Vanderbijlpark | H76: Set up | I76: Normal | J76: 07:00 | K76: 16:00 | L76: 9 | M76: 9 | O76: =IF(N76<>"",N76,M76) | P76: 855 | R76: =IF(Q76<>"",Q76,IF(N76<>"",IF(M76>0,ROUND(P76*N76/M76,2),0),P76)) | S76: 95 | T76: Venue/event: 9 h × R95
A77: 9833 | B77: Solomon Moyo | C77: 2026-09-24 | D77: Thursday | F77: Warehouse | G77: Johannesburg | H77: Set up | I77: Warehouse Team | J77: 07:00 | K77: 15:00 | L77: 8 | M77: 8 | O77: =IF(N77<>"",N77,M77) | P77: 1218.75 | R77: =IF(Q77<>"",Q77,IF(N77<>"",IF(M77>0,ROUND(P77*N77/M77,2),0),P77)) | S77: 162.5 | T77: OWNER CORRECTION: Owner 23 Sep: Heritage Day — whole crew in the warehouse 07:00–15:00 (worker wrote Botanical Gardens, 16:00). 7.5 h × R162,50 = R1 218,75 | W77: #10060 Public holiday (Heritage Day) — owner to approve or decline: PUBLIC HOLIDAY — OWNER APPROVAL NEEDED: Solomon Moyo worked 07:00–16:00 on 2026-09-24 (Heritage Day) at Botanical Gardens (Normal). Public-holiday work is not paid automatically. Recommended: Venue/event public holiday (Heritage Day): 9 h × R190 (R95 × 2) = R1 710,00. R0 is paid until the owner approves or declines. | X77: #10060 DECIDED 7.50 h by Bernie Burness 2026-09-23 10:31: Public holiday (Heritage Day) approved by Bernie Burness 23 Sep — warehouse, hours set to 07:00–15:00 (worker wrote Botanical Gardens until 16:00): Warehouse public holiday (Heritage Day), owner set hours 07:00–15:00: 8 h − 0.5 h staff meeting 07:00–07:30 (unpaid) = 7.5 h × R162,50 (R81,25 × 2) = R1 218,75
A78: 9832 | B78: Solomon Moyo | C78: 2026-09-25 | D78: Friday | F78: Riverside sun | G78: Vanderbijlpark | H78: Breakdown | I78: Normal | J78: 07:00 | K78: 16:00 | L78: 9 | M78: 9 | O78: =IF(N78<>"",N78,M78) | P78: 855 | R78: =IF(Q78<>"",Q78,IF(N78<>"",IF(M78>0,ROUND(P78*N78/M78,2),0),P78)) | S78: 95 | T78: Venue/event: 9 h × R95
A79: 9815 | B79: Takavaudza Chokuda | C79: 2026-09-17 | D79: Thursday | E79: YES | F79: FNB | G79: Johannesburg | H79: Set up | I79: Warehouse Team | J79: 16:00 | K79: 18:00 | L79: 2 | M79: 2 | O79: =IF(N79<>"",N79,M79) | P79: 190 | R79: =IF(Q79<>"",Q79,IF(N79<>"",IF(M79>0,ROUND(P79*N79/M79,2),0),P79)) | S79: 95 | T79: Venue/event: 2 h × R95 | W79: CLEAR: worked 07:00–16:00 that day (paid in payroll n/a); these hours are outside those times. | #10074 Warehouse claimed — but the entry names “Johannesburg”: WAREHOUSE CLAIMED BUT THE ENTRY NAMES “Johannesburg”: Takavaudza Chokuda selected Warehouse Team at “FNB” for 2.00 h on Thu 17 Sep 2026, but wrote “Johannesburg” — that is a venue, not the warehouse. 6 workers were at a venue that day (Additional 5 hour shift - 17/09/2026 Parys Golf Day, Botanical garden Pretoria, FNB Stadium, Parys golf & country Estate, Parys Country Club, Parys, Botanical gardens, Fnb stadium). If he was at “Johannesburg”, he is due the venue rate (R95/h); if he was really in the warehouse, R81,25/h. Choose below. | X79: #10074 DECIDED by Bernie Burness 2026-09-23 11:01: Event/Venue rate chosen — shift #9815 R162,50 → R190,00 (Venue/event: 2 h × R95)
A80: 9821 | B80: Takavaudza Chokuda | C80: 2026-09-20 | D80: Sunday | F80: House | G80: henley | H80: Installing lights and garden work | I80: House/Garden | J80: 08:00 | K80: 14:00 | L80: 6 | M80: 6 | O80: =IF(N80<>"",N80,M80) | P80: 450 | R80: =IF(Q80<>"",Q80,IF(N80<>"",IF(M80>0,ROUND(P80*N80/M80,2),0),P80)) | S80: 75 | T80: OWNER CORRECTION: Owner 24 Sep: Sunday house work 08:00–14:00 = 6 h × R62,50 × 1.2 (Sunday) = 6 h × R75 = R450,00 (was R375 — Sunday ×1.2 had been left off)
A81: 9816 | B81: Takavaudza Chokuda | C81: 2026-09-21 | D81: Monday | F81: Warehouse | G81: Henley-onklip | H81: Fixing equipment | I81: Warehouse Team | J81: 07:00 | K81: 16:00 | L81: 9 | M81: 9 | O81: =IF(N81<>"",N81,M81) | P81: 690.63 | R81: =IF(Q81<>"",Q81,IF(N81<>"",IF(M81>0,ROUND(P81*N81/M81,2),0),P81)) | S81: 81.25 | T81: Warehouse: 9 h − 0.5 h staff meeting 07:00–07:30 (unpaid, R40,63) = 8.5 h × R81,25 | W81: #9955 Crew pattern — 8 of 9 at a venue, this one says Warehouse: CREW PATTERN: 8 of 9 workers were at a venue on Mon 21 Sep 2026 (FNB Stadium, FNB strike down, Fnb stadium) — Takavaudza Chokuda says Warehouse for 9.00 h. Check he was not at the venue (R95/h would be due). | X81: #9955 DECIDED 9.00 h by Bernie Burness 2026-09-23 11:01: WAREHOUSE — R81,25/h chosen by Bernie Burness for draft #830 — will pay R690,63 when final-submitted (Warehouse: 9 h − 0.5 h staff meeting 07:00–07:30 (unpaid, R40,63) = 8.5 h × R81,25)
A82: 9820 | B82: Takavaudza Chokuda | C82: 2026-09-22 | D82: Tuesday | F82: Warehouse | G82: Henley-onklip | H82: Normal | I82: Warehouse Team | J82: 07:00 | K82: 16:00 | L82: 9 | M82: 9 | O82: =IF(N82<>"",N82,M82) | P82: 690.63 | R82: =IF(Q82<>"",Q82,IF(N82<>"",IF(M82>0,ROUND(P82*N82/M82,2),0),P82)) | S82: 81.25 | T82: Warehouse: 9 h − 0.5 h staff meeting 07:00–07:30 (unpaid, R40,63) = 8.5 h × R81,25
A83: 9819 | B83: Takavaudza Chokuda | C83: 2026-09-23 | D83: Wednesday | F83: Riverside | G83: The vaal | H83: Set up | I83: Warehouse Team | J83: 07:00 | K83: 16:00 | L83: 9 | M83: 9 | O83: =IF(N83<>"",N83,M83) | P83: 855 | R83: =IF(Q83<>"",Q83,IF(N83<>"",IF(M83>0,ROUND(P83*N83/M83,2),0),P83)) | S83: 95 | T83: Venue/event: 9 h × R95 | W83: #10075 Warehouse claimed — but the entry names “The vaal”: WAREHOUSE CLAIMED BUT THE ENTRY NAMES “The vaal”: Takavaudza Chokuda selected Warehouse Team at “Riverside” for 9.00 h on Wed 23 Sep 2026, but wrote “The vaal” — that is a venue, not the warehouse. 6 workers were at a venue that day (Work with the Team, wharehouse, Set up vaal Boating, Riverside sun, Vaal Boating Season, Stone Haven And Riverside Sun). If he was at “The vaal”, he is due the venue rate (R95/h); if he was really in the warehouse, R81,25/h. Choose below. | X83: #10075 DECIDED by Bernie Burness 2026-09-23 11:01: Event/Venue rate chosen — shift #9819 R690,63 → R855,00 (Venue/event: 9 h × R95)
A84: 9818 | B84: Takavaudza Chokuda | C84: 2026-09-24 | D84: Thursday | F84: Warehouse | G84: Henley-onklip | H84: Normal | I84: Warehouse Team | J84: 07:00 | K84: 15:00 | L84: 8 | M84: 8 | O84: =IF(N84<>"",N84,M84) | P84: 1218.75 | R84: =IF(Q84<>"",Q84,IF(N84<>"",IF(M84>0,ROUND(P84*N84/M84,2),0),P84)) | S84: 162.5 | T84: OWNER CORRECTION: Owner 23 Sep: Heritage Day — warehouse, hours set to 07:00–15:00 (no set-ups). 7.5 h × R162,50 = R1218.75 | W84: #10039 Public holiday (Heritage Day) — owner to approve or decline: PUBLIC HOLIDAY — OWNER APPROVAL NEEDED: Takavaudza Chokuda worked 07:00–16:00 on 2026-09-24 (Heritage Day) at Warehouse (Warehouse Team). Public-holiday work is not paid automatically. Recommended: Warehouse public holiday (Heritage Day): 9 h × R162,50 (R81,25 × 2, no meeting deduction) = R1 462,50. R0 is paid until the owner approves or declines. | X84: #10039 DECIDED 7.50 h by Bernie Burness 2026-09-23 10:32: Public holiday (Heritage Day) approved by Bernie Burness 23 Sep — hours set to 07:00–15:00 (no set-ups): Warehouse public holiday (Heritage Day), owner set hours 07:00–15:00: 8.0 h − 0.5 h staff meeting 07:00–07:30 (unpaid) = 7.5 h × R162,50 (R81,25 × 2) = R1218.75
A85: 9817 | B85: Takavaudza Chokuda | C85: 2026-09-25 | D85: Friday | F85: Warehouse | G85: Henley-onklip | H85: Normal | I85: Warehouse Team | J85: 07:00 | K85: 16:00 | L85: 9 | M85: 9 | O85: =IF(N85<>"",N85,M85) | P85: 690.63 | R85: =IF(Q85<>"",Q85,IF(N85<>"",IF(M85>0,ROUND(P85*N85/M85,2),0),P85)) | S85: 81.25 | T85: Warehouse: 9 h − 0.5 h staff meeting 07:00–07:30 (unpaid, R40,63) = 8.5 h × R81,25 | W85: #10076 Crew pattern — 7 of 8 at a venue, this one says Warehouse: CREW PATTERN: 7 of 8 workers were at a venue on Fri 25 Sep 2026 (The Capital Sandton and Bonitical Emmarentia, Pretoria country club, Botanical, Vaal Boating, Riverside sun, Pretoria Country Club, Capital hotel / botanical gardens JHB) — Takavaudza Chokuda says Warehouse for 9.00 h. Check he was not at the venue (R95/h would be due). | X85: #10076 DECIDED by Bernie Burness 2026-09-23 11:01: Warehouse rate chosen — shift #9817 R690,63 → R690,63 (Warehouse: 9 h − 0.5 h staff meeting 07:00–07:30 (unpaid, R40,63) = 8.5 h × R81,25)
A86: 9840 | B86: Thandanani Nkala | C86: 2026-09-21 | D86: Monday | F86: FNB Stadium and Warehouse | G86: Johannesburg / Highbury | H86: Scorpion Kings Strike Down and Offloading | I86: Normal | J86: 07:00 | K86: 16:00 | L86: 9 | M86: 9 | O86: =IF(N86<>"",N86,M86) | P86: 855 | R86: =IF(Q86<>"",Q86,IF(N86<>"",IF(M86>0,ROUND(P86*N86/M86,2),0),P86)) | S86: 95 | T86: Venue/event: 9 h × R95 | V86: #10080
A87: 9844 | B87: Thandanani Nkala | C87: 2026-09-22 | D87: Tuesday | F87: Warehouse | G87: Highbury | H87: Offloading ,Loading and Cleaning | I87: Normal | J87: 07:00 | K87: 16:00 | L87: 9 | M87: 9 | O87: =IF(N87<>"",N87,M87) | P87: 690.63 | R87: =IF(Q87<>"",Q87,IF(N87<>"",IF(M87>0,ROUND(P87*N87/M87,2),0),P87)) | S87: 81.25 | T87: Warehouse: 9 h − 0.5 h staff meeting 07:00–07:30 (unpaid, R40,63) = 8.5 h × R81,25 | V87: #10087
A88: 9843 | B88: Thandanani Nkala | C88: 2026-09-23 | D88: Wednesday | F88: Stone Haven And Riverside Sun | G88: Vanderbijlpark Vaal | H88: Set Up Castle Lager | I88: Normal | J88: 07:00 | K88: 16:00 | L88: 9 | M88: 9 | O88: =IF(N88<>"",N88,M88) | P88: 855 | R88: =IF(Q88<>"",Q88,IF(N88<>"",IF(M88>0,ROUND(P88*N88/M88,2),0),P88)) | S88: 95 | T88: Venue/event: 9 h × R95
A89: 9842 | B89: Thandanani Nkala | C89: 2026-09-24 | D89: Thursday | F89: Warehouse | G89: Highbury | H89: Offloading and Loading | I89: Warehouse Team | J89: 07:00 | K89: 15:00 | L89: 8 | M89: 8 | O89: =IF(N89<>"",N89,M89) | P89: 1218.75 | R89: =IF(Q89<>"",Q89,IF(N89<>"",IF(M89>0,ROUND(P89*N89/M89,2),0),P89)) | S89: 162.5 | T89: OWNER CORRECTION: Owner 23 Sep: Heritage Day — warehouse, hours set to 07:00–15:00 (no set-ups). 7.5 h × R162,50 = R1218.75 | V89: #10084 | W89: #10142 Public holiday (Heritage Day) — owner to approve or decline: PUBLIC HOLIDAY — Heritage Day (24 Sep 2026): Thandanani Nkala worked 07:00–15:00. Held for owner approval. | X89: #10142 DECIDED 7.50 h by Bernie Burness 2026-09-23 10:32: Public holiday (Heritage Day) approved by Bernie Burness 23 Sep — hours set to 07:00–15:00 (no set-ups): Warehouse public holiday (Heritage Day), owner set hours 07:00–15:00: 8.0 h − 0.5 h staff meeting 07:00–07:30 (unpaid) = 7.5 h × R162,50 (R81,25 × 2) = R1218.75
A90: 9841 | B90: Thandanani Nkala | C90: 2026-09-25 | D90: Friday | F90: Warehouse | G90: Highbury | H90: Offloading and Loading | I90: Normal | J90: 07:00 | K90: 16:00 | L90: 9 | M90: 9 | O90: =IF(N90<>"",N90,M90) | P90: 690.63 | R90: =IF(Q90<>"",Q90,IF(N90<>"",IF(M90>0,ROUND(P90*N90/M90,2),0),P90)) | S90: 81.25 | T90: Warehouse: 9 h − 0.5 h staff meeting 07:00–07:30 (unpaid, R40,63) = 8.5 h × R81,25 | V90: #10082
A91: 9796 | B91: Thina Dyani | C91: 2026-09-17 | D91: Thursday | E91: YES | F91: Additional 5 hour shift - 17/09/2026 Parys Golf Day | G91: Parys | H91: Strike down | I91: Normal | J91: 16:00 | K91: 21:00 | L91: 5 | M91: 5 | O91: =IF(N91<>"",N91,M91) | P91: 475 | R91: =IF(Q91<>"",Q91,IF(N91<>"",IF(M91>0,ROUND(P91*N91/M91,2),0),P91)) | S91: 95 | T91: Venue/event: 5 h × R95 | W91: CLEAR: nothing else paid for this day. | X91: No review needed
A92: 9802 | B92: Tsotlego Petrus Malakoane | C92: 2026-09-19 | D92: Saturday | F92: Warehouse | G92: Henley on klip | H92: Cleaning and re-packing | I92: Normal | J92: 06:45 | K92: 12:00 | L92: 5.25 | M92: 5.25 | O92: =IF(N92<>"",N92,M92) | P92: 640 | R92: =IF(Q92<>"",Q92,IF(N92<>"",IF(M92>0,ROUND(P92*N92/M92,2),0),P92)) | S92: 80 | T92: Petrus Saturday: R640 set day rate (06–16)
A93: 9803 | B93: Tsotlego Petrus Malakoane | C93: 2026-09-21 | D93: Monday | F93: Warehouse | G93: Henley on klip | H93: Loading, offloading & recieving | I93: Warehouse Team | J93: 06:30 | K93: 16:00 | L93: 9.5 | M93: 9.5 | O93: =IF(N93<>"",N93,M93) | P93: 640 | R93: =IF(Q93<>"",Q93,IF(N93<>"",IF(M93>0,ROUND(P93*N93/M93,2),0),P93)) | S93: 55 | T93: Petrus weekday: R640 set day rate (06–16)
A94: 9804 | B94: Tsotlego Petrus Malakoane | C94: 2026-09-22 | D94: Tuesday | F94: Warehouse | G94: Henley on klip | H94: Loading, washing of Gazebos and recieving | I94: Warehouse Team | J94: 06:30 | K94: 16:00 | L94: 9.5 | M94: 9.5 | O94: =IF(N94<>"",N94,M94) | P94: 640 | R94: =IF(Q94<>"",Q94,IF(N94<>"",IF(M94>0,ROUND(P94*N94/M94,2),0),P94)) | S94: 55 | T94: Petrus weekday: R640 set day rate (06–16)
A95: 9810 | B95: Tsotlego Petrus Malakoane | C95: 2026-09-23 | D95: Wednesday | F95: Warehouse | G95: Henley on klip | H95: Packing & Loading and re-packing | I95: Normal | J95: 06:30 | K95: 16:00 | L95: 9.5 | M95: 9.5 | O95: =IF(N95<>"",N95,M95) | P95: 640 | R95: =IF(Q95<>"",Q95,IF(N95<>"",IF(M95>0,ROUND(P95*N95/M95,2),0),P95)) | S95: 55 | T95: Petrus weekday: R640 set day rate (06–16)
A96: 9813 | B96: Tsotlego Petrus Malakoane | C96: 2026-09-24 | D96: Thursday | F96: Warehouse | G96: Henley on klip | H96: Cleaning & repacking | I96: Normal | J96: 06:30 | K96: 14:00 | L96: 7.5 | M96: 7.5 | O96: =IF(N96<>"",N96,M96) | P96: 1120 | R96: =IF(Q96<>"",Q96,IF(N96<>"",IF(M96>0,ROUND(P96*N96/M96,2),0),P96)) | S96: 160 | T96: OWNER CORRECTION: Owner 23 Sep: Heritage Day hours set to 06:30–14:00 (owner: worked till about 14:00 — TRIPLE-CHECK next week). 7.5 h − 0.5 h meeting = 7 h × R160 = R1 120 | W96: #10033 Public holiday (Heritage Day) — owner to approve or decline: PUBLIC HOLIDAY — OWNER APPROVAL NEEDED: Tsotlego Petrus Malakoane worked 06:30–16:00 on 2026-09-24 (Heritage Day) at Warehouse (Normal). Public-holiday work is not paid automatically. Recommended: Petrus public holiday (Heritage Day): no fixed day — 9.5 h × R160 (R80 × 2) = R1 520,00. R0 is paid until the owner approves or declines. | X96: #10033 DECIDED 7.00 h by Bernie Burness 2026-09-23 11:02: Public holiday (Heritage Day) approved by Bernie Burness 23 Sep — hours set to 06:30–14:00, meeting deducted: 7 h × R160 = R1 120,00. Owner not 100% sure of the end time — CONFIRM NEXT WEEK.
A97: 9814 | B97: Tsotlego Petrus Malakoane | C97: 2026-09-25 | D97: Friday | F97: Warehouse | G97: Henley on klip | H97: Dispatch of a collection for a client | I97: Normal | J97: 06:30 | K97: 16:00 | L97: 9.5 | M97: 9.5 | O97: =IF(N97<>"",N97,M97) | P97: 640 | R97: =IF(Q97<>"",Q97,IF(N97<>"",IF(M97>0,ROUND(P97*N97/M97,2),0),P97)) | S97: 55 | T97: Petrus weekday: R640 set day rate (06–16)
A99: GRAND TOTAL | L99: =SUM(L5:L97) | M99: =SUM(M5:M97) | O99: =SUM(O5:O97) | P99: =SUM(P5:P97) | R99: =SUM(R5:R97)

Sheet Auditor Trail Linked
A1: Employee | B1: 1 Sat | D1: 2 Sun | F1: 3 Mon | H1: 4 Tue | J1: 5 Wed | L1: 6 Thu | N1: 7 Fri | P1: 6 MISSED SHIFTS | R1: Total Hours (Sat–Fri + Missed) | S1: Wages (linked) | T1: Fixed Deductions Due | U1: Fixed Deducted (edit) | V1: Fixed Outstanding After Payroll | W1: Additional Loan Due | X1: Additional Loan Deducted (edit) | Y1: Additional Loan Outstanding After Payroll | Z1: Total Deducted This Period | AA1: NET WAGE
B2: 2026-09-19 | D2: 2026-09-20 | F2: 2026-09-21 | H2: 2026-09-22 | J2: 2026-09-23 | L2: 2026-09-24 | N2: 2026-09-25 | P2: previous payroll, approved
B3: HR | C3: Amount | D3: HR | E3: Amount | F3: HR | G3: Amount | H3: HR | I3: Amount | J3: HR | K3: Amount | L3: HR | M3: Amount | N3: HR | O3: Amount | P3: HR | Q3: Amount
A4: Bhekizitha Maphosa | B4: =SUMIFS('Wage Detail Linked'!$O$5:$O$97,'Wage Detail Linked'!$B$5:$B$97,$A4,'Wage Detail Linked'!$C$5:$C$97,B$2,'Wage Detail Linked'!$E$5:$E$97,"") | C4: =IF(SUMIFS('Wage Detail Linked'!$O$5:$O$97,'Wage Detail Linked'!$B$5:$B$97,$A4,'Wage Detail Linked'!$C$5:$C$97,B$2,'Wage Detail Linked'!$E$5:$E$97,"")=0,IF(B4>0,ROUND(B4*90,2),0),ROUND(SUMIFS('Wage Detail Linked'!$R$5:$R$97,'Wage Detail Linked'!$B$5:$B$97,$A4,'Wage Detail Linked'!$C$5:$C$97,B$2,'Wage Detail Linked'!$E$5:$E$97,"")*B4/SUMIFS('Wage Detail Linked'!$O$5:$O$97,'Wage Detail Linked'!$B$5:$B$97,$A4,'Wage Detail Linked'!$C$5:$C$97,B$2,'Wage Detail Linked'!$E$5:$E$97,""),2)) | D4: =SUMIFS('Wage Detail Linked'!$O$5:$O$97,'Wage Detail Linked'!$B$5:$B$97,$A4,'Wage Detail Linked'!$C$5:$C$97,D$2,'Wage Detail Linked'!$E$5:$E$97,"") | E4: =IF(SUMIFS('Wage Detail Linked'!$O$5:$O$97,'Wage Detail Linked'!$B$5:$B$97,$A4,'Wage Detail Linked'!$C$5:$C$97,D$2,'Wage Detail Linked'!$E$5:$E$97,"")=0,IF(D4>0,ROUND(D4*90,2),0),ROUND(SUMIFS('Wage Detail Linked'!$R$5:$R$97,'Wage Detail Linked'!$B$5:$B$97,$A4,'Wage Detail Linked'!$C$5:$C$97,D$2,'Wage Detail Linked'!$E$5:$E$97,"")*D4/SUMIFS('Wage Detail Linked'!$O$5:$O$97,'Wage Detail Linked'!$B$5:$B$97,$A4,'Wage Detail Linked'!$C$5:$C$97,D$2,'Wage Detail Linked'!$E$5:$E$97,""),2)) | F4: =SUMIFS('Wage Detail Linked'!$O$5:$O$97,'Wage Detail Linked'!$B$5:$B$97,$A4,'Wage Detail Linked'!$C$5:$C$97,F$2,'Wage Detail Linked'!$E$5:$E$97,"") | G4: =IF(SUMIFS('Wage Detail Linked'!$O$5:$O$97,'Wage Detail Linked'!$B$5:$B$97,$A4,'Wage Detail Linked'!$C$5:$C$97,F$2,'Wage Detail Linked'!$E$5:$E$97,"")=0,IF(F4>0,ROUND(F4*90,2),0),ROUND(SUMIFS('Wage Detail Linked'!$R$5:$R$97,'Wage Detail Linked'!$B$5:$B$97,$A4,'Wage Detail Linked'!$C$5:$C$97,F$2,'Wage Detail Linked'!$E$5:$E$97,"")*F4/SUMIFS('Wage Detail Linked'!$O$5:$O$97,'Wage Detail Linked'!$B$5:$B$97,$A4,'Wage Detail Linked'!$C$5:$C$97,F$2,'Wage Detail Linked'!$E$5:$E$97,""),2)) | H4: =SUMIFS('Wage Detail Linked'!$O$5:$O$97,'Wage Detail Linked'!$B$5:$B$97,$A4,'Wage Detail Linked'!$C$5:$C$97,H$2,'Wage Detail Linked'!$E$5:$E$97,"") | I4: =IF(SUMIFS('Wage Detail Linked'!$O$5:$O$97,'Wage Detail Linked'!$B$5:$B$97,$A4,'Wage Detail Linked'!$C$5:$C$97,H$2,'Wage Detail Linked'!$E$5:$E$97,"")=0,IF(H4>0,ROUND(H4*90,2),0),ROUND(SUMIFS('Wage Detail Linked'!$R$5:$R$97,'Wage Detail Linked'!$B$5:$B$97,$A4,'Wage Detail Linked'!$C$5:$C$97,H$2,'Wage Detail Linked'!$E$5:$E$97,"")*H4/SUMIFS('Wage Detail Linked'!$O$5:$O$97,'Wage Detail Linked'!$B$5:$B$97,$A4,'Wage Detail Linked'!$C$5:$C$97,H$2,'Wage Detail Linked'!$E$5:$E$97,""),2)) | J4: =SUMIFS('Wage Detail Linked'!$O$5:$O$97,'Wage Detail Linked'!$B$5:$B$97,$A4,'Wage Detail Linked'!$C$5:$C$97,J$2,'Wage Detail Linked'!$E$5:$E$97,"") | K4: =IF(SUMIFS('Wage Detail Linked'!$O$5:$O$97,'Wage Detail Linked'!$B$5:$B$97,$A4,'Wage Detail Linked'!$C$5:$C$97,J$2,'Wage Detail Linked'!$E$5:$E$97,"")=0,IF(J4>0,ROUND(J4*90,2),0),ROUND(SUMIFS('Wage Detail Linked'!$R$5:$R$97,'Wage Detail Linked'!$B$5:$B$97,$A4,'Wage Detail Linked'!$C$5:$C$97,J$2,'Wage Detail Linked'!$E$5:$E$97,"")*J4/SUMIFS('Wage Detail Linked'!$O$5:$O$97,'Wage Detail Linked'!$B$5:$B$97,$A4,'Wage Detail Linked'!$C$5:$C$97,J$2,'Wage Detail Linked'!$E$5:$E$97,""),2)) | L4: =SUMIFS('Wage Detail Linked'!$O$5:$O$97,'Wage Detail Linked'!$B$5:$B$97,$A4,'Wage Detail Linked'!$C$5:$C$97,L$2,'Wage Detail Linked'!$E$5:$E$97,"") | M4: =IF(SUMIFS('Wage Detail Linked'!$O$5:$O$97,'Wage Detail Linked'!$B$5:$B$97,$A4,'Wage Detail Linked'!$C$5:$C$97,L$2,'Wage Detail Linked'!$E$5:$E$97,"")=0,IF(L4>0,ROUND(L4*90,2),0),ROUND(SUMIFS('Wage Detail Linked'!$R$5:$R$97,'Wage Detail Linked'!$B$5:$B$97,$A4,'Wage Detail Linked'!$C$5:$C$97,L$2,'Wage Detail Linked'!$E$5:$E$97,"")*L4/SUMIFS('Wage Detail Linked'!$O$5:$O$97,'Wage Detail Linked'!$B$5:$B$97,$A4,'Wage Detail Linked'!$C$5:$C$97,L$2,'Wage Detail Linked'!$E$5:$E$97,""),2)) | N4: =SUMIFS('Wage Detail Linked'!$O$5:$O$97,'Wage Detail Linked'!$B$5:$B$97,$A4,'Wage Detail Linked'!$C$5:$C$97,N$2,'Wage Detail Linked'!$E$5:$E$97,"") | O4: =IF(SUMIFS('Wage Detail Linked'!$O$5:$O$97,'Wage Detail Linked'!$B$5:$B$97,$A4,'Wage Detail Linked'!$C$5:$C$97,N$2,'Wage Detail Linked'!$E$5:$E$97,"")=0,IF(N4>0,ROUND(N4*90,2),0),ROUND(SUMIFS('Wage Detail Linked'!$R$5:$R$97,'Wage Detail Linked'!$B$5:$B$97,$A4,'Wage Detail Linked'!$C$5:$C$97,N$2,'Wage Detail Linked'!$E$5:$E$97,"")*N4/SUMIFS('Wage Detail Linked'!$O$5:$O$97,'Wage Detail Linked'!$B$5:$B$97,$A4,'Wage Detail Linked'!$C$5:$C$97,N$2,'Wage Detail Linked'!$E$5:$E$97,""),2)) | P4: ='Missed Shifts'!C7 | Q4: =IF('Missed Shifts'!C7=0,IF(P4>0,ROUND(P4*90,2),0),ROUND('Missed Shifts'!D7*P4/'Missed Shifts'!C7,2)) | R4: =SUM(B4,D4,F4,H4,J4,L4,N4,P4) | S4: =SUM(C4,E4,G4,I4,K4,M4,O4,Q4) | T4: 0 | U4: 0 | V4: =MAX(0,T4-U4) | W4: 0 | X4: 0 | Y4: =MAX(0,0-X4) | Z4: =U4+X4 | AA4: =MAX(0,S4-Z4)
A5: Daniel Motaung | B5: =SUMIFS('Wage Detail Linked'!$O$5:$O$97,'Wage Detail Linked'!$B$5:$B$97,$A5,'Wage Detail Linked'!$C$5:$C$97,B$2,'Wage Detail Linked'!$E$5:$E$97,"") | C5: =IF(SUMIFS('Wage Detail Linked'!$O$5:$O$97,'Wage Detail Linked'!$B$5:$B$97,$A5,'Wage Detail Linked'!$C$5:$C$97,B$2,'Wage Detail Linked'!$E$5:$E$97,"")=0,IF(B5>0,ROUND(B5*90,2),0),ROUND(SUMIFS('Wage Detail Linked'!$R$5:$R$97,'Wage Detail Linked'!$B$5:$B$97,$A5,'Wage Detail Linked'!$C$5:$C$97,B$2,'Wage Detail Linked'!$E$5:$E$97,"")*B5/SUMIFS('Wage Detail Linked'!$O$5:$O$97,'Wage Detail Linked'!$B$5:$B$97,$A5,'Wage Detail Linked'!$C$5:$C$97,B$2,'Wage Detail Linked'!$E$5:$E$97,""),2)) | D5: =SUMIFS('Wage Detail Linked'!$O$5:$O$97,'Wage Detail Linked'!$B$5:$B$97,$A5,'Wage Detail Linked'!$C$5:$C$97,D$2,'Wage Detail Linked'!$E$5:$E$97,"") | E5: =IF(SUMIFS('Wage Detail Linked'!$O$5:$O$97,'Wage Detail Linked'!$B$5:$B$97,$A5,'Wage Detail Linked'!$C$5:$C$97,D$2,'Wage Detail Linked'!$E$5:$E$97,"")=0,IF(D5>0,ROUND(D5*90,2),0),ROUND(SUMIFS('Wage Detail Linked'!$R$5:$R$97,'Wage Detail Linked'!$B$5:$B$97,$A5,'Wage Detail Linked'!$C$5:$C$97,D$2,'Wage Detail Linked'!$E$5:$E$97,"")*D5/SUMIFS('Wage Detail Linked'!$O$5:$O$97,'Wage Detail Linked'!$B$5:$B$97,$A5,'Wage Detail Linked'!$C$5:$C$97,D$2,'Wage Detail Linked'!$E$5:$E$97,""),2)) | F5: =SUMIFS('Wage Detail Linked'!$O$5:$O$97,'Wage Detail Linked'!$B$5:$B$97,$A5,'Wage Detail Linked'!$C$5:$C$97,F$2,'Wage Detail Linked'!$E$5:$E$97,"") | G5: =IF(SUMIFS('Wage Detail Linked'!$O$5:$O$97,'Wage Detail Linked'!$B$5:$B$97,$A5,'Wage Detail Linked'!$C$5:$C$97,F$2,'Wage Detail Linked'!$E$5:$E$97,"")=0,IF(F5>0,ROUND(F5*90,2),0),ROUND(SUMIFS('Wage Detail Linked'!$R$5:$R$97,'Wage Detail Linked'!$B$5:$B$97,$A5,'Wage Detail Linked'!$C$5:$C$97,F$2,'Wage Detail Linked'!$E$5:$E$97,"")*F5/SUMIFS('Wage Detail Linked'!$O$5:$O$97,'Wage Detail Linked'!$B$5:$B$97,$A5,'Wage Detail Linked'!$C$5:$C$97,F$2,'Wage Detail Linked'!$E$5:$E$97,""),2)) | H5: =SUMIFS('Wage Detail Linked'!$O$5:$O$97,'Wage Detail Linked'!$B$5:$B$97,$A5,'Wage Detail Linked'!$C$5:$C$97,H$2,'Wage Detail Linked'!$E$5:$E$97,"") | I5: =IF(SUMIFS('Wage Detail Linked'!$O$5:$O$97,'Wage Detail Linked'!$B$5:$B$97,$A5,'Wage Detail Linked'!$C$5:$C$97,H$2,'Wage Detail Linked'!$E$5:$E$97,"")=0,IF(H5>0,ROUND(H5*90,2),0),ROUND(SUMIFS('Wage Detail Linked'!$R$5:$R$97,'Wage Detail Linked'!$B$5:$B$97,$A5,'Wage Detail Linked'!$C$5:$C$97,H$2,'Wage Detail Linked'!$E$5:$E$97,"")*H5/SUMIFS('Wage Detail Linked'!$O$5:$O$97,'Wage Detail Linked'!$B$5:$B$97,$A5,'Wage Detail Linked'!$C$5:$C$97,H$2,'Wage Detail Linked'!$E$5:$E$97,""),2)) | J5: =SUMIFS('Wage Detail Linked'!$O$5:$O$97,'Wage Detail Linked'!$B$5:$B$97,$A5,'Wage Detail Linked'!$C$5:$C$97,J$2,'Wage Detail Linked'!$E$5:$E$97,"") | K5: =IF(SUMIFS('Wage Detail Linked'!$O$5:$O$97,'Wage Detail Linked'!$B$5:$B$97,$A5,'Wage Detail Linked'!$C$5:$C$97,J$2,'Wage Detail Linked'!$E$5:$E$97,"")=0,IF(J5>0,ROUND(J5*90,2),0),ROUND(SUMIFS('Wage Detail Linked'!$R$5:$R$97,'Wage Detail Linked'!$B$5:$B$97,$A5,'Wage Detail Linked'!$C$5:$C$97,J$2,'Wage Detail Linked'!$E$5:$E$97,"")*J5/SUMIFS('Wage Detail Linked'!$O$5:$O$97,'Wage Detail Linked'!$B$5:$B$97,$A5,'Wage Detail Linked'!$C$5:$C$97,J$2,'Wage Detail Linked'!$E$5:$E$97,""),2)) | L5: =SUMIFS('Wage Detail Linked'!$O$5:$O$97,'Wage Detail Linked'!$B$5:$B$97,$A5,'Wage Detail Linked'!$C$5:$C$97,L$2,'Wage Detail Linked'!$E$5:$E$97,"") | M5: =IF(SUMIFS('Wage Detail Linked'!$O$5:$O$97,'Wage Detail Linked'!$B$5:$B$97,$A5,'Wage Detail Linked'!$C$5:$C$97,L$2,'Wage Detail Linked'!$E$5:$E$97,"")=0,IF(L5>0,ROUND(L5*90,2),0),ROUND(SUMIFS('Wage Detail Linked'!$R$5:$R$97,'Wage Detail Linked'!$B$5:$B$97,$A5,'Wage Detail Linked'!$C$5:$C$97,L$2,'Wage Detail Linked'!$E$5:$E$97,"")*L5/SUMIFS('Wage Detail Linked'!$O$5:$O$97,'Wage Detail Linked'!$B$5:$B$97,$A5,'Wage Detail Linked'!$C$5:$C$97,L$2,'Wage Detail Linked'!$E$5:$E$97,""),2)) | N5: =SUMIFS('Wage Detail Linked'!$O$5:$O$97,'Wage Detail Linked'!$B$5:$B$97,$A5,'Wage Detail Linked'!$C$5:$C$97,N$2,'Wage Detail Linked'!$E$5:$E$97,"") | O5: =IF(SUMIFS('Wage Detail Linked'!$O$5:$O$97,'Wage Detail Linked'!$B$5:$B$97,$A5,'Wage Detail Linked'!$C$5:$C$97,N$2,'Wage Detail Linked'!$E$5:$E$97,"")=0,IF(N5>0,ROUND(N5*90,2),0),ROUND(SUMIFS('Wage Detail Linked'!$R$5:$R$97,'Wage Detail Linked'!$B$5:$B$97,$A5,'Wage Detail Linked'!$C$5:$C$97,N$2,'Wage Detail Linked'!$E$5:$E$97,"")*N5/SUMIFS('Wage Detail Linked'!$O$5:$O$97,'Wage Detail Linked'!$B$5:$B$97,$A5,'Wage Detail Linked'!$C$5:$C$97,N$2,'Wage Detail Linked'!$E$5:$E$97,""),2)) | P5: =0 | Q5: =IF(P5>0,ROUND(P5*90,2),0) | R5: =SUM(B5,D5,F5,H5,J5,L5,N5,P5) | S5: =SUM(C5,E5,G5,I5,K5,M5,O5,Q5) | T5: 0 | U5: 0 | V5: =MAX(0,T5-U5) | W5: 0 | X5: 0 | Y5: =MAX(0,0-X5) | Z5: =U5+X5 | AA5: =MAX(0,S5-Z5)
A6: Erence Mngomezulu | B6: =SUMIFS('Wage Detail Linked'!$O$5:$O$97,'Wage Detail Linked'!$B$5:$B$97,$A6,'Wage Detail Linked'!$C$5:$C$97,B$2,'Wage Detail Linked'!$E$5:$E$97,"") | C6: =IF(SUMIFS('Wage Detail Linked'!$O$5:$O$97,'Wage Detail Linked'!$B$5:$B$97,$A6,'Wage Detail Linked'!$C$5:$C$97,B$2,'Wage Detail Linked'!$E$5:$E$97,"")=0,IF(B6>0,ROUND(B6*90,2),0),ROUND(SUMIFS('Wage Detail Linked'!$R$5:$R$97,'Wage Detail Linked'!$B$5:$B$97,$A6,'Wage Detail Linked'!$C$5:$C$97,B$2,'Wage Detail Linked'!$E$5:$E$97,"")*B6/SUMIFS('Wage Detail Linked'!$O$5:$O$97,'Wage Detail Linked'!$B$5:$B$97,$A6,'Wage Detail Linked'!$C$5:$C$97,B$2,'Wage Detail Linked'!$E$5:$E$97,""),2)) | D6: =SUMIFS('Wage Detail Linked'!$O$5:$O$97,'Wage Detail Linked'!$B$5:$B$97,$A6,'Wage Detail Linked'!$C$5:$C$97,D$2,'Wage Detail Linked'!$E$5:$E$97,"") | E6: =IF(SUMIFS('Wage Detail Linked'!$O$5:$O$97,'Wage Detail Linked'!$B$5:$B$97,$A6,'Wage Detail Linked'!$C$5:$C$97,D$2,'Wage Detail Linked'!$E$5:$E$97,"")=0,IF(D6>0,ROUND(D6*90,2),0),ROUND(SUMIFS('Wage Detail Linked'!$R$5:$R$97,'Wage Detail Linked'!$B$5:$B$97,$A6,'Wage Detail Linked'!$C$5:$C$97,D$2,'Wage Detail Linked'!$E$5:$E$97,"")*D6/SUMIFS('Wage Detail Linked'!$O$5:$O$97,'Wage Detail Linked'!$B$5:$B$97,$A6,'Wage Detail Linked'!$C$5:$C$97,D$2,'Wage Detail Linked'!$E$5:$E$97,""),2)) | F6: =SUMIFS('Wage Detail Linked'!$O$5:$O$97,'Wage Detail Linked'!$B$5:$B$97,$A6,'Wage Detail Linked'!$C$5:$C$97,F$2,'Wage Detail Linked'!$E$5:$E$97,"") | G6: =IF(SUMIFS('Wage Detail Linked'!$O$5:$O$97,'Wage Detail Linked'!$B$5:$B$97,$A6,'Wage Detail Linked'!$C$5:$C$97,F$2,'Wage Detail Linked'!$E$5:$E$97,"")=0,IF(F6>0,ROUND(F6*90,2),0),ROUND(SUMIFS('Wage Detail Linked'!$R$5:$R$97,'Wage Detail Linked'!$B$5:$B$97,$A6,'Wage Detail Linked'!$C$5:$C$97,F$2,'Wage Detail Linked'!$E$5:$E$97,"")*F6/SUMIFS('Wage Detail Linked'!$O$5:$O$97,'Wage Detail Linked'!$B$5:$B$97,$A6,'Wage Detail Linked'!$C$5:$C$97,F$2,'Wage Detail Linked'!$E$5:$E$97,""),2)) | H6: =SUMIFS('Wage Detail Linked'!$O$5:$O$97,'Wage Detail Linked'!$B$5:$B$97,$A6,'Wage Detail Linked'!$C$5:$C$97,H$2,'Wage Detail Linked'!$E$5:$E$97,"") | I6: =IF(SUMIFS('Wage Detail Linked'!$O$5:$O$97,'Wage Detail Linked'!$B$5:$B$97,$A6,'Wage Detail Linked'!$C$5:$C$97,H$2,'Wage Detail Linked'!$E$5:$E$97,"")=0,IF(H6>0,ROUND(H6*90,2),0),ROUND(SUMIFS('Wage Detail Linked'!$R$5:$R$97,'Wage Detail Linked'!$B$5:$B$97,$A6,'Wage Detail Linked'!$C$5:$C$97,H$2,'Wage Detail Linked'!$E$5:$E$97,"")*H6/SUMIFS('Wage Detail Linked'!$O$5:$O$97,'Wage Detail Linked'!$B$5:$B$97,$A6,'Wage Detail Linked'!$C$5:$C$97,H$2,'Wage Detail Linked'!$E$5:$E$97,""),2)) | J6: =SUMIFS('Wage Detail Linked'!$O$5:$O$97,'Wage Detail Linked'!$B$5:$B$97,$A6,'Wage Detail Linked'!$C$5:$C$97,J$2,'Wage Detail Linked'!$E$5:$E$97,"") | K6: =IF(SUMIFS('Wage Detail Linked'!$O$5:$O$97,'Wage Detail Linked'!$B$5:$B$97,$A6,'Wage Detail Linked'!$C$5:$C$97,J$2,'Wage Detail Linked'!$E$5:$E$97,"")=0,IF(J6>0,ROUND(J6*90,2),0),ROUND(SUMIFS('Wage Detail Linked'!$R$5:$R$97,'Wage Detail Linked'!$B$5:$B$97,$A6,'Wage Detail Linked'!$C$5:$C$97,J$2,'Wage Detail Linked'!$E$5:$E$97,"")*J6/SUMIFS('Wage Detail Linked'!$O$5:$O$97,'Wage Detail Linked'!$B$5:$B$97,$A6,'Wage Detail Linked'!$C$5:$C$97,J$2,'Wage Detail Linked'!$E$5:$E$97,""),2)) | L6: =SUMIFS('Wage Detail Linked'!$O$5:$O$97,'Wage Detail Linked'!$B$5:$B$97,$A6,'Wage Detail Linked'!$C$5:$C$97,L$2,'Wage Detail Linked'!$E$5:$E$97,"") | M6: =IF(SUMIFS('Wage Detail Linked'!$O$5:$O$97,'Wage Detail Linked'!$B$5:$B$97,$A6,'Wage Detail Linked'!$C$5:$C$97,L$2,'Wage Detail Linked'!$E$5:$E$97,"")=0,IF(L6>0,ROUND(L6*90,2),0),ROUND(SUMIFS('Wage Detail Linked'!$R$5:$R$97,'Wage Detail Linked'!$B$5:$B$97,$A6,'Wage Detail Linked'!$C$5:$C$97,L$2,'Wage Detail Linked'!$E$5:$E$97,"")*L6/SUMIFS('Wage Detail Linked'!$O$5:$O$97,'Wage Detail Linked'!$B$5:$B$97,$A6,'Wage Detail Linked'!$C$5:$C$97,L$2,'Wage Detail Linked'!$E$5:$E$97,""),2)) | N6: =SUMIFS('Wage Detail Linked'!$O$5:$O$97,'Wage Detail Linked'!$B$5:$B$97,$A6,'Wage Detail Linked'!$C$5:$C$97,N$2,'Wage Detail Linked'!$E$5:$E$97,"") | O6: =IF(SUMIFS('Wage Detail Linked'!$O$5:$O$97,'Wage Detail Linked'!$B$5:$B$97,$A6,'Wage Detail Linked'!$C$5:$C$97,N$2,'Wage Detail Linked'!$E$5:$E$97,"")=0,IF(N6>0,ROUND(N6*90,2),0),ROUND(SUMIFS('Wage Detail Linked'!$R$5:$R$97,'Wage Detail Linked'!$B$5:$B$97,$A6,'Wage Detail Linked'!$C$5:$C$97,N$2,'Wage Detail Linked'!$E$5:$E$97,"")*N6/SUMIFS('Wage Detail Linked'!$O$5:$O$97,'Wage Detail Linked'!$B$5:$B$97,$A6,'Wage Detail Linked'!$C$5:$C$97,N$2,'Wage Detail Linked'!$E$5:$E$97,""),2)) | P6: ='Missed Shifts'!C12 | Q6: =IF('Missed Shifts'!C12=0,IF(P6>0,ROUND(P6*90,2),0),ROUND('Missed Shifts'!D12*P6/'Missed Shifts'!C12,2)) | R6: =SUM(B6,D6,F6,H6,J6,L6,N6,P6) | S6: =SUM(C6,E6,G6,I6,K6,M6,O6,Q6) | T6: 0 | U6: 0 | V6: =MAX(0,T6-U6) | W6: 0 | X6: 0 | Y6: =MAX(0,0-X6) | Z6: =U6+X6 | AA6: =MAX(0,S6-Z6)
A7: Erick Mpho Molefe | B7: =SUMIFS('Wage Detail Linked'!$O$5:$O$97,'Wage Detail Linked'!$B$5:$B$97,$A7,'Wage Detail Linked'!$C$5:$C$97,B$2,'Wage Detail Linked'!$E$5:$E$97,"") | C7: =IF(SUMIFS('Wage Detail Linked'!$O$5:$O$97,'Wage Detail Linked'!$B$5:$B$97,$A7,'Wage Detail Linked'!$C$5:$C$97,B$2,'Wage Detail Linked'!$E$5:$E$97,"")=0,IF(B7>0,ROUND(B7*90,2),0),ROUND(SUMIFS('Wage Detail Linked'!$R$5:$R$97,'Wage Detail Linked'!$B$5:$B$97,$A7,'Wage Detail Linked'!$C$5:$C$97,B$2,'Wage Detail Linked'!$E$5:$E$97,"")*B7/SUMIFS('Wage Detail Linked'!$O$5:$O$97,'Wage Detail Linked'!$B$5:$B$97,$A7,'Wage Detail Linked'!$C$5:$C$97,B$2,'Wage Detail Linked'!$E$5:$E$97,""),2)) | D7: =SUMIFS('Wage Detail Linked'!$O$5:$O$97,'Wage Detail Linked'!$B$5:$B$97,$A7,'Wage Detail Linked'!$C$5:$C$97,D$2,'Wage Detail Linked'!$E$5:$E$97,"") | E7: =IF(SUMIFS('Wage Detail Linked'!$O$5:$O$97,'Wage Detail Linked'!$B$5:$B$97,$A7,'Wage Detail Linked'!$C$5:$C$97,D$2,'Wage Detail Linked'!$E$5:$E$97,"")=0,IF(D7>0,ROUND(D7*90,2),0),ROUND(SUMIFS('Wage Detail Linked'!$R$5:$R$97,'Wage Detail Linked'!$B$5:$B$97,$A7,'Wage Detail Linked'!$C$5:$C$97,D$2,'Wage Detail Linked'!$E$5:$E$97,"")*D7/SUMIFS('Wage Detail Linked'!$O$5:$O$97,'Wage Detail Linked'!$B$5:$B$97,$A7,'Wage Detail Linked'!$C$5:$C$97,D$2,'Wage Detail Linked'!$E$5:$E$97,""),2)) | F7: =SUMIFS('Wage Detail Linked'!$O$5:$O$97,'Wage Detail Linked'!$B$5:$B$97,$A7,'Wage Detail Linked'!$C$5:$C$97,F$2,'Wage Detail Linked'!$E$5:$E$97,"") | G7: =IF(SUMIFS('Wage Detail Linked'!$O$5:$O$97,'Wage Detail Linked'!$B$5:$B$97,$A7,'Wage Detail Linked'!$C$5:$C$97,F$2,'Wage Detail Linked'!$E$5:$E$97,"")=0,IF(F7>0,ROUND(F7*90,2),0),ROUND(SUMIFS('Wage Detail Linked'!$R$5:$R$97,'Wage Detail Linked'!$B$5:$B$97,$A7,'Wage Detail Linked'!$C$5:$C$97,F$2,'Wage Detail Linked'!$E$5:$E$97,"")*F7/SUMIFS('Wage Detail Linked'!$O$5:$O$97,'Wage Detail Linked'!$B$5:$B$97,$A7,'Wage Detail Linked'!$C$5:$C$97,F$2,'Wage Detail Linked'!$E$5:$E$97,""),2)) | H7: =SUMIFS('Wage Detail Linked'!$O$5:$O$97,'Wage Detail Linked'!$B$5:$B$97,$A7,'Wage Detail Linked'!$C$5:$C$97,H$2,'Wage Detail Linked'!$E$5:$E$97,"") | I7: =IF(SUMIFS('Wage Detail Linked'!$O$5:$O$97,'Wage Detail Linked'!$B$5:$B$97,$A7,'Wage Detail Linked'!$C$5:$C$97,H$2,'Wage Detail Linked'!$E$5:$E$97,"")=0,IF(H7>0,ROUND(H7*90,2),0),ROUND(SUMIFS('Wage Detail Linked'!$R$5:$R$97,'Wage Detail Linked'!$B$5:$B$97,$A7,'Wage Detail Linked'!$C$5:$C$97,H$2,'Wage Detail Linked'!$E$5:$E$97,"")*H7/SUMIFS('Wage Detail Linked'!$O$5:$O$97,'Wage Detail Linked'!$B$5:$B$97,$A7,'Wage Detail Linked'!$C$5:$C$97,H$2,'Wage Detail Linked'!$E$5:$E$97,""),2)) | J7: =SUMIFS('Wage Detail Linked'!$O$5:$O$97,'Wage Detail Linked'!$B$5:$B$97,$A7,'Wage Detail Linked'!$C$5:$C$97,J$2,'Wage Detail Linked'!$E$5:$E$97,"") | K7: =IF(SUMIFS('Wage Detail Linked'!$O$5:$O$97,'Wage Detail Linked'!$B$5:$B$97,$A7,'Wage Detail Linked'!$C$5:$C$97,J$2,'Wage Detail Linked'!$E$5:$E$97,"")=0,IF(J7>0,ROUND(J7*90,2),0),ROUND(SUMIFS('Wage Detail Linked'!$R$5:$R$97,'Wage Detail Linked'!$B$5:$B$97,$A7,'Wage Detail Linked'!$C$5:$C$97,J$2,'Wage Detail Linked'!$E$5:$E$97,"")*J7/SUMIFS('Wage Detail Linked'!$O$5:$O$97,'Wage Detail Linked'!$B$5:$B$97,$A7,'Wage Detail Linked'!$C$5:$C$97,J$2,'Wage Detail Linked'!$E$5:$E$97,""),2)) | L7: =SUMIFS('Wage Detail Linked'!$O$5:$O$97,'Wage Detail Linked'!$B$5:$B$97,$A7,'Wage Detail Linked'!$C$5:$C$97,L$2,'Wage Detail Linked'!$E$5:$E$97,"") | M7: =IF(SUMIFS('Wage Detail Linked'!$O$5:$O$97,'Wage Detail Linked'!$B$5:$B$97,$A7,'Wage Detail Linked'!$C$5:$C$97,L$2,'Wage Detail Linked'!$E$5:$E$97,"")=0,IF(L7>0,ROUND(L7*90,2),0),ROUND(SUMIFS('Wage Detail Linked'!$R$5:$R$97,'Wage Detail Linked'!$B$5:$B$97,$A7,'Wage Detail Linked'!$C$5:$C$97,L$2,'Wage Detail Linked'!$E$5:$E$97,"")*L7/SUMIFS('Wage Detail Linked'!$O$5:$O$97,'Wage Detail Linked'!$B$5:$B$97,$A7,'Wage Detail Linked'!$C$5:$C$97,L$2,'Wage Detail Linked'!$E$5:$E$97,""),2)) | N7: =SUMIFS('Wage Detail Linked'!$O$5:$O$97,'Wage Detail Linked'!$B$5:$B$97,$A7,'Wage Detail Linked'!$C$5:$C$97,N$2,'Wage Detail Linked'!$E$5:$E$97,"") | O7: =IF(SUMIFS('Wage Detail Linked'!$O$5:$O$97,'Wage Detail Linked'!$B$5:$B$97,$A7,'Wage Detail Linked'!$C$5:$C$97,N$2,'Wage Detail Linked'!$E$5:$E$97,"")=0,IF(N7>0,ROUND(N7*90,2),0),ROUND(SUMIFS('Wage Detail Linked'!$R$5:$R$97,'Wage Detail Linked'!$B$5:$B$97,$A7,'Wage Detail Linked'!$C$5:$C$97,N$2,'Wage Detail Linked'!$E$5:$E$97,"")*N7/SUMIFS('Wage Detail Linked'!$O$5:$O$97,'Wage Detail Linked'!$B$5:$B$97,$A7,'Wage Detail Linked'!$C$5:$C$97,N$2,'Wage Detail Linked'!$E$5:$E$97,""),2)) | P7: ='Missed Shifts'!C15 | Q7: =IF('Missed Shifts'!C15=0,IF(P7>0,ROUND(P7*90,2),0),ROUND('Missed Shifts'!D15*P7/'Missed Shifts'!C15,2)) | R7: =SUM(B7,D7,F7,H7,J7,L7,N7,P7) | S7: =SUM(C7,E7,G7,I7,K7,M7,O7,Q7) | T7: 1000 | U7: 1000 | V7: =MAX(0,T7-U7) | W7: 500 | X7: 500 | Y7: =MAX(0,1000-X7) | Z7: =U7+X7 | AA7: =MAX(0,S7-Z7)
A8: Givemore Chifetete Kuziwa | B8: =SUMIFS('Wage Detail Linked'!$O$5:$O$97,'Wage Detail Linked'!$B$5:$B$97,$A8,'Wage Detail Linked'!$C$5:$C$97,B$2,'Wage Detail Linked'!$E$5:$E$97,"") | C8: =IF(SUMIFS('Wage Detail Linked'!$O$5:$O$97,'Wage Detail Linked'!$B$5:$B$97,$A8,'Wage Detail Linked'!$C$5:$C$97,B$2,'Wage Detail Linked'!$E$5:$E$97,"")=0,IF(B8>0,ROUND(B8*90,2),0),ROUND(SUMIFS('Wage Detail Linked'!$R$5:$R$97,'Wage Detail Linked'!$B$5:$B$97,$A8,'Wage Detail Linked'!$C$5:$C$97,B$2,'Wage Detail Linked'!$E$5:$E$97,"")*B8/SUMIFS('Wage Detail Linked'!$O$5:$O$97,'Wage Detail Linked'!$B$5:$B$97,$A8,'Wage Detail Linked'!$C$5:$C$97,B$2,'Wage Detail Linked'!$E$5:$E$97,""),2)) | D8: =SUMIFS('Wage Detail Linked'!$O$5:$O$97,'Wage Detail Linked'!$B$5:$B$97,$A8,'Wage Detail Linked'!$C$5:$C$97,D$2,'Wage Detail Linked'!$E$5:$E$97,"") | E8: =IF(SUMIFS('Wage Detail Linked'!$O$5:$O$97,'Wage Detail Linked'!$B$5:$B$97,$A8,'Wage Detail Linked'!$C$5:$C$97,D$2,'Wage Detail Linked'!$E$5:$E$97,"")=0,IF(D8>0,ROUND(D8*90,2),0),ROUND(SUMIFS('Wage Detail Linked'!$R$5:$R$97,'Wage Detail Linked'!$B$5:$B$97,$A8,'Wage Detail Linked'!$C$5:$C$97,D$2,'Wage Detail Linked'!$E$5:$E$97,"")*D8/SUMIFS('Wage Detail Linked'!$O$5:$O$97,'Wage Detail Linked'!$B$5:$B$97,$A8,'Wage Detail Linked'!$C$5:$C$97,D$2,'Wage Detail Linked'!$E$5:$E$97,""),2)) | F8: =SUMIFS('Wage Detail Linked'!$O$5:$O$97,'Wage Detail Linked'!$B$5:$B$97,$A8,'Wage Detail Linked'!$C$5:$C$97,F$2,'Wage Detail Linked'!$E$5:$E$97,"") | G8: =IF(SUMIFS('Wage Detail Linked'!$O$5:$O$97,'Wage Detail Linked'!$B$5:$B$97,$A8,'Wage Detail Linked'!$C$5:$C$97,F$2,'Wage Detail Linked'!$E$5:$E$97,"")=0,IF(F8>0,ROUND(F8*90,2),0),ROUND(SUMIFS('Wage Detail Linked'!$R$5:$R$97,'Wage Detail Linked'!$B$5:$B$97,$A8,'Wage Detail Linked'!$C$5:$C$97,F$2,'Wage Detail Linked'!$E$5:$E$97,"")*F8/SUMIFS('Wage Detail Linked'!$O$5:$O$97,'Wage Detail Linked'!$B$5:$B$97,$A8,'Wage Detail Linked'!$C$5:$C$97,F$2,'Wage Detail Linked'!$E$5:$E$97,""),2)) | H8: =SUMIFS('Wage Detail Linked'!$O$5:$O$97,'Wage Detail Linked'!$B$5:$B$97,$A8,'Wage Detail Linked'!$C$5:$C$97,H$2,'Wage Detail Linked'!$E$5:$E$97,"") | I8: =IF(SUMIFS('Wage Detail Linked'!$O$5:$O$97,'Wage Detail Linked'!$B$5:$B$97,$A8,'Wage Detail Linked'!$C$5:$C$97,H$2,'Wage Detail Linked'!$E$5:$E$97,"")=0,IF(H8>0,ROUND(H8*90,2),0),ROUND(SUMIFS('Wage Detail Linked'!$R$5:$R$97,'Wage Detail Linked'!$B$5:$B$97,$A8,'Wage Detail Linked'!$C$5:$C$97,H$2,'Wage Detail Linked'!$E$5:$E$97,"")*H8/SUMIFS('Wage Detail Linked'!$O$5:$O$97,'Wage Detail Linked'!$B$5:$B$97,$A8,'Wage Detail Linked'!$C$5:$C$97,H$2,'Wage Detail Linked'!$E$5:$E$97,""),2)) | J8: =SUMIFS('Wage Detail Linked'!$O$5:$O$97,'Wage Detail Linked'!$B$5:$B$97,$A8,'Wage Detail Linked'!$C$5:$C$97,J$2,'Wage Detail Linked'!$E$5:$E$97,"") | K8: =IF(SUMIFS('Wage Detail Linked'!$O$5:$O$97,'Wage Detail Linked'!$B$5:$B$97,$A8,'Wage Detail Linked'!$C$5:$C$97,J$2,'Wage Detail Linked'!$E$5:$E$97,"")=0,IF(J8>0,ROUND(J8*90,2),0),ROUND(SUMIFS('Wage Detail Linked'!$R$5:$R$97,'Wage Detail Linked'!$B$5:$B$97,$A8,'Wage Detail Linked'!$C$5:$C$97,J$2,'Wage Detail Linked'!$E$5:$E$97,"")*J8/SUMIFS('Wage Detail Linked'!$O$5:$O$97,'Wage Detail Linked'!$B$5:$B$97,$A8,'Wage Detail Linked'!$C$5:$C$97,J$2,'Wage Detail Linked'!$E$5:$E$97,""),2)) | L8: =SUMIFS('Wage Detail Linked'!$O$5:$O$97,'Wage Detail Linked'!$B$5:$B$97,$A8,'Wage Detail Linked'!$C$5:$C$97,L$2,'Wage Detail Linked'!$E$5:$E$97,"") | M8: =IF(SUMIFS('Wage Detail Linked'!$O$5:$O$97,'Wage Detail Linked'!$B$5:$B$97,$A8,'Wage Detail Linked'!$C$5:$C$97,L$2,'Wage Detail Linked'!$E$5:$E$97,"")=0,IF(L8>0,ROUND(L8*90,2),0),ROUND(SUMIFS('Wage Detail Linked'!$R$5:$R$97,'Wage Detail Linked'!$B$5:$B$97,$A8,'Wage Detail Linked'!$C$5:$C$97,L$2,'Wage Detail Linked'!$E$5:$E$97,"")*L8/SUMIFS('Wage Detail Linked'!$O$5:$O$97,'Wage Detail Linked'!$B$5:$B$97,$A8,'Wage Detail Linked'!$C$5:$C$97,L$2,'Wage Detail Linked'!$E$5:$E$97,""),2)) | N8: =SUMIFS('Wage Detail Linked'!$O$5:$O$97,'Wage Detail Linked'!$B$5:$B$97,$A8,'Wage Detail Linked'!$C$5:$C$97,N$2,'Wage Detail Linked'!$E$5:$E$97,"") | O8: =IF(SUMIFS('Wage Detail Linked'!$O$5:$O$97,'Wage Detail Linked'!$B$5:$B$97,$A8,'Wage Detail Linked'!$C$5:$C$97,N$2,'Wage Detail Linked'!$E$5:$E$97,"")=0,IF(N8>0,ROUND(N8*90,2),0),ROUND(SUMIFS('Wage Detail Linked'!$R$5:$R$97,'Wage Detail Linked'!$B$5:$B$97,$A8,'Wage Detail Linked'!$C$5:$C$97,N$2,'Wage Detail Linked'!$E$5:$E$97,"")*N8/SUMIFS('Wage Detail Linked'!$O$5:$O$97,'Wage Detail Linked'!$B$5:$B$97,$A8,'Wage Detail Linked'!$C$5:$C$97,N$2,'Wage Detail Linked'!$E$5:$E$97,""),2)) | P8: ='Missed Shifts'!C18 | Q8: =IF('Missed Shifts'!C18=0,IF(P8>0,ROUND(P8*90,2),0),ROUND('Missed Shifts'!D18*P8/'Missed Shifts'!C18,2)) | R8: =SUM(B8,D8,F8,H8,J8,L8,N8,P8) | S8: =SUM(C8,E8,G8,I8,K8,M8,O8,Q8) | T8: 0 | U8: 0 | V8: =MAX(0,T8-U8) | W8: 0 | X8: 0 | Y8: =MAX(0,0-X8) | Z8: =U8+X8 | AA8: =MAX(0,S8-Z8)
A9: Isaac Mbele | B9: =SUMIFS('Wage Detail Linked'!$O$5:$O$97,'Wage Detail Linked'!$B$5:$B$97,$A9,'Wage Detail Linked'!$C$5:$C$97,B$2,'Wage Detail Linked'!$E$5:$E$97,"") | C9: =IF(SUMIFS('Wage Detail Linked'!$O$5:$O$97,'Wage Detail Linked'!$B$5:$B$97,$A9,'Wage Detail Linked'!$C$5:$C$97,B$2,'Wage Detail Linked'!$E$5:$E$97,"")=0,IF(B9>0,ROUND(B9*90,2),0),ROUND(SUMIFS('Wage Detail Linked'!$R$5:$R$97,'Wage Detail Linked'!$B$5:$B$97,$A9,'Wage Detail Linked'!$C$5:$C$97,B$2,'Wage Detail Linked'!$E$5:$E$97,"")*B9/SUMIFS('Wage Detail Linked'!$O$5:$O$97,'Wage Detail Linked'!$B$5:$B$97,$A9,'Wage Detail Linked'!$C$5:$C$97,B$2,'Wage Detail Linked'!$E$5:$E$97,""),2)) | D9: =SUMIFS('Wage Detail Linked'!$O$5:$O$97,'Wage Detail Linked'!$B$5:$B$97,$A9,'Wage Detail Linked'!$C$5:$C$97,D$2,'Wage Detail Linked'!$E$5:$E$97,"") | E9: =IF(SUMIFS('Wage Detail Linked'!$O$5:$O$97,'Wage Detail Linked'!$B$5:$B$97,$A9,'Wage Detail Linked'!$C$5:$C$97,D$2,'Wage Detail Linked'!$E$5:$E$97,"")=0,IF(D9>0,ROUND(D9*90,2),0),ROUND(SUMIFS('Wage Detail Linked'!$R$5:$R$97,'Wage Detail Linked'!$B$5:$B$97,$A9,'Wage Detail Linked'!$C$5:$C$97,D$2,'Wage Detail Linked'!$E$5:$E$97,"")*D9/SUMIFS('Wage Detail Linked'!$O$5:$O$97,'Wage Detail Linked'!$B$5:$B$97,$A9,'Wage Detail Linked'!$C$5:$C$97,D$2,'Wage Detail Linked'!$E$5:$E$97,""),2)) | F9: =SUMIFS('Wage Detail Linked'!$O$5:$O$97,'Wage Detail Linked'!$B$5:$B$97,$A9,'Wage Detail Linked'!$C$5:$C$97,F$2,'Wage Detail Linked'!$E$5:$E$97,"") | G9: =IF(SUMIFS('Wage Detail Linked'!$O$5:$O$97,'Wage Detail Linked'!$B$5:$B$97,$A9,'Wage Detail Linked'!$C$5:$C$97,F$2,'Wage Detail Linked'!$E$5:$E$97,"")=0,IF(F9>0,ROUND(F9*90,2),0),ROUND(SUMIFS('Wage Detail Linked'!$R$5:$R$97,'Wage Detail Linked'!$B$5:$B$97,$A9,'Wage Detail Linked'!$C$5:$C$97,F$2,'Wage Detail Linked'!$E$5:$E$97,"")*F9/SUMIFS('Wage Detail Linked'!$O$5:$O$97,'Wage Detail Linked'!$B$5:$B$97,$A9,'Wage Detail Linked'!$C$5:$C$97,F$2,'Wage Detail Linked'!$E$5:$E$97,""),2)) | H9: =SUMIFS('Wage Detail Linked'!$O$5:$O$97,'Wage Detail Linked'!$B$5:$B$97,$A9,'Wage Detail Linked'!$C$5:$C$97,H$2,'Wage Detail Linked'!$E$5:$E$97,"") | I9: =IF(SUMIFS('Wage Detail Linked'!$O$5:$O$97,'Wage Detail Linked'!$B$5:$B$97,$A9,'Wage Detail Linked'!$C$5:$C$97,H$2,'Wage Detail Linked'!$E$5:$E$97,"")=0,IF(H9>0,ROUND(H9*90,2),0),ROUND(SUMIFS('Wage Detail Linked'!$R$5:$R$97,'Wage Detail Linked'!$B$5:$B$97,$A9,'Wage Detail Linked'!$C$5:$C$97,H$2,'Wage Detail Linked'!$E$5:$E$97,"")*H9/SUMIFS('Wage Detail Linked'!$O$5:$O$97,'Wage Detail Linked'!$B$5:$B$97,$A9,'Wage Detail Linked'!$C$5:$C$97,H$2,'Wage Detail Linked'!$E$5:$E$97,""),2)) | J9: =SUMIFS('Wage Detail Linked'!$O$5:$O$97,'Wage Detail Linked'!$B$5:$B$97,$A9,'Wage Detail Linked'!$C$5:$C$97,J$2,'Wage Detail Linked'!$E$5:$E$97,"") | K9: =IF(SUMIFS('Wage Detail Linked'!$O$5:$O$97,'Wage Detail Linked'!$B$5:$B$97,$A9,'Wage Detail Linked'!$C$5:$C$97,J$2,'Wage Detail Linked'!$E$5:$E$97,"")=0,IF(J9>0,ROUND(J9*90,2),0),ROUND(SUMIFS('Wage Detail Linked'!$R$5:$R$97,'Wage Detail Linked'!$B$5:$B$97,$A9,'Wage Detail Linked'!$C$5:$C$97,J$2,'Wage Detail Linked'!$E$5:$E$97,"")*J9/SUMIFS('Wage Detail Linked'!$O$5:$O$97,'Wage Detail Linked'!$B$5:$B$97,$A9,'Wage Detail Linked'!$C$5:$C$97,J$2,'Wage Detail Linked'!$E$5:$E$97,""),2)) | L9: =SUMIFS('Wage Detail Linked'!$O$5:$O$97,'Wage Detail Linked'!$B$5:$B$97,$A9,'Wage Detail Linked'!$C$5:$C$97,L$2,'Wage Detail Linked'!$E$5:$E$97,"") | M9: =IF(SUMIFS('Wage Detail Linked'!$O$5:$O$97,'Wage Detail Linked'!$B$5:$B$97,$A9,'Wage Detail Linked'!$C$5:$C$97,L$2,'Wage Detail Linked'!$E$5:$E$97,"")=0,IF(L9>0,ROUND(L9*90,2),0),ROUND(SUMIFS('Wage Detail Linked'!$R$5:$R$97,'Wage Detail Linked'!$B$5:$B$97,$A9,'Wage Detail Linked'!$C$5:$C$97,L$2,'Wage Detail Linked'!$E$5:$E$97,"")*L9/SUMIFS('Wage Detail Linked'!$O$5:$O$97,'Wage Detail Linked'!$B$5:$B$97,$A9,'Wage Detail Linked'!$C$5:$C$97,L$2,'Wage Detail Linked'!$E$5:$E$97,""),2)) | N9: =SUMIFS('Wage Detail Linked'!$O$5:$O$97,'Wage Detail Linked'!$B$5:$B$97,$A9,'Wage Detail Linked'!$C$5:$C$97,N$2,'Wage Detail Linked'!$E$5:$E$97,"") | O9: =IF(SUMIFS('Wage Detail Linked'!$O$5:$O$97,'Wage Detail Linked'!$B$5:$B$97,$A9,'Wage Detail Linked'!$C$5:$C$97,N$2,'Wage Detail Linked'!$E$5:$E$97,"")=0,IF(N9>0,ROUND(N9*90,2),0),ROUND(SUMIFS('Wage Detail Linked'!$R$5:$R$97,'Wage Detail Linked'!$B$5:$B$97,$A9,'Wage Detail Linked'!$C$5:$C$97,N$2,'Wage Detail Linked'!$E$5:$E$97,"")*N9/SUMIFS('Wage Detail Linked'!$O$5:$O$97,'Wage Detail Linked'!$B$5:$B$97,$A9,'Wage Detail Linked'!$C$5:$C$97,N$2,'Wage Detail Linked'!$E$5:$E$97,""),2)) | P9: =0 | Q9: =IF(P9>0,ROUND(P9*90,2),0) | R9: =SUM(B9,D9,F9,H9,J9,L9,N9,P9) | S9: =SUM(C9,E9,G9,I9,K9,M9,O9,Q9) | T9: 260 | U9: 260 | V9: =MAX(0,T9-U9) | W9: 1000 | X9: 1000 | Y9: =MAX(0,1600-X9) | Z9: =U9+X9 | AA9: =MAX(0,S9-Z9)
A10: John Simbarashe Mhlanga | B10: =SUMIFS('Wage Detail Linked'!$O$5:$O$97,'Wage Detail Linked'!$B$5:$B$97,$A10,'Wage Detail Linked'!$C$5:$C$97,B$2,'Wage Detail Linked'!$E$5:$E$97,"") | C10: =IF(SUMIFS('Wage Detail Linked'!$O$5:$O$97,'Wage Detail Linked'!$B$5:$B$97,$A10,'Wage Detail Linked'!$C$5:$C$97,B$2,'Wage Detail Linked'!$E$5:$E$97,"")=0,IF(B10>0,ROUND(B10*90,2),0),ROUND(SUMIFS('Wage Detail Linked'!$R$5:$R$97,'Wage Detail Linked'!$B$5:$B$97,$A10,'Wage Detail Linked'!$C$5:$C$97,B$2,'Wage Detail Linked'!$E$5:$E$97,"")*B10/SUMIFS('Wage Detail Linked'!$O$5:$O$97,'Wage Detail Linked'!$B$5:$B$97,$A10,'Wage Detail Linked'!$C$5:$C$97,B$2,'Wage Detail Linked'!$E$5:$E$97,""),2)) | D10: =SUMIFS('Wage Detail Linked'!$O$5:$O$97,'Wage Detail Linked'!$B$5:$B$97,$A10,'Wage Detail Linked'!$C$5:$C$97,D$2,'Wage Detail Linked'!$E$5:$E$97,"") | E10: =IF(SUMIFS('Wage Detail Linked'!$O$5:$O$97,'Wage Detail Linked'!$B$5:$B$97,$A10,'Wage Detail Linked'!$C$5:$C$97,D$2,'Wage Detail Linked'!$E$5:$E$97,"")=0,IF(D10>0,ROUND(D10*90,2),0),ROUND(SUMIFS('Wage Detail Linked'!$R$5:$R$97,'Wage Detail Linked'!$B$5:$B$97,$A10,'Wage Detail Linked'!$C$5:$C$97,D$2,'Wage Detail Linked'!$E$5:$E$97,"")*D10/SUMIFS('Wage Detail Linked'!$O$5:$O$97,'Wage Detail Linked'!$B$5:$B$97,$A10,'Wage Detail Linked'!$C$5:$C$97,D$2,'Wage Detail Linked'!$E$5:$E$97,""),2)) | F10: =SUMIFS('Wage Detail Linked'!$O$5:$O$97,'Wage Detail Linked'!$B$5:$B$97,$A10,'Wage Detail Linked'!$C$5:$C$97,F$2,'Wage Detail Linked'!$E$5:$E$97,"") | G10: =IF(SUMIFS('Wage Detail Linked'!$O$5:$O$97,'Wage Detail Linked'!$B$5:$B$97,$A10,'Wage Detail Linked'!$C$5:$C$97,F$2,'Wage Detail Linked'!$E$5:$E$97,"")=0,IF(F10>0,ROUND(F10*90,2),0),ROUND(SUMIFS('Wage Detail Linked'!$R$5:$R$97,'Wage Detail Linked'!$B$5:$B$97,$A10,'Wage Detail Linked'!$C$5:$C$97,F$2,'Wage Detail Linked'!$E$5:$E$97,"")*F10/SUMIFS('Wage Detail Linked'!$O$5:$O$97,'Wage Detail Linked'!$B$5:$B$97,$A10,'Wage Detail Linked'!$C$5:$C$97,F$2,'Wage Detail Linked'!$E$5:$E$97,""),2)) | H10: =SUMIFS('Wage Detail Linked'!$O$5:$O$97,'Wage Detail Linked'!$B$5:$B$97,$A10,'Wage Detail Linked'!$C$5:$C$97,H$2,'Wage Detail Linked'!$E$5:$E$97,"") | I10: =IF(SUMIFS('Wage Detail Linked'!$O$5:$O$97,'Wage Detail Linked'!$B$5:$B$97,$A10,'Wage Detail Linked'!$C$5:$C$97,H$2,'Wage Detail Linked'!$E$5:$E$97,"")=0,IF(H10>0,ROUND(H10*90,2),0),ROUND(SUMIFS('Wage Detail Linked'!$R$5:$R$97,'Wage Detail Linked'!$B$5:$B$97,$A10,'Wage Detail Linked'!$C$5:$C$97,H$2,'Wage Detail Linked'!$E$5:$E$97,"")*H10/SUMIFS('Wage Detail Linked'!$O$5:$O$97,'Wage Detail Linked'!$B$5:$B$97,$A10,'Wage Detail Linked'!$C$5:$C$97,H$2,'Wage Detail Linked'!$E$5:$E$97,""),2)) | J10: =SUMIFS('Wage Detail Linked'!$O$5:$O$97,'Wage Detail Linked'!$B$5:$B$97,$A10,'Wage Detail Linked'!$C$5:$C$97,J$2,'Wage Detail Linked'!$E$5:$E$97,"") | K10: =IF(SUMIFS('Wage Detail Linked'!$O$5:$O$97,'Wage Detail Linked'!$B$5:$B$97,$A10,'Wage Detail Linked'!$C$5:$C$97,J$2,'Wage Detail Linked'!$E$5:$E$97,"")=0,IF(J10>0,ROUND(J10*90,2),0),ROUND(SUMIFS('Wage Detail Linked'!$R$5:$R$97,'Wage Detail Linked'!$B$5:$B$97,$A10,'Wage Detail Linked'!$C$5:$C$97,J$2,'Wage Detail Linked'!$E$5:$E$97,"")*J10/SUMIFS('Wage Detail Linked'!$O$5:$O$97,'Wage Detail Linked'!$B$5:$B$97,$A10,'Wage Detail Linked'!$C$5:$C$97,J$2,'Wage Detail Linked'!$E$5:$E$97,""),2)) | L10: =SUMIFS('Wage Detail Linked'!$O$5:$O$97,'Wage Detail Linked'!$B$5:$B$97,$A10,'Wage Detail Linked'!$C$5:$C$97,L$2,'Wage Detail Linked'!$E$5:$E$97,"") | M10: =IF(SUMIFS('Wage Detail Linked'!$O$5:$O$97,'Wage Detail Linked'!$B$5:$B$97,$A10,'Wage Detail Linked'!$C$5:$C$97,L$2,'Wage Detail Linked'!$E$5:$E$97,"")=0,IF(L10>0,ROUND(L10*90,2),0),ROUND(SUMIFS('Wage Detail Linked'!$R$5:$R$97,'Wage Detail Linked'!$B$5:$B$97,$A10,'Wage Detail Linked'!$C$5:$C$97,L$2,'Wage Detail Linked'!$E$5:$E$97,"")*L10/SUMIFS('Wage Detail Linked'!$O$5:$O$97,'Wage Detail Linked'!$B$5:$B$97,$A10,'Wage Detail Linked'!$C$5:$C$97,L$2,'Wage Detail Linked'!$E$5:$E$97,""),2)) | N10: =SUMIFS('Wage Detail Linked'!$O$5:$O$97,'Wage Detail Linked'!$B$5:$B$97,$A10,'Wage Detail Linked'!$C$5:$C$97,N$2,'Wage Detail Linked'!$E$5:$E$97,"") | O10: =IF(SUMIFS('Wage Detail Linked'!$O$5:$O$97,'Wage Detail Linked'!$B$5:$B$97,$A10,'Wage Detail Linked'!$C$5:$C$97,N$2,'Wage Detail Linked'!$E$5:$E$97,"")=0,IF(N10>0,ROUND(N10*90,2),0),ROUND(SUMIFS('Wage Detail Linked'!$R$5:$R$97,'Wage Detail Linked'!$B$5:$B$97,$A10,'Wage Detail Linked'!$C$5:$C$97,N$2,'Wage Detail Linked'!$E$5:$E$97,"")*N10/SUMIFS('Wage Detail Linked'!$O$5:$O$97,'Wage Detail Linked'!$B$5:$B$97,$A10,'Wage Detail Linked'!$C$5:$C$97,N$2,'Wage Detail Linked'!$E$5:$E$97,""),2)) | P10: ='Missed Shifts'!C22 | Q10: =IF('Missed Shifts'!C22=0,IF(P10>0,ROUND(P10*90,2),0),ROUND('Missed Shifts'!D22*P10/'Missed Shifts'!C22,2)) | R10: =SUM(B10,D10,F10,H10,J10,L10,N10,P10) | S10: =SUM(C10,E10,G10,I10,K10,M10,O10,Q10) | T10: 0 | U10: 0 | V10: =MAX(0,T10-U10) | W10: 0 | X10: 0 | Y10: =MAX(0,0-X10) | Z10: =U10+X10 | AA10: =MAX(0,S10-Z10)
A11: Joshua Motsamai Nteo | B11: =SUMIFS('Wage Detail Linked'!$O$5:$O$97,'Wage Detail Linked'!$B$5:$B$97,$A11,'Wage Detail Linked'!$C$5:$C$97,B$2,'Wage Detail Linked'!$E$5:$E$97,"") | C11: =IF(SUMIFS('Wage Detail Linked'!$O$5:$O$97,'Wage Detail Linked'!$B$5:$B$97,$A11,'Wage Detail Linked'!$C$5:$C$97,B$2,'Wage Detail Linked'!$E$5:$E$97,"")=0,IF(B11>0,ROUND(B11*90,2),0),ROUND(SUMIFS('Wage Detail Linked'!$R$5:$R$97,'Wage Detail Linked'!$B$5:$B$97,$A11,'Wage Detail Linked'!$C$5:$C$97,B$2,'Wage Detail Linked'!$E$5:$E$97,"")*B11/SUMIFS('Wage Detail Linked'!$O$5:$O$97,'Wage Detail Linked'!$B$5:$B$97,$A11,'Wage Detail Linked'!$C$5:$C$97,B$2,'Wage Detail Linked'!$E$5:$E$97,""),2)) | D11: =SUMIFS('Wage Detail Linked'!$O$5:$O$97,'Wage Detail Linked'!$B$5:$B$97,$A11,'Wage Detail Linked'!$C$5:$C$97,D$2,'Wage Detail Linked'!$E$5:$E$97,"") | E11: =IF(SUMIFS('Wage Detail Linked'!$O$5:$O$97,'Wage Detail Linked'!$B$5:$B$97,$A11,'Wage Detail Linked'!$C$5:$C$97,D$2,'Wage Detail Linked'!$E$5:$E$97,"")=0,IF(D11>0,ROUND(D11*90,2),0),ROUND(SUMIFS('Wage Detail Linked'!$R$5:$R$97,'Wage Detail Linked'!$B$5:$B$97,$A11,'Wage Detail Linked'!$C$5:$C$97,D$2,'Wage Detail Linked'!$E$5:$E$97,"")*D11/SUMIFS('Wage Detail Linked'!$O$5:$O$97,'Wage Detail Linked'!$B$5:$B$97,$A11,'Wage Detail Linked'!$C$5:$C$97,D$2,'Wage Detail Linked'!$E$5:$E$97,""),2)) | F11: =SUMIFS('Wage Detail Linked'!$O$5:$O$97,'Wage Detail Linked'!$B$5:$B$97,$A11,'Wage Detail Linked'!$C$5:$C$97,F$2,'Wage Detail Linked'!$E$5:$E$97,"") | G11: =IF(SUMIFS('Wage Detail Linked'!$O$5:$O$97,'Wage Detail Linked'!$B$5:$B$97,$A11,'Wage Detail Linked'!$C$5:$C$97,F$2,'Wage Detail Linked'!$E$5:$E$97,"")=0,IF(F11>0,ROUND(F11*90,2),0),ROUND(SUMIFS('Wage Detail Linked'!$R$5:$R$97,'Wage Detail Linked'!$B$5:$B$97,$A11,'Wage Detail Linked'!$C$5:$C$97,F$2,'Wage Detail Linked'!$E$5:$E$97,"")*F11/SUMIFS('Wage Detail Linked'!$O$5:$O$97,'Wage Detail Linked'!$B$5:$B$97,$A11,'Wage Detail Linked'!$C$5:$C$97,F$2,'Wage Detail Linked'!$E$5:$E$97,""),2)) | H11: =SUMIFS('Wage Detail Linked'!$O$5:$O$97,'Wage Detail Linked'!$B$5:$B$97,$A11,'Wage Detail Linked'!$C$5:$C$97,H$2,'Wage Detail Linked'!$E$5:$E$97,"") | I11: =IF(SUMIFS('Wage Detail Linked'!$O$5:$O$97,'Wage Detail Linked'!$B$5:$B$97,$A11,'Wage Detail Linked'!$C$5:$C$97,H$2,'Wage Detail Linked'!$E$5:$E$97,"")=0,IF(H11>0,ROUND(H11*90,2),0),ROUND(SUMIFS('Wage Detail Linked'!$R$5:$R$97,'Wage Detail Linked'!$B$5:$B$97,$A11,'Wage Detail Linked'!$C$5:$C$97,H$2,'Wage Detail Linked'!$E$5:$E$97,"")*H11/SUMIFS('Wage Detail Linked'!$O$5:$O$97,'Wage Detail Linked'!$B$5:$B$97,$A11,'Wage Detail Linked'!$C$5:$C$97,H$2,'Wage Detail Linked'!$E$5:$E$97,""),2)) | J11: =SUMIFS('Wage Detail Linked'!$O$5:$O$97,'Wage Detail Linked'!$B$5:$B$97,$A11,'Wage Detail Linked'!$C$5:$C$97,J$2,'Wage Detail Linked'!$E$5:$E$97,"") | K11: =IF(SUMIFS('Wage Detail Linked'!$O$5:$O$97,'Wage Detail Linked'!$B$5:$B$97,$A11,'Wage Detail Linked'!$C$5:$C$97,J$2,'Wage Detail Linked'!$E$5:$E$97,"")=0,IF(J11>0,ROUND(J11*90,2),0),ROUND(SUMIFS('Wage Detail Linked'!$R$5:$R$97,'Wage Detail Linked'!$B$5:$B$97,$A11,'Wage Detail Linked'!$C$5:$C$97,J$2,'Wage Detail Linked'!$E$5:$E$97,"")*J11/SUMIFS('Wage Detail Linked'!$O$5:$O$97,'Wage Detail Linked'!$B$5:$B$97,$A11,'Wage Detail Linked'!$C$5:$C$97,J$2,'Wage Detail Linked'!$E$5:$E$97,""),2)) | L11: =SUMIFS('Wage Detail Linked'!$O$5:$O$97,'Wage Detail Linked'!$B$5:$B$97,$A11,'Wage Detail Linked'!$C$5:$C$97,L$2,'Wage Detail Linked'!$E$5:$E$97,"") | M11: =IF(SUMIFS('Wage Detail Linked'!$O$5:$O$97,'Wage Detail Linked'!$B$5:$B$97,$A11,'Wage Detail Linked'!$C$5:$C$97,L$2,'Wage Detail Linked'!$E$5:$E$97,"")=0,IF(L11>0,ROUND(L11*90,2),0),ROUND(SUMIFS('Wage Detail Linked'!$R$5:$R$97,'Wage Detail Linked'!$B$5:$B$97,$A11,'Wage Detail Linked'!$C$5:$C$97,L$2,'Wage Detail Linked'!$E$5:$E$97,"")*L11/SUMIFS('Wage Detail Linked'!$O$5:$O$97,'Wage Detail Linked'!$B$5:$B$97,$A11,'Wage Detail Linked'!$C$5:$C$97,L$2,'Wage Detail Linked'!$E$5:$E$97,""),2)) | N11: =SUMIFS('Wage Detail Linked'!$O$5:$O$97,'Wage Detail Linked'!$B$5:$B$97,$A11,'Wage Detail Linked'!$C$5:$C$97,N$2,'Wage Detail Linked'!$E$5:$E$97,"") | O11: =IF(SUMIFS('Wage Detail Linked'!$O$5:$O$97,'Wage Detail Linked'!$B$5:$B$97,$A11,'Wage Detail Linked'!$C$5:$C$97,N$2,'Wage Detail Linked'!$E$5:$E$97,"")=0,IF(N11>0,ROUND(N11*90,2),0),ROUND(SUMIFS('Wage Detail Linked'!$R$5:$R$97,'Wage Detail Linked'!$B$5:$B$97,$A11,'Wage Detail Linked'!$C$5:$C$97,N$2,'Wage Detail Linked'!$E$5:$E$97,"")*N11/SUMIFS('Wage Detail Linked'!$O$5:$O$97,'Wage Detail Linked'!$B$5:$B$97,$A11,'Wage Detail Linked'!$C$5:$C$97,N$2,'Wage Detail Linked'!$E$5:$E$97,""),2)) | P11: ='Missed Shifts'!C27 | Q11: =IF('Missed Shifts'!C27=0,IF(P11>0,ROUND(P11*90,2),0),ROUND('Missed Shifts'!D27*P11/'Missed Shifts'!C27,2)) | R11: =SUM(B11,D11,F11,H11,J11,L11,N11,P11) | S11: =SUM(C11,E11,G11,I11,K11,M11,O11,Q11) | T11: 0 | U11: 0 | V11: =MAX(0,T11-U11) | W11: 0 | X11: 0 | Y11: =MAX(0,0-X11) | Z11: =U11+X11 | AA11: =MAX(0,S11-Z11)
A12: Lebo Lebo | B12: =SUMIFS('Wage Detail Linked'!$O$5:$O$97,'Wage Detail Linked'!$B$5:$B$97,$A12,'Wage Detail Linked'!$C$5:$C$97,B$2,'Wage Detail Linked'!$E$5:$E$97,"") | C12: =IF(SUMIFS('Wage Detail Linked'!$O$5:$O$97,'Wage Detail Linked'!$B$5:$B$97,$A12,'Wage Detail Linked'!$C$5:$C$97,B$2,'Wage Detail Linked'!$E$5:$E$97,"")=0,IF(B12>0,ROUND(B12*90,2),0),ROUND(SUMIFS('Wage Detail Linked'!$R$5:$R$97,'Wage Detail Linked'!$B$5:$B$97,$A12,'Wage Detail Linked'!$C$5:$C$97,B$2,'Wage Detail Linked'!$E$5:$E$97,"")*B12/SUMIFS('Wage Detail Linked'!$O$5:$O$97,'Wage Detail Linked'!$B$5:$B$97,$A12,'Wage Detail Linked'!$C$5:$C$97,B$2,'Wage Detail Linked'!$E$5:$E$97,""),2)) | D12: =SUMIFS('Wage Detail Linked'!$O$5:$O$97,'Wage Detail Linked'!$B$5:$B$97,$A12,'Wage Detail Linked'!$C$5:$C$97,D$2,'Wage Detail Linked'!$E$5:$E$97,"") | E12: =IF(SUMIFS('Wage Detail Linked'!$O$5:$O$97,'Wage Detail Linked'!$B$5:$B$97,$A12,'Wage Detail Linked'!$C$5:$C$97,D$2,'Wage Detail Linked'!$E$5:$E$97,"")=0,IF(D12>0,ROUND(D12*90,2),0),ROUND(SUMIFS('Wage Detail Linked'!$R$5:$R$97,'Wage Detail Linked'!$B$5:$B$97,$A12,'Wage Detail Linked'!$C$5:$C$97,D$2,'Wage Detail Linked'!$E$5:$E$97,"")*D12/SUMIFS('Wage Detail Linked'!$O$5:$O$97,'Wage Detail Linked'!$B$5:$B$97,$A12,'Wage Detail Linked'!$C$5:$C$97,D$2,'Wage Detail Linked'!$E$5:$E$97,""),2)) | F12: =SUMIFS('Wage Detail Linked'!$O$5:$O$97,'Wage Detail Linked'!$B$5:$B$97,$A12,'Wage Detail Linked'!$C$5:$C$97,F$2,'Wage Detail Linked'!$E$5:$E$97,"") | G12: =IF(SUMIFS('Wage Detail Linked'!$O$5:$O$97,'Wage Detail Linked'!$B$5:$B$97,$A12,'Wage Detail Linked'!$C$5:$C$97,F$2,'Wage Detail Linked'!$E$5:$E$97,"")=0,IF(F12>0,ROUND(F12*90,2),0),ROUND(SUMIFS('Wage Detail Linked'!$R$5:$R$97,'Wage Detail Linked'!$B$5:$B$97,$A12,'Wage Detail Linked'!$C$5:$C$97,F$2,'Wage Detail Linked'!$E$5:$E$97,"")*F12/SUMIFS('Wage Detail Linked'!$O$5:$O$97,'Wage Detail Linked'!$B$5:$B$97,$A12,'Wage Detail Linked'!$C$5:$C$97,F$2,'Wage Detail Linked'!$E$5:$E$97,""),2)) | H12: =SUMIFS('Wage Detail Linked'!$O$5:$O$97,'Wage Detail Linked'!$B$5:$B$97,$A12,'Wage Detail Linked'!$C$5:$C$97,H$2,'Wage Detail Linked'!$E$5:$E$97,"") | I12: =IF(SUMIFS('Wage Detail Linked'!$O$5:$O$97,'Wage Detail Linked'!$B$5:$B$97,$A12,'Wage Detail Linked'!$C$5:$C$97,H$2,'Wage Detail Linked'!$E$5:$E$97,"")=0,IF(H12>0,ROUND(H12*90,2),0),ROUND(SUMIFS('Wage Detail Linked'!$R$5:$R$97,'Wage Detail Linked'!$B$5:$B$97,$A12,'Wage Detail Linked'!$C$5:$C$97,H$2,'Wage Detail Linked'!$E$5:$E$97,"")*H12/SUMIFS('Wage Detail Linked'!$O$5:$O$97,'Wage Detail Linked'!$B$5:$B$97,$A12,'Wage Detail Linked'!$C$5:$C$97,H$2,'Wage Detail Linked'!$E$5:$E$97,""),2)) | J12: =SUMIFS('Wage Detail Linked'!$O$5:$O$97,'Wage Detail Linked'!$B$5:$B$97,$A12,'Wage Detail Linked'!$C$5:$C$97,J$2,'Wage Detail Linked'!$E$5:$E$97,"") | K12: =IF(SUMIFS('Wage Detail Linked'!$O$5:$O$97,'Wage Detail Linked'!$B$5:$B$97,$A12,'Wage Detail Linked'!$C$5:$C$97,J$2,'Wage Detail Linked'!$E$5:$E$97,"")=0,IF(J12>0,ROUND(J12*90,2),0),ROUND(SUMIFS('Wage Detail Linked'!$R$5:$R$97,'Wage Detail Linked'!$B$5:$B$97,$A12,'Wage Detail Linked'!$C$5:$C$97,J$2,'Wage Detail Linked'!$E$5:$E$97,"")*J12/SUMIFS('Wage Detail Linked'!$O$5:$O$97,'Wage Detail Linked'!$B$5:$B$97,$A12,'Wage Detail Linked'!$C$5:$C$97,J$2,'Wage Detail Linked'!$E$5:$E$97,""),2)) | L12: =SUMIFS('Wage Detail Linked'!$O$5:$O$97,'Wage Detail Linked'!$B$5:$B$97,$A12,'Wage Detail Linked'!$C$5:$C$97,L$2,'Wage Detail Linked'!$E$5:$E$97,"") | M12: =IF(SUMIFS('Wage Detail Linked'!$O$5:$O$97,'Wage Detail Linked'!$B$5:$B$97,$A12,'Wage Detail Linked'!$C$5:$C$97,L$2,'Wage Detail Linked'!$E$5:$E$97,"")=0,IF(L12>0,ROUND(L12*90,2),0),ROUND(SUMIFS('Wage Detail Linked'!$R$5:$R$97,'Wage Detail Linked'!$B$5:$B$97,$A12,'Wage Detail Linked'!$C$5:$C$97,L$2,'Wage Detail Linked'!$E$5:$E$97,"")*L12/SUMIFS('Wage Detail Linked'!$O$5:$O$97,'Wage Detail Linked'!$B$5:$B$97,$A12,'Wage Detail Linked'!$C$5:$C$97,L$2,'Wage Detail Linked'!$E$5:$E$97,""),2)) | N12: =SUMIFS('Wage Detail Linked'!$O$5:$O$97,'Wage Detail Linked'!$B$5:$B$97,$A12,'Wage Detail Linked'!$C$5:$C$97,N$2,'Wage Detail Linked'!$E$5:$E$97,"") | O12: =IF(SUMIFS('Wage Detail Linked'!$O$5:$O$97,'Wage Detail Linked'!$B$5:$B$97,$A12,'Wage Detail Linked'!$C$5:$C$97,N$2,'Wage Detail Linked'!$E$5:$E$97,"")=0,IF(N12>0,ROUND(N12*90,2),0),ROUND(SUMIFS('Wage Detail Linked'!$R$5:$R$97,'Wage Detail Linked'!$B$5:$B$97,$A12,'Wage Detail Linked'!$C$5:$C$97,N$2,'Wage Detail Linked'!$E$5:$E$97,"")*N12/SUMIFS('Wage Detail Linked'!$O$5:$O$97,'Wage Detail Linked'!$B$5:$B$97,$A12,'Wage Detail Linked'!$C$5:$C$97,N$2,'Wage Detail Linked'!$E$5:$E$97,""),2)) | P12: =0 | Q12: =IF(P12>0,ROUND(P12*90,2),0) | R12: =SUM(B12,D12,F12,H12,J12,L12,N12,P12) | S12: =SUM(C12,E12,G12,I12,K12,M12,O12,Q12) | T12: 0 | U12: 0 | V12: =MAX(0,T12-U12) | W12: 0 | X12: 0 | Y12: =MAX(0,0-X12) | Z12: =U12+X12 | AA12: =MAX(0,S12-Z12)
A13: Patrick Ngozo | B13: =SUMIFS('Wage Detail Linked'!$O$5:$O$97,'Wage Detail Linked'!$B$5:$B$97,$A13,'Wage Detail Linked'!$C$5:$C$97,B$2,'Wage Detail Linked'!$E$5:$E$97,"") | C13: =IF(SUMIFS('Wage Detail Linked'!$O$5:$O$97,'Wage Detail Linked'!$B$5:$B$97,$A13,'Wage Detail Linked'!$C$5:$C$97,B$2,'Wage Detail Linked'!$E$5:$E$97,"")=0,IF(B13>0,ROUND(B13*90,2),0),ROUND(SUMIFS('Wage Detail Linked'!$R$5:$R$97,'Wage Detail Linked'!$B$5:$B$97,$A13,'Wage Detail Linked'!$C$5:$C$97,B$2,'Wage Detail Linked'!$E$5:$E$97,"")*B13/SUMIFS('Wage Detail Linked'!$O$5:$O$97,'Wage Detail Linked'!$B$5:$B$97,$A13,'Wage Detail Linked'!$C$5:$C$97,B$2,'Wage Detail Linked'!$E$5:$E$97,""),2)) | D13: =SUMIFS('Wage Detail Linked'!$O$5:$O$97,'Wage Detail Linked'!$B$5:$B$97,$A13,'Wage Detail Linked'!$C$5:$C$97,D$2,'Wage Detail Linked'!$E$5:$E$97,"") | E13: =IF(SUMIFS('Wage Detail Linked'!$O$5:$O$97,'Wage Detail Linked'!$B$5:$B$97,$A13,'Wage Detail Linked'!$C$5:$C$97,D$2,'Wage Detail Linked'!$E$5:$E$97,"")=0,IF(D13>0,ROUND(D13*90,2),0),ROUND(SUMIFS('Wage Detail Linked'!$R$5:$R$97,'Wage Detail Linked'!$B$5:$B$97,$A13,'Wage Detail Linked'!$C$5:$C$97,D$2,'Wage Detail Linked'!$E$5:$E$97,"")*D13/SUMIFS('Wage Detail Linked'!$O$5:$O$97,'Wage Detail Linked'!$B$5:$B$97,$A13,'Wage Detail Linked'!$C$5:$C$97,D$2,'Wage Detail Linked'!$E$5:$E$97,""),2)) | F13: =SUMIFS('Wage Detail Linked'!$O$5:$O$97,'Wage Detail Linked'!$B$5:$B$97,$A13,'Wage Detail Linked'!$C$5:$C$97,F$2,'Wage Detail Linked'!$E$5:$E$97,"") | G13: =IF(SUMIFS('Wage Detail Linked'!$O$5:$O$97,'Wage Detail Linked'!$B$5:$B$97,$A13,'Wage Detail Linked'!$C$5:$C$97,F$2,'Wage Detail Linked'!$E$5:$E$97,"")=0,IF(F13>0,ROUND(F13*90,2),0),ROUND(SUMIFS('Wage Detail Linked'!$R$5:$R$97,'Wage Detail Linked'!$B$5:$B$97,$A13,'Wage Detail Linked'!$C$5:$C$97,F$2,'Wage Detail Linked'!$E$5:$E$97,"")*F13/SUMIFS('Wage Detail Linked'!$O$5:$O$97,'Wage Detail Linked'!$B$5:$B$97,$A13,'Wage Detail Linked'!$C$5:$C$97,F$2,'Wage Detail Linked'!$E$5:$E$97,""),2)) | H13: =SUMIFS('Wage Detail Linked'!$O$5:$O$97,'Wage Detail Linked'!$B$5:$B$97,$A13,'Wage Detail Linked'!$C$5:$C$97,H$2,'Wage Detail Linked'!$E$5:$E$97,"") | I13: =IF(SUMIFS('Wage Detail Linked'!$O$5:$O$97,'Wage Detail Linked'!$B$5:$B$97,$A13,'Wage Detail Linked'!$C$5:$C$97,H$2,'Wage Detail Linked'!$E$5:$E$97,"")=0,IF(H13>0,ROUND(H13*90,2),0),ROUND(SUMIFS('Wage Detail Linked'!$R$5:$R$97,'Wage Detail Linked'!$B$5:$B$97,$A13,'Wage Detail Linked'!$C$5:$C$97,H$2,'Wage Detail Linked'!$E$5:$E$97,"")*H13/SUMIFS('Wage Detail Linked'!$O$5:$O$97,'Wage Detail Linked'!$B$5:$B$97,$A13,'Wage Detail Linked'!$C$5:$C$97,H$2,'Wage Detail Linked'!$E$5:$E$97,""),2)) | J13: =SUMIFS('Wage Detail Linked'!$O$5:$O$97,'Wage Detail Linked'!$B$5:$B$97,$A13,'Wage Detail Linked'!$C$5:$C$97,J$2,'Wage Detail Linked'!$E$5:$E$97,"") | K13: =IF(SUMIFS('Wage Detail Linked'!$O$5:$O$97,'Wage Detail Linked'!$B$5:$B$97,$A13,'Wage Detail Linked'!$C$5:$C$97,J$2,'Wage Detail Linked'!$E$5:$E$97,"")=0,IF(J13>0,ROUND(J13*90,2),0),ROUND(SUMIFS('Wage Detail Linked'!$R$5:$R$97,'Wage Detail Linked'!$B$5:$B$97,$A13,'Wage Detail Linked'!$C$5:$C$97,J$2,'Wage Detail Linked'!$E$5:$E$97,"")*J13/SUMIFS('Wage Detail Linked'!$O$5:$O$97,'Wage Detail Linked'!$B$5:$B$97,$A13,'Wage Detail Linked'!$C$5:$C$97,J$2,'Wage Detail Linked'!$E$5:$E$97,""),2)) | L13: =SUMIFS('Wage Detail Linked'!$O$5:$O$97,'Wage Detail Linked'!$B$5:$B$97,$A13,'Wage Detail Linked'!$C$5:$C$97,L$2,'Wage Detail Linked'!$E$5:$E$97,"") | M13: =IF(SUMIFS('Wage Detail Linked'!$O$5:$O$97,'Wage Detail Linked'!$B$5:$B$97,$A13,'Wage Detail Linked'!$C$5:$C$97,L$2,'Wage Detail Linked'!$E$5:$E$97,"")=0,IF(L13>0,ROUND(L13*90,2),0),ROUND(SUMIFS('Wage Detail Linked'!$R$5:$R$97,'Wage Detail Linked'!$B$5:$B$97,$A13,'Wage Detail Linked'!$C$5:$C$97,L$2,'Wage Detail Linked'!$E$5:$E$97,"")*L13/SUMIFS('Wage Detail Linked'!$O$5:$O$97,'Wage Detail Linked'!$B$5:$B$97,$A13,'Wage Detail Linked'!$C$5:$C$97,L$2,'Wage Detail Linked'!$E$5:$E$97,""),2)) | N13: =SUMIFS('Wage Detail Linked'!$O$5:$O$97,'Wage Detail Linked'!$B$5:$B$97,$A13,'Wage Detail Linked'!$C$5:$C$97,N$2,'Wage Detail Linked'!$E$5:$E$97,"") | O13: =IF(SUMIFS('Wage Detail Linked'!$O$5:$O$97,'Wage Detail Linked'!$B$5:$B$97,$A13,'Wage Detail Linked'!$C$5:$C$97,N$2,'Wage Detail Linked'!$E$5:$E$97,"")=0,IF(N13>0,ROUND(N13*90,2),0),ROUND(SUMIFS('Wage Detail Linked'!$R$5:$R$97,'Wage Detail Linked'!$B$5:$B$97,$A13,'Wage Detail Linked'!$C$5:$C$97,N$2,'Wage Detail Linked'!$E$5:$E$97,"")*N13/SUMIFS('Wage Detail Linked'!$O$5:$O$97,'Wage Detail Linked'!$B$5:$B$97,$A13,'Wage Detail Linked'!$C$5:$C$97,N$2,'Wage Detail Linked'!$E$5:$E$97,""),2)) | P13: ='Missed Shifts'!C32 | Q13: =IF('Missed Shifts'!C32=0,IF(P13>0,ROUND(P13*90,2),0),ROUND('Missed Shifts'!D32*P13/'Missed Shifts'!C32,2)) | R13: =SUM(B13,D13,F13,H13,J13,L13,N13,P13) | S13: =SUM(C13,E13,G13,I13,K13,M13,O13,Q13) | T13: 0 | U13: 0 | V13: =MAX(0,T13-U13) | W13: 0 | X13: 0 | Y13: =MAX(0,0-X13) | Z13: =U13+X13 | AA13: =MAX(0,S13-Z13)
A14: Sharleen Ndlovu | B14: =SUMIFS('Wage Detail Linked'!$O$5:$O$97,'Wage Detail Linked'!$B$5:$B$97,$A14,'Wage Detail Linked'!$C$5:$C$97,B$2,'Wage Detail Linked'!$E$5:$E$97,"") | C14: =IF(SUMIFS('Wage Detail Linked'!$O$5:$O$97,'Wage Detail Linked'!$B$5:$B$97,$A14,'Wage Detail Linked'!$C$5:$C$97,B$2,'Wage Detail Linked'!$E$5:$E$97,"")=0,IF(B14>0,ROUND(B14*90,2),0),ROUND(SUMIFS('Wage Detail Linked'!$R$5:$R$97,'Wage Detail Linked'!$B$5:$B$97,$A14,'Wage Detail Linked'!$C$5:$C$97,B$2,'Wage Detail Linked'!$E$5:$E$97,"")*B14/SUMIFS('Wage Detail Linked'!$O$5:$O$97,'Wage Detail Linked'!$B$5:$B$97,$A14,'Wage Detail Linked'!$C$5:$C$97,B$2,'Wage Detail Linked'!$E$5:$E$97,""),2)) | D14: =SUMIFS('Wage Detail Linked'!$O$5:$O$97,'Wage Detail Linked'!$B$5:$B$97,$A14,'Wage Detail Linked'!$C$5:$C$97,D$2,'Wage Detail Linked'!$E$5:$E$97,"") | E14: =IF(SUMIFS('Wage Detail Linked'!$O$5:$O$97,'Wage Detail Linked'!$B$5:$B$97,$A14,'Wage Detail Linked'!$C$5:$C$97,D$2,'Wage Detail Linked'!$E$5:$E$97,"")=0,IF(D14>0,ROUND(D14*90,2),0),ROUND(SUMIFS('Wage Detail Linked'!$R$5:$R$97,'Wage Detail Linked'!$B$5:$B$97,$A14,'Wage Detail Linked'!$C$5:$C$97,D$2,'Wage Detail Linked'!$E$5:$E$97,"")*D14/SUMIFS('Wage Detail Linked'!$O$5:$O$97,'Wage Detail Linked'!$B$5:$B$97,$A14,'Wage Detail Linked'!$C$5:$C$97,D$2,'Wage Detail Linked'!$E$5:$E$97,""),2)) | F14: =SUMIFS('Wage Detail Linked'!$O$5:$O$97,'Wage Detail Linked'!$B$5:$B$97,$A14,'Wage Detail Linked'!$C$5:$C$97,F$2,'Wage Detail Linked'!$E$5:$E$97,"") | G14: =IF(SUMIFS('Wage Detail Linked'!$O$5:$O$97,'Wage Detail Linked'!$B$5:$B$97,$A14,'Wage Detail Linked'!$C$5:$C$97,F$2,'Wage Detail Linked'!$E$5:$E$97,"")=0,IF(F14>0,ROUND(F14*90,2),0),ROUND(SUMIFS('Wage Detail Linked'!$R$5:$R$97,'Wage Detail Linked'!$B$5:$B$97,$A14,'Wage Detail Linked'!$C$5:$C$97,F$2,'Wage Detail Linked'!$E$5:$E$97,"")*F14/SUMIFS('Wage Detail Linked'!$O$5:$O$97,'Wage Detail Linked'!$B$5:$B$97,$A14,'Wage Detail Linked'!$C$5:$C$97,F$2,'Wage Detail Linked'!$E$5:$E$97,""),2)) | H14: =SUMIFS('Wage Detail Linked'!$O$5:$O$97,'Wage Detail Linked'!$B$5:$B$97,$A14,'Wage Detail Linked'!$C$5:$C$97,H$2,'Wage Detail Linked'!$E$5:$E$97,"") | I14: =IF(SUMIFS('Wage Detail Linked'!$O$5:$O$97,'Wage Detail Linked'!$B$5:$B$97,$A14,'Wage Detail Linked'!$C$5:$C$97,H$2,'Wage Detail Linked'!$E$5:$E$97,"")=0,IF(H14>0,ROUND(H14*90,2),0),ROUND(SUMIFS('Wage Detail Linked'!$R$5:$R$97,'Wage Detail Linked'!$B$5:$B$97,$A14,'Wage Detail Linked'!$C$5:$C$97,H$2,'Wage Detail Linked'!$E$5:$E$97,"")*H14/SUMIFS('Wage Detail Linked'!$O$5:$O$97,'Wage Detail Linked'!$B$5:$B$97,$A14,'Wage Detail Linked'!$C$5:$C$97,H$2,'Wage Detail Linked'!$E$5:$E$97,""),2)) | J14: =SUMIFS('Wage Detail Linked'!$O$5:$O$97,'Wage Detail Linked'!$B$5:$B$97,$A14,'Wage Detail Linked'!$C$5:$C$97,J$2,'Wage Detail Linked'!$E$5:$E$97,"") | K14: =IF(SUMIFS('Wage Detail Linked'!$O$5:$O$97,'Wage Detail Linked'!$B$5:$B$97,$A14,'Wage Detail Linked'!$C$5:$C$97,J$2,'Wage Detail Linked'!$E$5:$E$97,"")=0,IF(J14>0,ROUND(J14*90,2),0),ROUND(SUMIFS('Wage Detail Linked'!$R$5:$R$97,'Wage Detail Linked'!$B$5:$B$97,$A14,'Wage Detail Linked'!$C$5:$C$97,J$2,'Wage Detail Linked'!$E$5:$E$97,"")*J14/SUMIFS('Wage Detail Linked'!$O$5:$O$97,'Wage Detail Linked'!$B$5:$B$97,$A14,'Wage Detail Linked'!$C$5:$C$97,J$2,'Wage Detail Linked'!$E$5:$E$97,""),2)) | L14: =SUMIFS('Wage Detail Linked'!$O$5:$O$97,'Wage Detail Linked'!$B$5:$B$97,$A14,'Wage Detail Linked'!$C$5:$C$97,L$2,'Wage Detail Linked'!$E$5:$E$97,"") | M14: =IF(SUMIFS('Wage Detail Linked'!$O$5:$O$97,'Wage Detail Linked'!$B$5:$B$97,$A14,'Wage Detail Linked'!$C$5:$C$97,L$2,'Wage Detail Linked'!$E$5:$E$97,"")=0,IF(L14>0,ROUND(L14*90,2),0),ROUND(SUMIFS('Wage Detail Linked'!$R$5:$R$97,'Wage Detail Linked'!$B$5:$B$97,$A14,'Wage Detail Linked'!$C$5:$C$97,L$2,'Wage Detail Linked'!$E$5:$E$97,"")*L14/SUMIFS('Wage Detail Linked'!$O$5:$O$97,'Wage Detail Linked'!$B$5:$B$97,$A14,'Wage Detail Linked'!$C$5:$C$97,L$2,'Wage Detail Linked'!$E$5:$E$97,""),2)) | N14: =SUMIFS('Wage Detail Linked'!$O$5:$O$97,'Wage Detail Linked'!$B$5:$B$97,$A14,'Wage Detail Linked'!$C$5:$C$97,N$2,'Wage Detail Linked'!$E$5:$E$97,"") | O14: =IF(SUMIFS('Wage Detail Linked'!$O$5:$O$97,'Wage Detail Linked'!$B$5:$B$97,$A14,'Wage Detail Linked'!$C$5:$C$97,N$2,'Wage Detail Linked'!$E$5:$E$97,"")=0,IF(N14>0,ROUND(N14*90,2),0),ROUND(SUMIFS('Wage Detail Linked'!$R$5:$R$97,'Wage Detail Linked'!$B$5:$B$97,$A14,'Wage Detail Linked'!$C$5:$C$97,N$2,'Wage Detail Linked'!$E$5:$E$97,"")*N14/SUMIFS('Wage Detail Linked'!$O$5:$O$97,'Wage Detail Linked'!$B$5:$B$97,$A14,'Wage Detail Linked'!$C$5:$C$97,N$2,'Wage Detail Linked'!$E$5:$E$97,""),2)) | P14: =0 | Q14: =IF(P14>0,ROUND(P14*90,2),0) | R14: =SUM(B14,D14,F14,H14,J14,L14,N14,P14) | S14: 3000 | T14: 0 | U14: 0 | V14: =MAX(0,T14-U14) | W14: 0 | X14: 0 | Y14: =MAX(0,0-X14) | Z14: =U14+X14 | AA14: =MAX(0,S14-Z14)
A15: Solomon Moyo | B15: =SUMIFS('Wage Detail Linked'!$O$5:$O$97,'Wage Detail Linked'!$B$5:$B$97,$A15,'Wage Detail Linked'!$C$5:$C$97,B$2,'Wage Detail Linked'!$E$5:$E$97,"") | C15: =IF(SUMIFS('Wage Detail Linked'!$O$5:$O$97,'Wage Detail Linked'!$B$5:$B$97,$A15,'Wage Detail Linked'!$C$5:$C$97,B$2,'Wage Detail Linked'!$E$5:$E$97,"")=0,IF(B15>0,ROUND(B15*90,2),0),ROUND(SUMIFS('Wage Detail Linked'!$R$5:$R$97,'Wage Detail Linked'!$B$5:$B$97,$A15,'Wage Detail Linked'!$C$5:$C$97,B$2,'Wage Detail Linked'!$E$5:$E$97,"")*B15/SUMIFS('Wage Detail Linked'!$O$5:$O$97,'Wage Detail Linked'!$B$5:$B$97,$A15,'Wage Detail Linked'!$C$5:$C$97,B$2,'Wage Detail Linked'!$E$5:$E$97,""),2)) | D15: =SUMIFS('Wage Detail Linked'!$O$5:$O$97,'Wage Detail Linked'!$B$5:$B$97,$A15,'Wage Detail Linked'!$C$5:$C$97,D$2,'Wage Detail Linked'!$E$5:$E$97,"") | E15: =IF(SUMIFS('Wage Detail Linked'!$O$5:$O$97,'Wage Detail Linked'!$B$5:$B$97,$A15,'Wage Detail Linked'!$C$5:$C$97,D$2,'Wage Detail Linked'!$E$5:$E$97,"")=0,IF(D15>0,ROUND(D15*90,2),0),ROUND(SUMIFS('Wage Detail Linked'!$R$5:$R$97,'Wage Detail Linked'!$B$5:$B$97,$A15,'Wage Detail Linked'!$C$5:$C$97,D$2,'Wage Detail Linked'!$E$5:$E$97,"")*D15/SUMIFS('Wage Detail Linked'!$O$5:$O$97,'Wage Detail Linked'!$B$5:$B$97,$A15,'Wage Detail Linked'!$C$5:$C$97,D$2,'Wage Detail Linked'!$E$5:$E$97,""),2)) | F15: =SUMIFS('Wage Detail Linked'!$O$5:$O$97,'Wage Detail Linked'!$B$5:$B$97,$A15,'Wage Detail Linked'!$C$5:$C$97,F$2,'Wage Detail Linked'!$E$5:$E$97,"") | G15: =IF(SUMIFS('Wage Detail Linked'!$O$5:$O$97,'Wage Detail Linked'!$B$5:$B$97,$A15,'Wage Detail Linked'!$C$5:$C$97,F$2,'Wage Detail Linked'!$E$5:$E$97,"")=0,IF(F15>0,ROUND(F15*90,2),0),ROUND(SUMIFS('Wage Detail Linked'!$R$5:$R$97,'Wage Detail Linked'!$B$5:$B$97,$A15,'Wage Detail Linked'!$C$5:$C$97,F$2,'Wage Detail Linked'!$E$5:$E$97,"")*F15/SUMIFS('Wage Detail Linked'!$O$5:$O$97,'Wage Detail Linked'!$B$5:$B$97,$A15,'Wage Detail Linked'!$C$5:$C$97,F$2,'Wage Detail Linked'!$E$5:$E$97,""),2)) | H15: =SUMIFS('Wage Detail Linked'!$O$5:$O$97,'Wage Detail Linked'!$B$5:$B$97,$A15,'Wage Detail Linked'!$C$5:$C$97,H$2,'Wage Detail Linked'!$E$5:$E$97,"") | I15: =IF(SUMIFS('Wage Detail Linked'!$O$5:$O$97,'Wage Detail Linked'!$B$5:$B$97,$A15,'Wage Detail Linked'!$C$5:$C$97,H$2,'Wage Detail Linked'!$E$5:$E$97,"")=0,IF(H15>0,ROUND(H15*90,2),0),ROUND(SUMIFS('Wage Detail Linked'!$R$5:$R$97,'Wage Detail Linked'!$B$5:$B$97,$A15,'Wage Detail Linked'!$C$5:$C$97,H$2,'Wage Detail Linked'!$E$5:$E$97,"")*H15/SUMIFS('Wage Detail Linked'!$O$5:$O$97,'Wage Detail Linked'!$B$5:$B$97,$A15,'Wage Detail Linked'!$C$5:$C$97,H$2,'Wage Detail Linked'!$E$5:$E$97,""),2)) | J15: =SUMIFS('Wage Detail Linked'!$O$5:$O$97,'Wage Detail Linked'!$B$5:$B$97,$A15,'Wage Detail Linked'!$C$5:$C$97,J$2,'Wage Detail Linked'!$E$5:$E$97,"") | K15: =IF(SUMIFS('Wage Detail Linked'!$O$5:$O$97,'Wage Detail Linked'!$B$5:$B$97,$A15,'Wage Detail Linked'!$C$5:$C$97,J$2,'Wage Detail Linked'!$E$5:$E$97,"")=0,IF(J15>0,ROUND(J15*90,2),0),ROUND(SUMIFS('Wage Detail Linked'!$R$5:$R$97,'Wage Detail Linked'!$B$5:$B$97,$A15,'Wage Detail Linked'!$C$5:$C$97,J$2,'Wage Detail Linked'!$E$5:$E$97,"")*J15/SUMIFS('Wage Detail Linked'!$O$5:$O$97,'Wage Detail Linked'!$B$5:$B$97,$A15,'Wage Detail Linked'!$C$5:$C$97,J$2,'Wage Detail Linked'!$E$5:$E$97,""),2)) | L15: =SUMIFS('Wage Detail Linked'!$O$5:$O$97,'Wage Detail Linked'!$B$5:$B$97,$A15,'Wage Detail Linked'!$C$5:$C$97,L$2,'Wage Detail Linked'!$E$5:$E$97,"") | M15: =IF(SUMIFS('Wage Detail Linked'!$O$5:$O$97,'Wage Detail Linked'!$B$5:$B$97,$A15,'Wage Detail Linked'!$C$5:$C$97,L$2,'Wage Detail Linked'!$E$5:$E$97,"")=0,IF(L15>0,ROUND(L15*90,2),0),ROUND(SUMIFS('Wage Detail Linked'!$R$5:$R$97,'Wage Detail Linked'!$B$5:$B$97,$A15,'Wage Detail Linked'!$C$5:$C$97,L$2,'Wage Detail Linked'!$E$5:$E$97,"")*L15/SUMIFS('Wage Detail Linked'!$O$5:$O$97,'Wage Detail Linked'!$B$5:$B$97,$A15,'Wage Detail Linked'!$C$5:$C$97,L$2,'Wage Detail Linked'!$E$5:$E$97,""),2)) | N15: =SUMIFS('Wage Detail Linked'!$O$5:$O$97,'Wage Detail Linked'!$B$5:$B$97,$A15,'Wage Detail Linked'!$C$5:$C$97,N$2,'Wage Detail Linked'!$E$5:$E$97,"") | O15: =IF(SUMIFS('Wage Detail Linked'!$O$5:$O$97,'Wage Detail Linked'!$B$5:$B$97,$A15,'Wage Detail Linked'!$C$5:$C$97,N$2,'Wage Detail Linked'!$E$5:$E$97,"")=0,IF(N15>0,ROUND(N15*90,2),0),ROUND(SUMIFS('Wage Detail Linked'!$R$5:$R$97,'Wage Detail Linked'!$B$5:$B$97,$A15,'Wage Detail Linked'!$C$5:$C$97,N$2,'Wage Detail Linked'!$E$5:$E$97,"")*N15/SUMIFS('Wage Detail Linked'!$O$5:$O$97,'Wage Detail Linked'!$B$5:$B$97,$A15,'Wage Detail Linked'!$C$5:$C$97,N$2,'Wage Detail Linked'!$E$5:$E$97,""),2)) | P15: ='Missed Shifts'!C36 | Q15: =IF('Missed Shifts'!C36=0,IF(P15>0,ROUND(P15*90,2),0),ROUND('Missed Shifts'!D36*P15/'Missed Shifts'!C36,2)) | R15: =SUM(B15,D15,F15,H15,J15,L15,N15,P15) | S15: =SUM(C15,E15,G15,I15,K15,M15,O15,Q15) | T15: 0 | U15: 0 | V15: =MAX(0,T15-U15) | W15: 0 | X15: 0 | Y15: =MAX(0,0-X15) | Z15: =U15+X15 | AA15: =MAX(0,S15-Z15)
A16: Takavaudza Chokuda | B16: =SUMIFS('Wage Detail Linked'!$O$5:$O$97,'Wage Detail Linked'!$B$5:$B$97,$A16,'Wage Detail Linked'!$C$5:$C$97,B$2,'Wage Detail Linked'!$E$5:$E$97,"") | C16: =IF(SUMIFS('Wage Detail Linked'!$O$5:$O$97,'Wage Detail Linked'!$B$5:$B$97,$A16,'Wage Detail Linked'!$C$5:$C$97,B$2,'Wage Detail Linked'!$E$5:$E$97,"")=0,IF(B16>0,ROUND(B16*90,2),0),ROUND(SUMIFS('Wage Detail Linked'!$R$5:$R$97,'Wage Detail Linked'!$B$5:$B$97,$A16,'Wage Detail Linked'!$C$5:$C$97,B$2,'Wage Detail Linked'!$E$5:$E$97,"")*B16/SUMIFS('Wage Detail Linked'!$O$5:$O$97,'Wage Detail Linked'!$B$5:$B$97,$A16,'Wage Detail Linked'!$C$5:$C$97,B$2,'Wage Detail Linked'!$E$5:$E$97,""),2)) | D16: =SUMIFS('Wage Detail Linked'!$O$5:$O$97,'Wage Detail Linked'!$B$5:$B$97,$A16,'Wage Detail Linked'!$C$5:$C$97,D$2,'Wage Detail Linked'!$E$5:$E$97,"") | E16: =IF(SUMIFS('Wage Detail Linked'!$O$5:$O$97,'Wage Detail Linked'!$B$5:$B$97,$A16,'Wage Detail Linked'!$C$5:$C$97,D$2,'Wage Detail Linked'!$E$5:$E$97,"")=0,IF(D16>0,ROUND(D16*90,2),0),ROUND(SUMIFS('Wage Detail Linked'!$R$5:$R$97,'Wage Detail Linked'!$B$5:$B$97,$A16,'Wage Detail Linked'!$C$5:$C$97,D$2,'Wage Detail Linked'!$E$5:$E$97,"")*D16/SUMIFS('Wage Detail Linked'!$O$5:$O$97,'Wage Detail Linked'!$B$5:$B$97,$A16,'Wage Detail Linked'!$C$5:$C$97,D$2,'Wage Detail Linked'!$E$5:$E$97,""),2)) | F16: =SUMIFS('Wage Detail Linked'!$O$5:$O$97,'Wage Detail Linked'!$B$5:$B$97,$A16,'Wage Detail Linked'!$C$5:$C$97,F$2,'Wage Detail Linked'!$E$5:$E$97,"") | G16: =IF(SUMIFS('Wage Detail Linked'!$O$5:$O$97,'Wage Detail Linked'!$B$5:$B$97,$A16,'Wage Detail Linked'!$C$5:$C$97,F$2,'Wage Detail Linked'!$E$5:$E$97,"")=0,IF(F16>0,ROUND(F16*90,2),0),ROUND(SUMIFS('Wage Detail Linked'!$R$5:$R$97,'Wage Detail Linked'!$B$5:$B$97,$A16,'Wage Detail Linked'!$C$5:$C$97,F$2,'Wage Detail Linked'!$E$5:$E$97,"")*F16/SUMIFS('Wage Detail Linked'!$O$5:$O$97,'Wage Detail Linked'!$B$5:$B$97,$A16,'Wage Detail Linked'!$C$5:$C$97,F$2,'Wage Detail Linked'!$E$5:$E$97,""),2)) | H16: =SUMIFS('Wage Detail Linked'!$O$5:$O$97,'Wage Detail Linked'!$B$5:$B$97,$A16,'Wage Detail Linked'!$C$5:$C$97,H$2,'Wage Detail Linked'!$E$5:$E$97,"") | I16: =IF(SUMIFS('Wage Detail Linked'!$O$5:$O$97,'Wage Detail Linked'!$B$5:$B$97,$A16,'Wage Detail Linked'!$C$5:$C$97,H$2,'Wage Detail Linked'!$E$5:$E$97,"")=0,IF(H16>0,ROUND(H16*90,2),0),ROUND(SUMIFS('Wage Detail Linked'!$R$5:$R$97,'Wage Detail Linked'!$B$5:$B$97,$A16,'Wage Detail Linked'!$C$5:$C$97,H$2,'Wage Detail Linked'!$E$5:$E$97,"")*H16/SUMIFS('Wage Detail Linked'!$O$5:$O$97,'Wage Detail Linked'!$B$5:$B$97,$A16,'Wage Detail Linked'!$C$5:$C$97,H$2,'Wage Detail Linked'!$E$5:$E$97,""),2)) | J16: =SUMIFS('Wage Detail Linked'!$O$5:$O$97,'Wage Detail Linked'!$B$5:$B$97,$A16,'Wage Detail Linked'!$C$5:$C$97,J$2,'Wage Detail Linked'!$E$5:$E$97,"") | K16: =IF(SUMIFS('Wage Detail Linked'!$O$5:$O$97,'Wage Detail Linked'!$B$5:$B$97,$A16,'Wage Detail Linked'!$C$5:$C$97,J$2,'Wage Detail Linked'!$E$5:$E$97,"")=0,IF(J16>0,ROUND(J16*90,2),0),ROUND(SUMIFS('Wage Detail Linked'!$R$5:$R$97,'Wage Detail Linked'!$B$5:$B$97,$A16,'Wage Detail Linked'!$C$5:$C$97,J$2,'Wage Detail Linked'!$E$5:$E$97,"")*J16/SUMIFS('Wage Detail Linked'!$O$5:$O$97,'Wage Detail Linked'!$B$5:$B$97,$A16,'Wage Detail Linked'!$C$5:$C$97,J$2,'Wage Detail Linked'!$E$5:$E$97,""),2)) | L16: =SUMIFS('Wage Detail Linked'!$O$5:$O$97,'Wage Detail Linked'!$B$5:$B$97,$A16,'Wage Detail Linked'!$C$5:$C$97,L$2,'Wage Detail Linked'!$E$5:$E$97,"") | M16: =IF(SUMIFS('Wage Detail Linked'!$O$5:$O$97,'Wage Detail Linked'!$B$5:$B$97,$A16,'Wage Detail Linked'!$C$5:$C$97,L$2,'Wage Detail Linked'!$E$5:$E$97,"")=0,IF(L16>0,ROUND(L16*90,2),0),ROUND(SUMIFS('Wage Detail Linked'!$R$5:$R$97,'Wage Detail Linked'!$B$5:$B$97,$A16,'Wage Detail Linked'!$C$5:$C$97,L$2,'Wage Detail Linked'!$E$5:$E$97,"")*L16/SUMIFS('Wage Detail Linked'!$O$5:$O$97,'Wage Detail Linked'!$B$5:$B$97,$A16,'Wage Detail Linked'!$C$5:$C$97,L$2,'Wage Detail Linked'!$E$5:$E$97,""),2)) | N16: =SUMIFS('Wage Detail Linked'!$O$5:$O$97,'Wage Detail Linked'!$B$5:$B$97,$A16,'Wage Detail Linked'!$C$5:$C$97,N$2,'Wage Detail Linked'!$E$5:$E$97,"") | O16: =IF(SUMIFS('Wage Detail Linked'!$O$5:$O$97,'Wage Detail Linked'!$B$5:$B$97,$A16,'Wage Detail Linked'!$C$5:$C$97,N$2,'Wage Detail Linked'!$E$5:$E$97,"")=0,IF(N16>0,ROUND(N16*90,2),0),ROUND(SUMIFS('Wage Detail Linked'!$R$5:$R$97,'Wage Detail Linked'!$B$5:$B$97,$A16,'Wage Detail Linked'!$C$5:$C$97,N$2,'Wage Detail Linked'!$E$5:$E$97,"")*N16/SUMIFS('Wage Detail Linked'!$O$5:$O$97,'Wage Detail Linked'!$B$5:$B$97,$A16,'Wage Detail Linked'!$C$5:$C$97,N$2,'Wage Detail Linked'!$E$5:$E$97,""),2)) | P16: ='Missed Shifts'!C39 | Q16: =IF('Missed Shifts'!C39=0,IF(P16>0,ROUND(P16*90,2),0),ROUND('Missed Shifts'!D39*P16/'Missed Shifts'!C39,2)) | R16: =SUM(B16,D16,F16,H16,J16,L16,N16,P16) | S16: =SUM(C16,E16,G16,I16,K16,M16,O16,Q16) | T16: 0 | U16: 0 | V16: =MAX(0,T16-U16) | W16: 0 | X16: 0 | Y16: =MAX(0,0-X16) | Z16: =U16+X16 | AA16: =MAX(0,S16-Z16)
A17: Thandanani Nkala | B17: =SUMIFS('Wage Detail Linked'!$O$5:$O$97,'Wage Detail Linked'!$B$5:$B$97,$A17,'Wage Detail Linked'!$C$5:$C$97,B$2,'Wage Detail Linked'!$E$5:$E$97,"") | C17: =IF(SUMIFS('Wage Detail Linked'!$O$5:$O$97,'Wage Detail Linked'!$B$5:$B$97,$A17,'Wage Detail Linked'!$C$5:$C$97,B$2,'Wage Detail Linked'!$E$5:$E$97,"")=0,IF(B17>0,ROUND(B17*90,2),0),ROUND(SUMIFS('Wage Detail Linked'!$R$5:$R$97,'Wage Detail Linked'!$B$5:$B$97,$A17,'Wage Detail Linked'!$C$5:$C$97,B$2,'Wage Detail Linked'!$E$5:$E$97,"")*B17/SUMIFS('Wage Detail Linked'!$O$5:$O$97,'Wage Detail Linked'!$B$5:$B$97,$A17,'Wage Detail Linked'!$C$5:$C$97,B$2,'Wage Detail Linked'!$E$5:$E$97,""),2)) | D17: =SUMIFS('Wage Detail Linked'!$O$5:$O$97,'Wage Detail Linked'!$B$5:$B$97,$A17,'Wage Detail Linked'!$C$5:$C$97,D$2,'Wage Detail Linked'!$E$5:$E$97,"") | E17: =IF(SUMIFS('Wage Detail Linked'!$O$5:$O$97,'Wage Detail Linked'!$B$5:$B$97,$A17,'Wage Detail Linked'!$C$5:$C$97,D$2,'Wage Detail Linked'!$E$5:$E$97,"")=0,IF(D17>0,ROUND(D17*90,2),0),ROUND(SUMIFS('Wage Detail Linked'!$R$5:$R$97,'Wage Detail Linked'!$B$5:$B$97,$A17,'Wage Detail Linked'!$C$5:$C$97,D$2,'Wage Detail Linked'!$E$5:$E$97,"")*D17/SUMIFS('Wage Detail Linked'!$O$5:$O$97,'Wage Detail Linked'!$B$5:$B$97,$A17,'Wage Detail Linked'!$C$5:$C$97,D$2,'Wage Detail Linked'!$E$5:$E$97,""),2)) | F17: =SUMIFS('Wage Detail Linked'!$O$5:$O$97,'Wage Detail Linked'!$B$5:$B$97,$A17,'Wage Detail Linked'!$C$5:$C$97,F$2,'Wage Detail Linked'!$E$5:$E$97,"") | G17: =IF(SUMIFS('Wage Detail Linked'!$O$5:$O$97,'Wage Detail Linked'!$B$5:$B$97,$A17,'Wage Detail Linked'!$C$5:$C$97,F$2,'Wage Detail Linked'!$E$5:$E$97,"")=0,IF(F17>0,ROUND(F17*90,2),0),ROUND(SUMIFS('Wage Detail Linked'!$R$5:$R$97,'Wage Detail Linked'!$B$5:$B$97,$A17,'Wage Detail Linked'!$C$5:$C$97,F$2,'Wage Detail Linked'!$E$5:$E$97,"")*F17/SUMIFS('Wage Detail Linked'!$O$5:$O$97,'Wage Detail Linked'!$B$5:$B$97,$A17,'Wage Detail Linked'!$C$5:$C$97,F$2,'Wage Detail Linked'!$E$5:$E$97,""),2)) | H17: =SUMIFS('Wage Detail Linked'!$O$5:$O$97,'Wage Detail Linked'!$B$5:$B$97,$A17,'Wage Detail Linked'!$C$5:$C$97,H$2,'Wage Detail Linked'!$E$5:$E$97,"") | I17: =IF(SUMIFS('Wage Detail Linked'!$O$5:$O$97,'Wage Detail Linked'!$B$5:$B$97,$A17,'Wage Detail Linked'!$C$5:$C$97,H$2,'Wage Detail Linked'!$E$5:$E$97,"")=0,IF(H17>0,ROUND(H17*90,2),0),ROUND(SUMIFS('Wage Detail Linked'!$R$5:$R$97,'Wage Detail Linked'!$B$5:$B$97,$A17,'Wage Detail Linked'!$C$5:$C$97,H$2,'Wage Detail Linked'!$E$5:$E$97,"")*H17/SUMIFS('Wage Detail Linked'!$O$5:$O$97,'Wage Detail Linked'!$B$5:$B$97,$A17,'Wage Detail Linked'!$C$5:$C$97,H$2,'Wage Detail Linked'!$E$5:$E$97,""),2)) | J17: =SUMIFS('Wage Detail Linked'!$O$5:$O$97,'Wage Detail Linked'!$B$5:$B$97,$A17,'Wage Detail Linked'!$C$5:$C$97,J$2,'Wage Detail Linked'!$E$5:$E$97,"") | K17: =IF(SUMIFS('Wage Detail Linked'!$O$5:$O$97,'Wage Detail Linked'!$B$5:$B$97,$A17,'Wage Detail Linked'!$C$5:$C$97,J$2,'Wage Detail Linked'!$E$5:$E$97,"")=0,IF(J17>0,ROUND(J17*90,2),0),ROUND(SUMIFS('Wage Detail Linked'!$R$5:$R$97,'Wage Detail Linked'!$B$5:$B$97,$A17,'Wage Detail Linked'!$C$5:$C$97,J$2,'Wage Detail Linked'!$E$5:$E$97,"")*J17/SUMIFS('Wage Detail Linked'!$O$5:$O$97,'Wage Detail Linked'!$B$5:$B$97,$A17,'Wage Detail Linked'!$C$5:$C$97,J$2,'Wage Detail Linked'!$E$5:$E$97,""),2)) | L17: =SUMIFS('Wage Detail Linked'!$O$5:$O$97,'Wage Detail Linked'!$B$5:$B$97,$A17,'Wage Detail Linked'!$C$5:$C$97,L$2,'Wage Detail Linked'!$E$5:$E$97,"") | M17: =IF(SUMIFS('Wage Detail Linked'!$O$5:$O$97,'Wage Detail Linked'!$B$5:$B$97,$A17,'Wage Detail Linked'!$C$5:$C$97,L$2,'Wage Detail Linked'!$E$5:$E$97,"")=0,IF(L17>0,ROUND(L17*90,2),0),ROUND(SUMIFS('Wage Detail Linked'!$R$5:$R$97,'Wage Detail Linked'!$B$5:$B$97,$A17,'Wage Detail Linked'!$C$5:$C$97,L$2,'Wage Detail Linked'!$E$5:$E$97,"")*L17/SUMIFS('Wage Detail Linked'!$O$5:$O$97,'Wage Detail Linked'!$B$5:$B$97,$A17,'Wage Detail Linked'!$C$5:$C$97,L$2,'Wage Detail Linked'!$E$5:$E$97,""),2)) | N17: =SUMIFS('Wage Detail Linked'!$O$5:$O$97,'Wage Detail Linked'!$B$5:$B$97,$A17,'Wage Detail Linked'!$C$5:$C$97,N$2,'Wage Detail Linked'!$E$5:$E$97,"") | O17: =IF(SUMIFS('Wage Detail Linked'!$O$5:$O$97,'Wage Detail Linked'!$B$5:$B$97,$A17,'Wage Detail Linked'!$C$5:$C$97,N$2,'Wage Detail Linked'!$E$5:$E$97,"")=0,IF(N17>0,ROUND(N17*90,2),0),ROUND(SUMIFS('Wage Detail Linked'!$R$5:$R$97,'Wage Detail Linked'!$B$5:$B$97,$A17,'Wage Detail Linked'!$C$5:$C$97,N$2,'Wage Detail Linked'!$E$5:$E$97,"")*N17/SUMIFS('Wage Detail Linked'!$O$5:$O$97,'Wage Detail Linked'!$B$5:$B$97,$A17,'Wage Detail Linked'!$C$5:$C$97,N$2,'Wage Detail Linked'!$E$5:$E$97,""),2)) | P17: =0 | Q17: =IF(P17>0,ROUND(P17*90,2),0) | R17: =SUM(B17,D17,F17,H17,J17,L17,N17,P17) | S17: =SUM(C17,E17,G17,I17,K17,M17,O17,Q17) | T17: 0 | U17: 0 | V17: =MAX(0,T17-U17) | W17: 0 | X17: 0 | Y17: =MAX(0,0-X17) | Z17: =U17+X17 | AA17: =MAX(0,S17-Z17)
A18: Thina Dyani | B18: =SUMIFS('Wage Detail Linked'!$O$5:$O$97,'Wage Detail Linked'!$B$5:$B$97,$A18,'Wage Detail Linked'!$C$5:$C$97,B$2,'Wage Detail Linked'!$E$5:$E$97,"") | C18: =IF(SUMIFS('Wage Detail Linked'!$O$5:$O$97,'Wage Detail Linked'!$B$5:$B$97,$A18,'Wage Detail Linked'!$C$5:$C$97,B$2,'Wage Detail Linked'!$E$5:$E$97,"")=0,IF(B18>0,ROUND(B18*90,2),0),ROUND(SUMIFS('Wage Detail Linked'!$R$5:$R$97,'Wage Detail Linked'!$B$5:$B$97,$A18,'Wage Detail Linked'!$C$5:$C$97,B$2,'Wage Detail Linked'!$E$5:$E$97,"")*B18/SUMIFS('Wage Detail Linked'!$O$5:$O$97,'Wage Detail Linked'!$B$5:$B$97,$A18,'Wage Detail Linked'!$C$5:$C$97,B$2,'Wage Detail Linked'!$E$5:$E$97,""),2)) | D18: =SUMIFS('Wage Detail Linked'!$O$5:$O$97,'Wage Detail Linked'!$B$5:$B$97,$A18,'Wage Detail Linked'!$C$5:$C$97,D$2,'Wage Detail Linked'!$E$5:$E$97,"") | E18: =IF(SUMIFS('Wage Detail Linked'!$O$5:$O$97,'Wage Detail Linked'!$B$5:$B$97,$A18,'Wage Detail Linked'!$C$5:$C$97,D$2,'Wage Detail Linked'!$E$5:$E$97,"")=0,IF(D18>0,ROUND(D18*90,2),0),ROUND(SUMIFS('Wage Detail Linked'!$R$5:$R$97,'Wage Detail Linked'!$B$5:$B$97,$A18,'Wage Detail Linked'!$C$5:$C$97,D$2,'Wage Detail Linked'!$E$5:$E$97,"")*D18/SUMIFS('Wage Detail Linked'!$O$5:$O$97,'Wage Detail Linked'!$B$5:$B$97,$A18,'Wage Detail Linked'!$C$5:$C$97,D$2,'Wage Detail Linked'!$E$5:$E$97,""),2)) | F18: =SUMIFS('Wage Detail Linked'!$O$5:$O$97,'Wage Detail Linked'!$B$5:$B$97,$A18,'Wage Detail Linked'!$C$5:$C$97,F$2,'Wage Detail Linked'!$E$5:$E$97,"") | G18: =IF(SUMIFS('Wage Detail Linked'!$O$5:$O$97,'Wage Detail Linked'!$B$5:$B$97,$A18,'Wage Detail Linked'!$C$5:$C$97,F$2,'Wage Detail Linked'!$E$5:$E$97,"")=0,IF(F18>0,ROUND(F18*90,2),0),ROUND(SUMIFS('Wage Detail Linked'!$R$5:$R$97,'Wage Detail Linked'!$B$5:$B$97,$A18,'Wage Detail Linked'!$C$5:$C$97,F$2,'Wage Detail Linked'!$E$5:$E$97,"")*F18/SUMIFS('Wage Detail Linked'!$O$5:$O$97,'Wage Detail Linked'!$B$5:$B$97,$A18,'Wage Detail Linked'!$C$5:$C$97,F$2,'Wage Detail Linked'!$E$5:$E$97,""),2)) | H18: =SUMIFS('Wage Detail Linked'!$O$5:$O$97,'Wage Detail Linked'!$B$5:$B$97,$A18,'Wage Detail Linked'!$C$5:$C$97,H$2,'Wage Detail Linked'!$E$5:$E$97,"") | I18: =IF(SUMIFS('Wage Detail Linked'!$O$5:$O$97,'Wage Detail Linked'!$B$5:$B$97,$A18,'Wage Detail Linked'!$C$5:$C$97,H$2,'Wage Detail Linked'!$E$5:$E$97,"")=0,IF(H18>0,ROUND(H18*90,2),0),ROUND(SUMIFS('Wage Detail Linked'!$R$5:$R$97,'Wage Detail Linked'!$B$5:$B$97,$A18,'Wage Detail Linked'!$C$5:$C$97,H$2,'Wage Detail Linked'!$E$5:$E$97,"")*H18/SUMIFS('Wage Detail Linked'!$O$5:$O$97,'Wage Detail Linked'!$B$5:$B$97,$A18,'Wage Detail Linked'!$C$5:$C$97,H$2,'Wage Detail Linked'!$E$5:$E$97,""),2)) | J18: =SUMIFS('Wage Detail Linked'!$O$5:$O$97,'Wage Detail Linked'!$B$5:$B$97,$A18,'Wage Detail Linked'!$C$5:$C$97,J$2,'Wage Detail Linked'!$E$5:$E$97,"") | K18: =IF(SUMIFS('Wage Detail Linked'!$O$5:$O$97,'Wage Detail Linked'!$B$5:$B$97,$A18,'Wage Detail Linked'!$C$5:$C$97,J$2,'Wage Detail Linked'!$E$5:$E$97,"")=0,IF(J18>0,ROUND(J18*90,2),0),ROUND(SUMIFS('Wage Detail Linked'!$R$5:$R$97,'Wage Detail Linked'!$B$5:$B$97,$A18,'Wage Detail Linked'!$C$5:$C$97,J$2,'Wage Detail Linked'!$E$5:$E$97,"")*J18/SUMIFS('Wage Detail Linked'!$O$5:$O$97,'Wage Detail Linked'!$B$5:$B$97,$A18,'Wage Detail Linked'!$C$5:$C$97,J$2,'Wage Detail Linked'!$E$5:$E$97,""),2)) | L18: =SUMIFS('Wage Detail Linked'!$O$5:$O$97,'Wage Detail Linked'!$B$5:$B$97,$A18,'Wage Detail Linked'!$C$5:$C$97,L$2,'Wage Detail Linked'!$E$5:$E$97,"") | M18: =IF(SUMIFS('Wage Detail Linked'!$O$5:$O$97,'Wage Detail Linked'!$B$5:$B$97,$A18,'Wage Detail Linked'!$C$5:$C$97,L$2,'Wage Detail Linked'!$E$5:$E$97,"")=0,IF(L18>0,ROUND(L18*90,2),0),ROUND(SUMIFS('Wage Detail Linked'!$R$5:$R$97,'Wage Detail Linked'!$B$5:$B$97,$A18,'Wage Detail Linked'!$C$5:$C$97,L$2,'Wage Detail Linked'!$E$5:$E$97,"")*L18/SUMIFS('Wage Detail Linked'!$O$5:$O$97,'Wage Detail Linked'!$B$5:$B$97,$A18,'Wage Detail Linked'!$C$5:$C$97,L$2,'Wage Detail Linked'!$E$5:$E$97,""),2)) | N18: =SUMIFS('Wage Detail Linked'!$O$5:$O$97,'Wage Detail Linked'!$B$5:$B$97,$A18,'Wage Detail Linked'!$C$5:$C$97,N$2,'Wage Detail Linked'!$E$5:$E$97,"") | O18: =IF(SUMIFS('Wage Detail Linked'!$O$5:$O$97,'Wage Detail Linked'!$B$5:$B$97,$A18,'Wage Detail Linked'!$C$5:$C$97,N$2,'Wage Detail Linked'!$E$5:$E$97,"")=0,IF(N18>0,ROUND(N18*90,2),0),ROUND(SUMIFS('Wage Detail Linked'!$R$5:$R$97,'Wage Detail Linked'!$B$5:$B$97,$A18,'Wage Detail Linked'!$C$5:$C$97,N$2,'Wage Detail Linked'!$E$5:$E$97,"")*N18/SUMIFS('Wage Detail Linked'!$O$5:$O$97,'Wage Detail Linked'!$B$5:$B$97,$A18,'Wage Detail Linked'!$C$5:$C$97,N$2,'Wage Detail Linked'!$E$5:$E$97,""),2)) | P18: ='Missed Shifts'!C42 | Q18: =IF('Missed Shifts'!C42=0,IF(P18>0,ROUND(P18*90,2),0),ROUND('Missed Shifts'!D42*P18/'Missed Shifts'!C42,2)) | R18: =SUM(B18,D18,F18,H18,J18,L18,N18,P18) | S18: =SUM(C18,E18,G18,I18,K18,M18,O18,Q18) | T18: 0 | U18: 0 | V18: =MAX(0,T18-U18) | W18: 0 | X18: 0 | Y18: =MAX(0,0-X18) | Z18: =U18+X18 | AA18: =MAX(0,S18-Z18)
A19: Tsotlego Petrus Malakoane | B19: =SUMIFS('Wage Detail Linked'!$O$5:$O$97,'Wage Detail Linked'!$B$5:$B$97,$A19,'Wage Detail Linked'!$C$5:$C$97,B$2,'Wage Detail Linked'!$E$5:$E$97,"") | C19: =IF(SUMIFS('Wage Detail Linked'!$O$5:$O$97,'Wage Detail Linked'!$B$5:$B$97,$A19,'Wage Detail Linked'!$C$5:$C$97,B$2,'Wage Detail Linked'!$E$5:$E$97,"")=0,IF(B19>0,ROUND(B19*90,2),0),ROUND(SUMIFS('Wage Detail Linked'!$R$5:$R$97,'Wage Detail Linked'!$B$5:$B$97,$A19,'Wage Detail Linked'!$C$5:$C$97,B$2,'Wage Detail Linked'!$E$5:$E$97,"")*B19/SUMIFS('Wage Detail Linked'!$O$5:$O$97,'Wage Detail Linked'!$B$5:$B$97,$A19,'Wage Detail Linked'!$C$5:$C$97,B$2,'Wage Detail Linked'!$E$5:$E$97,""),2)) | D19: =SUMIFS('Wage Detail Linked'!$O$5:$O$97,'Wage Detail Linked'!$B$5:$B$97,$A19,'Wage Detail Linked'!$C$5:$C$97,D$2,'Wage Detail Linked'!$E$5:$E$97,"") | E19: =IF(SUMIFS('Wage Detail Linked'!$O$5:$O$97,'Wage Detail Linked'!$B$5:$B$97,$A19,'Wage Detail Linked'!$C$5:$C$97,D$2,'Wage Detail Linked'!$E$5:$E$97,"")=0,IF(D19>0,ROUND(D19*90,2),0),ROUND(SUMIFS('Wage Detail Linked'!$R$5:$R$97,'Wage Detail Linked'!$B$5:$B$97,$A19,'Wage Detail Linked'!$C$5:$C$97,D$2,'Wage Detail Linked'!$E$5:$E$97,"")*D19/SUMIFS('Wage Detail Linked'!$O$5:$O$97,'Wage Detail Linked'!$B$5:$B$97,$A19,'Wage Detail Linked'!$C$5:$C$97,D$2,'Wage Detail Linked'!$E$5:$E$97,""),2)) | F19: =SUMIFS('Wage Detail Linked'!$O$5:$O$97,'Wage Detail Linked'!$B$5:$B$97,$A19,'Wage Detail Linked'!$C$5:$C$97,F$2,'Wage Detail Linked'!$E$5:$E$97,"") | G19: =IF(SUMIFS('Wage Detail Linked'!$O$5:$O$97,'Wage Detail Linked'!$B$5:$B$97,$A19,'Wage Detail Linked'!$C$5:$C$97,F$2,'Wage Detail Linked'!$E$5:$E$97,"")=0,IF(F19>0,ROUND(F19*90,2),0),ROUND(SUMIFS('Wage Detail Linked'!$R$5:$R$97,'Wage Detail Linked'!$B$5:$B$97,$A19,'Wage Detail Linked'!$C$5:$C$97,F$2,'Wage Detail Linked'!$E$5:$E$97,"")*F19/SUMIFS('Wage Detail Linked'!$O$5:$O$97,'Wage Detail Linked'!$B$5:$B$97,$A19,'Wage Detail Linked'!$C$5:$C$97,F$2,'Wage Detail Linked'!$E$5:$E$97,""),2)) | H19: =SUMIFS('Wage Detail Linked'!$O$5:$O$97,'Wage Detail Linked'!$B$5:$B$97,$A19,'Wage Detail Linked'!$C$5:$C$97,H$2,'Wage Detail Linked'!$E$5:$E$97,"") | I19: =IF(SUMIFS('Wage Detail Linked'!$O$5:$O$97,'Wage Detail Linked'!$B$5:$B$97,$A19,'Wage Detail Linked'!$C$5:$C$97,H$2,'Wage Detail Linked'!$E$5:$E$97,"")=0,IF(H19>0,ROUND(H19*90,2),0),ROUND(SUMIFS('Wage Detail Linked'!$R$5:$R$97,'Wage Detail Linked'!$B$5:$B$97,$A19,'Wage Detail Linked'!$C$5:$C$97,H$2,'Wage Detail Linked'!$E$5:$E$97,"")*H19/SUMIFS('Wage Detail Linked'!$O$5:$O$97,'Wage Detail Linked'!$B$5:$B$97,$A19,'Wage Detail Linked'!$C$5:$C$97,H$2,'Wage Detail Linked'!$E$5:$E$97,""),2)) | J19: =SUMIFS('Wage Detail Linked'!$O$5:$O$97,'Wage Detail Linked'!$B$5:$B$97,$A19,'Wage Detail Linked'!$C$5:$C$97,J$2,'Wage Detail Linked'!$E$5:$E$97,"") | K19: =IF(SUMIFS('Wage Detail Linked'!$O$5:$O$97,'Wage Detail Linked'!$B$5:$B$97,$A19,'Wage Detail Linked'!$C$5:$C$97,J$2,'Wage Detail Linked'!$E$5:$E$97,"")=0,IF(J19>0,ROUND(J19*90,2),0),ROUND(SUMIFS('Wage Detail Linked'!$R$5:$R$97,'Wage Detail Linked'!$B$5:$B$97,$A19,'Wage Detail Linked'!$C$5:$C$97,J$2,'Wage Detail Linked'!$E$5:$E$97,"")*J19/SUMIFS('Wage Detail Linked'!$O$5:$O$97,'Wage Detail Linked'!$B$5:$B$97,$A19,'Wage Detail Linked'!$C$5:$C$97,J$2,'Wage Detail Linked'!$E$5:$E$97,""),2)) | L19: =SUMIFS('Wage Detail Linked'!$O$5:$O$97,'Wage Detail Linked'!$B$5:$B$97,$A19,'Wage Detail Linked'!$C$5:$C$97,L$2,'Wage Detail Linked'!$E$5:$E$97,"") | M19: =IF(SUMIFS('Wage Detail Linked'!$O$5:$O$97,'Wage Detail Linked'!$B$5:$B$97,$A19,'Wage Detail Linked'!$C$5:$C$97,L$2,'Wage Detail Linked'!$E$5:$E$97,"")=0,IF(L19>0,ROUND(L19*90,2),0),ROUND(SUMIFS('Wage Detail Linked'!$R$5:$R$97,'Wage Detail Linked'!$B$5:$B$97,$A19,'Wage Detail Linked'!$C$5:$C$97,L$2,'Wage Detail Linked'!$E$5:$E$97,"")*L19/SUMIFS('Wage Detail Linked'!$O$5:$O$97,'Wage Detail Linked'!$B$5:$B$97,$A19,'Wage Detail Linked'!$C$5:$C$97,L$2,'Wage Detail Linked'!$E$5:$E$97,""),2)) | N19: =SUMIFS('Wage Detail Linked'!$O$5:$O$97,'Wage Detail Linked'!$B$5:$B$97,$A19,'Wage Detail Linked'!$C$5:$C$97,N$2,'Wage Detail Linked'!$E$5:$E$97,"") | O19: =IF(SUMIFS('Wage Detail Linked'!$O$5:$O$97,'Wage Detail Linked'!$B$5:$B$97,$A19,'Wage Detail Linked'!$C$5:$C$97,N$2,'Wage Detail Linked'!$E$5:$E$97,"")=0,IF(N19>0,ROUND(N19*90,2),0),ROUND(SUMIFS('Wage Detail Linked'!$R$5:$R$97,'Wage Detail Linked'!$B$5:$B$97,$A19,'Wage Detail Linked'!$C$5:$C$97,N$2,'Wage Detail Linked'!$E$5:$E$97,"")*N19/SUMIFS('Wage Detail Linked'!$O$5:$O$97,'Wage Detail Linked'!$B$5:$B$97,$A19,'Wage Detail Linked'!$C$5:$C$97,N$2,'Wage Detail Linked'!$E$5:$E$97,""),2)) | P19: =0 | Q19: =IF(P19>0,ROUND(P19*90,2),0) | R19: =SUM(B19,D19,F19,H19,J19,L19,N19,P19) | S19: =SUM(C19,E19,G19,I19,K19,M19,O19,Q19) | T19: 0 | U19: 0 | V19: =MAX(0,T19-U19) | W19: 0 | X19: 0 | Y19: =MAX(0,0-X19) | Z19: =U19+X19 | AA19: =MAX(0,S19-Z19)
A20: GRAND TOTAL | B20: =SUM(B4:B19) | C20: =SUM(C4:C19) | D20: =SUM(D4:D19) | E20: =SUM(E4:E19) | F20: =SUM(F4:F19) | G20: =SUM(G4:G19) | H20: =SUM(H4:H19) | I20: =SUM(I4:I19) | ... AA20: =SUM(AA4:AA19)

Sheet Auditor Summary
A1: B&W PRODUCTIONS — AUDITOR SUMMARY
A2: Payroll week 2026-09-19 to 2026-09-25. Linked to Auditor Trail Linked; hours and wages include block 6 (Missed Shifts). No bonus columns.
A4: Name | B4: Days Worked | C4: Hours (incl. missed) | D4: Missed Shift Hours | E4: Wages | F4: Fixed Deductions Due | G4: Fixed Deducted | H4: Fixed Outstanding | I4: Additional Loan Due | J4: Additional Loan Deducted | K4: Additional Loan Outstanding | L4: Total Deducted | M4: NET WAGE
A5: Bhekizitha Maphosa | B5: =--('Auditor Trail Linked'!B4>0)+--('Auditor Trail Linked'!D4>0)+--('Auditor Trail Linked'!F4>0)+--('Auditor Trail Linked'!H4>0)+--('Auditor Trail Linked'!J4>0)+--('Auditor Trail Linked'!L4>0)+--('Auditor Trail Linked'!N4>0) | C5: ='Auditor Trail Linked'!R4 | D5: ='Auditor Trail Linked'!P4 | E5: ='Auditor Trail Linked'!S4 | F5: ='Auditor Trail Linked'!T4 | G5: ='Auditor Trail Linked'!U4 | H5: ='Auditor Trail Linked'!V4 | I5: ='Auditor Trail Linked'!W4 | J5: ='Auditor Trail Linked'!X4 | K5: ='Auditor Trail Linked'!Y4 | L5: ='Auditor Trail Linked'!Z4 | M5: ='Auditor Trail Linked'!AA4
A6: Daniel Motaung | B6: =--('Auditor Trail Linked'!B5>0)+--('Auditor Trail Linked'!D5>0)+--('Auditor Trail Linked'!F5>0)+--('Auditor Trail Linked'!H5>0)+--('Auditor Trail Linked'!J5>0)+--('Auditor Trail Linked'!L5>0)+--('Auditor Trail Linked'!N5>0) | C6: ='Auditor Trail Linked'!R5 | D6: ='Auditor Trail Linked'!P5 | E6: ='Auditor Trail Linked'!S5 | F6: ='Auditor Trail Linked'!T5 | G6: ='Auditor Trail Linked'!U5 | H6: ='Auditor Trail Linked'!V5 | I6: ='Auditor Trail Linked'!W5 | J6: ='Auditor Trail Linked'!X5 | K6: ='Auditor Trail Linked'!Y5 | L6: ='Auditor Trail Linked'!Z5 | M6: ='Auditor Trail Linked'!AA5
A7: Erence Mngomezulu | B7: =--('Auditor Trail Linked'!B6>0)+--('Auditor Trail Linked'!D6>0)+--('Auditor Trail Linked'!F6>0)+--('Auditor Trail Linked'!H6>0)+--('Auditor Trail Linked'!J6>0)+--('Auditor Trail Linked'!L6>0)+--('Auditor Trail Linked'!N6>0) | C7: ='Auditor Trail Linked'!R6 | D7: ='Auditor Trail Linked'!P6 | E7: ='Auditor Trail Linked'!S6 | F7: ='Auditor Trail Linked'!T6 | G7: ='Auditor Trail Linked'!U6 | H7: ='Auditor Trail Linked'!V6 | I7: ='Auditor Trail Linked'!W6 | J7: ='Auditor Trail Linked'!X6 | K7: ='Auditor Trail Linked'!Y6 | L7: ='Auditor Trail Linked'!Z6 | M7: ='Auditor Trail Linked'!AA6
A8: Erick Mpho Molefe | B8: =--('Auditor Trail Linked'!B7>0)+--('Auditor Trail Linked'!D7>0)+--('Auditor Trail Linked'!F7>0)+--('Auditor Trail Linked'!H7>0)+--('Auditor Trail Linked'!J7>0)+--('Auditor Trail Linked'!L7>0)+--('Auditor Trail Linked'!N7>0) | C8: ='Auditor Trail Linked'!R7 | D8: ='Auditor Trail Linked'!P7 | E8: ='Auditor Trail Linked'!S7 | F8: ='Auditor Trail Linked'!T7 | G8: ='Auditor Trail Linked'!U7 | H8: ='Auditor Trail Linked'!V7 | I8: ='Auditor Trail Linked'!W7 | J8: ='Auditor Trail Linked'!X7 | K8: ='Auditor Trail Linked'!Y7 | L8: ='Auditor Trail Linked'!Z7 | M8: ='Auditor Trail Linked'!AA7
A9: Givemore Chifetete Kuziwa | B9: =--('Auditor Trail Linked'!B8>0)+--('Auditor Trail Linked'!D8>0)+--('Auditor Trail Linked'!F8>0)+--('Auditor Trail Linked'!H8>0)+--('Auditor Trail Linked'!J8>0)+--('Auditor Trail Linked'!L8>0)+--('Auditor Trail Linked'!N8>0) | C9: ='Auditor Trail Linked'!R8 | D9: ='Auditor Trail Linked'!P8 | E9: ='Auditor Trail Linked'!S8 | F9: ='Auditor Trail Linked'!T8 | G9: ='Auditor Trail Linked'!U8 | H9: ='Auditor Trail Linked'!V8 | I9: ='Auditor Trail Linked'!W8 | J9: ='Auditor Trail Linked'!X8 | K9: ='Auditor Trail Linked'!Y8 | L9: ='Auditor Trail Linked'!Z8 | M9: ='Auditor Trail Linked'!AA8
A10: Isaac Mbele | B10: =--('Auditor Trail Linked'!B9>0)+--('Auditor Trail Linked'!D9>0)+--('Auditor Trail Linked'!F9>0)+--('Auditor Trail Linked'!H9>0)+--('Auditor Trail Linked'!J9>0)+--('Auditor Trail Linked'!L9>0)+--('Auditor Trail Linked'!N9>0) | C10: ='Auditor Trail Linked'!R9 | D10: ='Auditor Trail Linked'!P9 | E10: ='Auditor Trail Linked'!S9 | F10: ='Auditor Trail Linked'!T9 | G10: ='Auditor Trail Linked'!U9 | H10: ='Auditor Trail Linked'!V9 | I10: ='Auditor Trail Linked'!W9 | J10: ='Auditor Trail Linked'!X9 | K10: ='Auditor Trail Linked'!Y9 | L10: ='Auditor Trail Linked'!Z9 | M10: ='Auditor Trail Linked'!AA9
A11: John Simbarashe Mhlanga | B11: =--('Auditor Trail Linked'!B10>0)+--('Auditor Trail Linked'!D10>0)+--('Auditor Trail Linked'!F10>0)+--('Auditor Trail Linked'!H10>0)+--('Auditor Trail Linked'!J10>0)+--('Auditor Trail Linked'!L10>0)+--('Auditor Trail Linked'!N10>0) | C11: ='Auditor Trail Linked'!R10 | D11: ='Auditor Trail Linked'!P10 | E11: ='Auditor Trail Linked'!S10 | F11: ='Auditor Trail Linked'!T10 | G11: ='Auditor Trail Linked'!U10 | H11: ='Auditor Trail Linked'!V10 | I11: ='Auditor Trail Linked'!W10 | J11: ='Auditor Trail Linked'!X10 | K11: ='Auditor Trail Linked'!Y10 | L11: ='Auditor Trail Linked'!Z10 | M11: ='Auditor Trail Linked'!AA10
A12: Joshua Motsamai Nteo | B12: =--('Auditor Trail Linked'!B11>0)+--('Auditor Trail Linked'!D11>0)+--('Auditor Trail Linked'!F11>0)+--('Auditor Trail Linked'!H11>0)+--('Auditor Trail Linked'!J11>0)+--('Auditor Trail Linked'!L11>0)+--('Auditor Trail Linked'!N11>0) | C12: ='Auditor Trail Linked'!R11 | D12: ='Auditor Trail Linked'!P11 | E12: ='Auditor Trail Linked'!S11 | F12: ='Auditor Trail Linked'!T11 | G12: ='Auditor Trail Linked'!U11 | H12: ='Auditor Trail Linked'!V11 | I12: ='Auditor Trail Linked'!W11 | J12: ='Auditor Trail Linked'!X11 | K12: ='Auditor Trail Linked'!Y11 | L12: ='Auditor Trail Linked'!Z11 | M12: ='Auditor Trail Linked'!AA11
A13: Lebo Lebo | B13: =--('Auditor Trail Linked'!B12>0)+--('Auditor Trail Linked'!D12>0)+--('Auditor Trail Linked'!F12>0)+--('Auditor Trail Linked'!H12>0)+--('Auditor Trail Linked'!J12>0)+--('Auditor Trail Linked'!L12>0)+--('Auditor Trail Linked'!N12>0) | C13: ='Auditor Trail Linked'!R12 | D13: ='Auditor Trail Linked'!P12 | E13: ='Auditor Trail Linked'!S12 | F13: ='Auditor Trail Linked'!T12 | G13: ='Auditor Trail Linked'!U12 | H13: ='Auditor Trail Linked'!V12 | I13: ='Auditor Trail Linked'!W12 | J13: ='Auditor Trail Linked'!X12 | K13: ='Auditor Trail Linked'!Y12 | L13: ='Auditor Trail Linked'!Z12 | M13: ='Auditor Trail Linked'!AA12
A14: Patrick Ngozo | B14: =--('Auditor Trail Linked'!B13>0)+--('Auditor Trail Linked'!D13>0)+--('Auditor Trail Linked'!F13>0)+--('Auditor Trail Linked'!H13>0)+--('Auditor Trail Linked'!J13>0)+--('Auditor Trail Linked'!L13>0)+--('Auditor Trail Linked'!N13>0) | C14: ='Auditor Trail Linked'!R13 | D14: ='Auditor Trail Linked'!P13 | E14: ='Auditor Trail Linked'!S13 | F14: ='Auditor Trail Linked'!T13 | G14: ='Auditor Trail Linked'!U13 | H14: ='Auditor Trail Linked'!V13 | I14: ='Auditor Trail Linked'!W13 | J14: ='Auditor Trail Linked'!X13 | K14: ='Auditor Trail Linked'!Y13 | L14: ='Auditor Trail Linked'!Z13 | M14: ='Auditor Trail Linked'!AA13
A15: Sharleen Ndlovu | B15: =--('Auditor Trail Linked'!B14>0)+--('Auditor Trail Linked'!D14>0)+--('Auditor Trail Linked'!F14>0)+--('Auditor Trail Linked'!H14>0)+--('Auditor Trail Linked'!J14>0)+--('Auditor Trail Linked'!L14>0)+--('Auditor Trail Linked'!N14>0) | C15: ='Auditor Trail Linked'!R14 | D15: ='Auditor Trail Linked'!P14 | E15: ='Auditor Trail Linked'!S14 | F15: ='Auditor Trail Linked'!T14 | G15: ='Auditor Trail Linked'!U14 | H15: ='Auditor Trail Linked'!V14 | I15: ='Auditor Trail Linked'!W14 | J15: ='Auditor Trail Linked'!X14 | K15: ='Auditor Trail Linked'!Y14 | L15: ='Auditor Trail Linked'!Z14 | M15: ='Auditor Trail Linked'!AA14
A16: Solomon Moyo | B16: =--('Auditor Trail Linked'!B15>0)+--('Auditor Trail Linked'!D15>0)+--('Auditor Trail Linked'!F15>0)+--('Auditor Trail Linked'!H15>0)+--('Auditor Trail Linked'!J15>0)+--('Auditor Trail Linked'!L15>0)+--('Auditor Trail Linked'!N15>0) | C16: ='Auditor Trail Linked'!R15 | D16: ='Auditor Trail Linked'!P15 | E16: ='Auditor Trail Linked'!S15 | F16: ='Auditor Trail Linked'!T15 | G16: ='Auditor Trail Linked'!U15 | H16: ='Auditor Trail Linked'!V15 | I16: ='Auditor Trail Linked'!W15 | J16: ='Auditor Trail Linked'!X15 | K16: ='Auditor Trail Linked'!Y15 | L16: ='Auditor Trail Linked'!Z15 | M16: ='Auditor Trail Linked'!AA15
... A20: Tsotlego Petrus Malakoane | B20: =--('Auditor Trail Linked'!B19>0)+--('Auditor Trail Linked'!D19>0)+--('Auditor Trail Linked'!F19>0)+--('Auditor Trail Linked'!H19>0)+--('Auditor Trail Linked'!J19>0)+--('Auditor Trail Linked'!L19>0)+--('Auditor Trail Linked'!N19>0) | C20: ='Auditor Trail Linked'!R19 | D20: ='Auditor Trail Linked'!P19 | E20: ='Auditor Trail Linked'!S19 | F20: ='Auditor Trail Linked'!T19 | G20: ='Auditor Trail Linked'!U19 | H20: ='Auditor Trail Linked'!V19 | I20: ='Auditor Trail Linked'!W19 | J20: ='Auditor Trail Linked'!X19 | K20: ='Auditor Trail Linked'!Y19 | L20: ='Auditor Trail Linked'!Z19 | M20: ='Auditor Trail Linked'!AA19
A21: GRAND TOTAL | B21: =SUM(B5:B20) | C21: =SUM(C5:C20) | D21: =SUM(D5:D20) | E21: =SUM(E5:E20) | F21: =SUM(F5:F20) | G21: =SUM(G5:G20) | H21: =SUM(H5:H20) | I21: =SUM(I5:I20) | ... M21: =SUM(M5:M20)

Sheet Flagged - Reviewed
A1: B&W PRODUCTIONS — FLAGGED / REVIEWED
A2: Payroll week 2026-09-19 to 2026-09-25. Every review on a paid shift in this payroll: what the system flagged, and the office decision (name, time, reason). OPEN items first.
A4: Status | B4: Review # | C4: Employee | D4: Date | E4: Shift | F4: Flag | G4: System note | H4: System recommended hours | I4: Claimed hours | J4: Approved hours | K4: Decision | L4: Decided by | M4: Decided at | N4: Reason recorded
A5: RESOLVED | B5: 10027 | C5: Bhekizitha Maphosa | D5: 2026-09-22 | E5: 07:00–16:00 Warehouse loading | F5: Rate choice: Warehouse or Event/Venue | G5: RATE CHOICE NEEDED: the wording mentions "warehouse" but the work type is Normal, so it is not clearly warehouse-only. Bernie must choose Warehouse (R81,25/h, Sunday R97,50, meeting time unpaid) or Venue/Event (R95/h, Sunday R114) before the rate is decided. Until then the shift stays at the engine amount. | I5: 9 | K5: approve original | L5: Bernie Burness | M5: 2026-09-23 06:38:31 | N5: Warehouse rate chosen — shift #9808 R750,00 → R690,63 (Warehouse: 9 h − 0.5 h staff meeting 07:00–07:30 (unpaid, R40,63) = 8.5 h × R81,25)
A6: RESOLVED | B6: 10025 | C6: Bhekizitha Maphosa | D6: 2026-09-23 | E6: 07:00–16:00 Warehouse | F6: Rate choice: Warehouse or Event/Venue | G6: RATE CHOICE NEEDED: the wording mentions "warehouse" but the work type is Normal, so it is not clearly warehouse-only. Bernie must choose Warehouse (R81,25/h, Sunday R97,50, meeting time unpaid) or Venue/Event (R95/h, Sunday R114) before the rate is decided. Until then the shift stays at the engine amount. | I6: 9 | K6: approve original | L6: Bernie Burness | M6: 2026-09-23 06:38:36 | N6: Warehouse rate chosen — shift #9807 R750,00 → R690,63 (Warehouse: 9 h − 0.5 h staff meeting 07:00–07:30 (unpaid, R40,63) = 8.5 h × R81,25)
A7: RESOLVED | B7: 10023 | C7: Bhekizitha Maphosa | D7: 2026-09-24 | E7: 07:00–15:00 Warehouse | F7: Rate choice: Warehouse or Event/Venue | G7: RATE CHOICE NEEDED: the wording mentions "warehouse" but the work type is Normal, so it is not clearly warehouse-only. Bernie must choose Warehouse (R81,25/h, Sunday R97,50, meeting time unpaid) or Venue/Event (R95/h, Sunday R114) before the rate is decided. Until then the shift stays at the engine amount. | I7: 8 | K7: approve original | L7: Bernie Burness | M7: 2026-09-23 06:38:41 | N7: Warehouse rate chosen — shift #9806 R1 620,00 → R0,00 (PUBLIC HOLIDAY — HELD for owner approval — recommended Warehouse public holiday (Heritage Day): 9 h × R162,50 (R81,25 × 2, no meeting deduction) = R1 462,50; R0 until approved)
A8: RESOLVED | B8: 10137 | C8: Bhekizitha Maphosa | D8: 2026-09-24 | E8: 07:00–15:00 Warehouse | F8: Public holiday (Heritage Day) — owner to approve or decline | G8: PUBLIC HOLIDAY — Heritage Day (24 Sep 2026): Bhekizitha Maphosa worked 07:00–16:00. Held for owner approval. | I8: 8 | J8: 7.5 | K8: approve adjusted | L8: Bernie Burness | M8: 2026-09-23 10:28:47 | N8: Public holiday (Heritage Day) approved by Bernie Burness 23 Sep — hours set to 07:00–15:00 (no set-ups): Warehouse public holiday (Heritage Day), owner set hours 07:00–15:00: 8.0 h − 0.5 h staff meeting 07:00–07:30 (unpaid) = 7.5 h × R162,50 (R81,25 × 2) = R1218.75
A9: RESOLVED | B9: 9990 | C9: Daniel Motaung | D9: 2026-09-22 | E9: 07:00–16:00 Warehouse loading | F9: Rate choice: Warehouse or Event/Venue | G9: RATE CHOICE NEEDED: the wording mentions "warehouse" but the work type is Normal, so it is not clearly warehouse-only. Bernie must choose Warehouse (R81,25/h, Sunday R97,50, meeting time unpaid) or Venue/Event (R95/h, Sunday R114) before the rate is decided. Until then the shift stays at the engine amount. | I9: 9 | K9: approve original | L9: Bernie Burness | M9: 2026-09-23 06:39:19 | N9: Warehouse rate chosen — shift #9787 R750,00 → R690,63 (Warehouse: 9 h − 0.5 h staff meeting 07:00–07:30 (unpaid, R40,63) = 8.5 h × R81,25)
A10: RESOLVED | B10: 9987 | C10: Daniel Motaung | D10: 2026-09-24 | E10: 07:00–15:00 Warehouse | F10: Rate choice: Warehouse or Event/Venue | G10: RATE CHOICE NEEDED: the wording mentions "warehouse" but the work type is Normal, so it is not clearly warehouse-only. Bernie must choose Warehouse (R81,25/h, Sunday R97,50, meeting time unpaid) or Venue/Event (R95/h, Sunday R114) before the rate is decided. Until then the shift stays at the engine amount. | I10: 8 | K10: approve original | L10: Bernie Burness | M10: 2026-09-23 06:39:23 | N10: Warehouse rate chosen — shift #9785 R1 620,00 → R0,00 (PUBLIC HOLIDAY — HELD for owner approval — recommended Warehouse public holiday (Heritage Day): 9 h × R162,50 (R81,25 × 2, no meeting deduction) = R1 462,50; R0 until approved)
A11: RESOLVED | B11: 10138 | C11: Daniel Motaung | D11: 2026-09-24 | E11: 07:00–15:00 Warehouse | F11: Public holiday (Heritage Day) — owner to approve or decline | G11: PUBLIC HOLIDAY — Heritage Day (24 Sep 2026): Daniel Motaung worked 07:00–16:00. Held for owner approval. | I11: 8 | J11: 7.5 | K11: approve adjusted | L11: Bernie Burness | M11: 2026-09-23 10:28:52 | N11: Public holiday (Heritage Day) approved by Bernie Burness 23 Sep — hours set to 07:00–15:00 (no set-ups): Warehouse public holiday (Heritage Day), owner set hours 07:00–15:00: 8.0 h − 0.5 h staff meeting 07:00–07:30 (unpaid) = 7.5 h × R162,50 (R81,25 × 2) = R1218.75
A12: RESOLVED | B12: 10048 | C12: Erence Mngomezulu | D12: 2026-09-22 | E12: 07:00–16:00 Warehouse | F12: Rate choice: Warehouse or Event/Venue | G12: RATE CHOICE NEEDED: the wording mentions "warehouse" but the work type is Normal, so it is not clearly warehouse-only. Bernie must choose Warehouse (R81,25/h, Sunday R97,50, meeting time unpaid) or Venue/Event (R95/h, Sunday R114) before the rate is decided. Until then the shift stays at the engine amount. | I12: 9 | K12: approve original | L12: Bernie Burness | M12: 2026-09-23 06:40:06 | N12: Warehouse rate chosen — shift #9826 R750,00 → R690,63 (Warehouse: 9 h − 0.5 h staff meeting 07:00–07:30 (unpaid, R40,63) = 8.5 h × R81,25)
A13: RESOLVED | B13: 10050 | C13: Erence Mngomezulu | D13: 2026-09-23 | E13: 07:00–16:00 Warehouse | F13: Rate choice: Warehouse or Event/Venue | G13: RATE CHOICE NEEDED: the wording mentions "warehouse" but the work type is Normal, so it is not clearly warehouse-only. Bernie must choose Warehouse (R81,25/h, Sunday R97,50, meeting time unpaid) or Venue/Event (R95/h, Sunday R114) before the rate is decided. Until then the shift stays at the engine amount. | I13: 9 | K13: approve original | L13: Bernie Burness | M13: 2026-09-23 06:40:07 | N13: Warehouse rate chosen — shift #9827 R750,00 → R690,63 (Warehouse: 9 h − 0.5 h staff meeting 07:00–07:30 (unpaid, R40,63) = 8.5 h × R81,25)
A14: RESOLVED | B14: 10053 | C14: Erence Mngomezulu | D14: 2026-09-24 | E14: 07:00–15:00 Warehouse | F14: Rate choice: Warehouse or Event/Venue | G14: RATE CHOICE NEEDED: the wording mentions "warehouse" but the work type is Normal, so it is not clearly warehouse-only. Bernie must choose Warehouse (R81,25/h, Sunday R97,50, meeting time unpaid) or Venue/Event (R95/h, Sunday R114) before the rate is decided. Until then the shift stays at the engine amount. | I14: 8 | K14: approve original | L14: Bernie Burness | M14: 2026-09-23 06:40:09 | N14: Warehouse rate chosen — shift #9829 R1 620,00 → R0,00 (PUBLIC HOLIDAY — HELD for owner approval — recommended Warehouse public holiday (Heritage Day): 9 h × R162,50 (R81,25 × 2, no meeting deduction) = R1 462,50; R0 until approved)
A15: RESOLVED | B15: 10139 | C15: Erence Mngomezulu | D15: 2026-09-24 | E15: 07:00–15:00 Warehouse | F15: Public holiday (Heritage Day) — owner to approve or decline | G15: PUBLIC HOLIDAY — Heritage Day (24 Sep 2026): Erence Mngomezulu worked 07:00–16:00. Held for owner approval. | I15: 8 | J15: 7.5 | K15: approve adjusted | L15: Bernie Burness | M15: 2026-09-23 10:28:58 | N15: Public holiday (Heritage Day) approved by Bernie Burness 23 Sep — hours set to 07:00–15:00 (no set-ups): Warehouse public holiday (Heritage Day), owner set hours 07:00–15:00: 8.0 h − 0.5 h staff meeting 07:00–07:30 (unpaid) = 7.5 h × R162,50 (R81,25 × 2) = R1218.75
A16: RESOLVED | B16: 10015 | C16: Erick Mpho Molefe | D16: 2026-09-22 | E16: 07:00–16:00 warehouse | F16: Rate choice: Warehouse or Event/Venue | G16: RATE CHOICE NEEDED: the wording mentions "warehouse" but the work type is Normal, so it is not clearly warehouse-only. Bernie must choose Warehouse (R81,25/h, Sunday R97,50, meeting time unpaid) or Venue/Event (R95/h, Sunday R114) before the rate is decided. Until then the shift stays at the engine amount. | I16: 9 | K16: approve original | L16: Bernie Burness | M16: 2026-09-23 06:40:17 | N16: Warehouse rate chosen — shift #9800 R750,00 → R690,63 (Warehouse: 9 h − 0.5 h staff meeting 07:00–07:30 (unpaid, R40,63) = 8.5 h × R81,25)
A17: RESOLVED | B17: 10010 | C17: Erick Mpho Molefe | D17: 2026-09-24 | E17: 07:00–15:00 wharehouse | F17: Public holiday (Heritage Day) — owner to approve or decline | G17: PUBLIC HOLIDAY — OWNER APPROVAL NEEDED: Erick Mpho Molefe worked 07:00–16:00 on 2026-09-24 (Heritage Day) at wharehouse (Normal). Public-holiday work is not paid automatically. Recommended: Venue/event public holiday (Heritage Day): 9 h × R190 (R95 × 2) = R1 710,00. R0 is paid until the owner approves or declines. | I17: 8 | J17: 7.5 | K17: approve adjusted | L17: Bernie Burness | M17: 2026-09-23 10:29:03 | N17: Public holiday (Heritage Day) approved by Bernie Burness 23 Sep — hours set to 07:00–15:00 (no set-ups): Warehouse public holiday (Heritage Day), owner set hours 07:00–15:00: 8.0 h − 0.5 h staff meeting 07:00–07:30 (unpaid) = 7.5 h × R162,50 (R81,25 × 2) = R1218.75
A18: RESOLVED | B18: 10073 | C18: Givemore Chifetete Kuziwa | D18: 2026-09-17 | E18: 06:00–18:00 Warehouse | F18: Warehouse claimed — but area says “Pretoria and fnb” | G18: WAREHOUSE CLAIMED BUT AREA SAYS “Pretoria and fnb”: Givemore Chifetete Kuziwa selected Warehouse Team at “Warehouse” for 12.00 h on Thu 17 Sep 2026, but wrote the area as “Pretoria and fnb” — that is a venue, not the warehouse. Other workers were at Botanical garden Pretoria that day. If he was at “Pretoria and fnb”, he is due the venue rate (R95/h); if he was really in the warehouse, R81,25/h. Choose below. | I18: 12 | K18: approve original | L18: Bernie Burness | M18: 2026-09-23 08:58:26 | N18: Event/Venue rate chosen — shift #9789 R934,38 → R640,00 (Venue/event: 12 h × R95 → DIFFERENCE ONLY: Paid last week 08:00–16:00 House/Garden 8.00 h × R62,50 = R500,00 (shift #9705, payroll earlier); 06:00–18:00 at a venue = R1 140,00 (R95,00/h); less the House/Garden already paid R500,00; TO PAY THIS WEEK R640,00)
A19: RESOLVED | B19: 10140 | C19: Givemore Chifetete Kuziwa | D19: 2026-09-24 | E19: 08:00–15:00 Garden | F19: Public holiday (Heritage Day) — Givemore — approved R1 000,00 — CHECK HOURS NEXT WEEK | G19: PUBLIC HOLIDAY — Heritage Day: Givemore (gardener) claimed 08:00–16:00. Owner: double the day = R1 000. VERIFY NEXT WEEK whether he actually worked 8 h or 4 h. | I19: 7 | J19: 7 | K19: approve original | L19: Bernie Burness | M19: 2026-09-23 10:31:30 | N19: Public holiday (Heritage Day) approved by Bernie Burness 23 Sep — gardener, hours set to 08:00–15:00: 7 h × R62,50 × 2 = R875,00. CHECK NEXT WEEK what time he really worked until.
A20: RESOLVED | B20: 10104 | C20: Isaac Mbele | D20: 2026-09-21 | E20: 07:00–16:00 Warehouse | F20: Rate choice: Warehouse or Event/Venue | G20: RATE CHOICE NEEDED: the wording mentions "warehouse" but the work type is Normal, so it is not clearly warehouse-only. Bernie must choose Warehouse (R81,25/h, Sunday R97,50, meeting time unpaid) or Venue/Event (R95/h, Sunday R114) before the rate is decided. Until then the shift stays at the engine amount. | I20: 9 | K20: approve original | L20: Bernie Burness | M20: 2026-09-23 08:43:25 | N20: Warehouse rate chosen — shift #9850 R750,00 → R690,63 (Warehouse: 9 h − 0.5 h staff meeting 07:00–07:30 (unpaid, R40,63) = 8.5 h × R81,25)
A21: RESOLVED | B21: 10106 | C21: Isaac Mbele | D21: 2026-09-22 | E21: 07:00–16:00 Warehouse | F21: Rate choice: Warehouse or Event/Venue | G21: RATE CHOICE NEEDED: the wording mentions "warehouse" but the work type is Normal, so it is not clearly warehouse-only. Bernie must choose Warehouse (R81,25/h, Sunday R97,50, meeting time unpaid) or Venue/Event (R95/h, Sunday R114) before the rate is decided. Until then the shift stays at the engine amount. | I21: 9 | K21: approve original | L21: Bernie Burness | M21: 2026-09-23 08:43:27 | N21: Warehouse rate chosen — shift #9851 R750,00 → R690,63 (Warehouse: 9 h − 0.5 h staff meeting 07:00–07:30 (unpaid, R40,63) = 8.5 h × R81,25)
A22: RESOLVED | B22: 10118 | C22: Isaac Mbele | D22: 2026-09-23 | E22: 07:00–16:00 Warehouse | F22: Rate choice: Warehouse or Event/Venue | G22: RATE CHOICE NEEDED: the wording mentions "warehouse" but the work type is Normal, so it is not clearly warehouse-only. Bernie must choose Warehouse (R81,25/h, Sunday R97,50, meeting time unpaid) or Venue/Event (R95/h, Sunday R114) before the rate is decided. Until then the shift stays at the engine amount. | I22: 9 | K22: approve original | L22: Bernie Burness | M22: 2026-09-23 08:43:31 | N22: Warehouse rate chosen — shift #9854 R750,00 → R690,63 (Warehouse: 9 h − 0.5 h staff meeting 07:00–07:30 (unpaid, R40,63) = 8.5 h × R81,25)
A23: RESOLVED | B23: 10125 | C23: Isaac Mbele | D23: 2026-09-24 | E23: 07:00–15:00 Warehouse | F23: Rate choice: Warehouse or Event/Venue | G23: RATE CHOICE NEEDED: the wording mentions "warehouse" but the work type is Normal, so it is not clearly warehouse-only. Bernie must choose Warehouse (R81,25/h, Sunday R97,50, meeting time unpaid) or Venue/Event (R95/h, Sunday R114) before the rate is decided. Until then the shift stays at the engine amount. | I23: 8 | K23: approve original | L23: Bernie Burness | M23: 2026-09-23 08:43:34 | N23: Warehouse rate chosen — shift #9856 R1 620,00 → R0,00 (PUBLIC HOLIDAY — HELD for owner approval — recommended Warehouse public holiday (Heritage Day): 9 h × R162,50 (R81,25 × 2, no meeting deduction) = R1 462,50; R0 until approved)
A24: RESOLVED | B24: 10141 | C24: Isaac Mbele | D24: 2026-09-24 | E24: 07:00–15:00 Warehouse | F24: Public holiday (Heritage Day) — owner to approve or decline | G24: PUBLIC HOLIDAY — Heritage Day (24 Sep 2026): Isaac Mbele worked 07:00–15:00. Held for owner approval. | I24: 8 | J24: 7.5 | K24: approve adjusted | L24: Bernie Burness | M24: 2026-09-23 10:32:01 | N24: Public holiday (Heritage Day) approved by Bernie Burness 23 Sep — hours set to 07:00–15:00 (no set-ups): Warehouse public holiday (Heritage Day), owner set hours 07:00–15:00: 8.0 h − 0.5 h staff meeting 07:00–07:30 (unpaid) = 7.5 h × R162,50 (R81,25 × 2) = R1218.75
A25: RESOLVED | B25: 10129 | C25: Isaac Mbele | D25: 2026-09-25 | E25: 07:00–16:00 Warehouse | F25: Rate choice: Warehouse or Event/Venue | G25: RATE CHOICE NEEDED: the wording mentions "warehouse" but the work type is Normal, so it is not clearly warehouse-only. Bernie must choose Warehouse (R81,25/h, Sunday R97,50, meeting time unpaid) or Venue/Event (R95/h, Sunday R114) before the rate is decided. Until then the shift stays at the engine amount. | I25: 9 | K25: approve original | L25: Bernie Burness | M25: 2026-09-23 08:43:37 | N25: Warehouse rate chosen — shift #9858 R750,00 → R690,63 (Warehouse: 9 h − 0.5 h staff meeting 07:00–07:30 (unpaid, R40,63) = 8.5 h × R81,25)
A26: RESOLVED | B26: 10122 | C26: John Simbarashe Mhlanga | D26: 2026-09-16 | E26: 07:00–16:00 Botanical gardens event day | F26: Manual overlap review | G26: the same employee has another overlapping entry on 2026-09-16 for 07:00-16:00. | I26: 9 | J26: 0 | K26: already paid r0 | L26: Bernie Burness | M26: 2026-09-23 08:53:49 | N26: ALREADY BILLED Wednesday 2026-09-16 · 07:00–16:00 · 9.00 h Normal · Botanical gardens event day · Running the event at botanical Gardens R750,00 · shift #9766 · PAID in payroll 2026-09-12 → 2026-09-18 (closed)
A27: RESOLVED | B27: 10132 | C27: John Simbarashe Mhlanga | D27: 2026-09-16 | E27: 07:00–16:00 Botanical gardens event day | F27: ALREADY PAID — WRONG RATE | G27: John was paid Wed 16 Sep 2026 07:00–16:00 · Botanical gardens event day (Pretoria) · Normal · "Running the event at botanical Gardens" · 9.00 h × R90,00 = R750,00 (payroll 2026-09-12). He now claims 07:00–16:00 · Botanical gardens event day (Pretoria) · Normal · "Running the event at botanical Gardens" · 9.00 h for the same day. Same work type, but the rate paid (R90,00/h) differs from the rule (R95,00/h). • Rate correction on the paid hours 07:00–16:00: 9.00 h — worth R855,00 at the correct rule, R750,00 was paid → +R105,00 Still due: R105,00 (full day 9.00 h at the correct rule = R855,00 − R750,00 already paid). Hours from Wednesday onwards are estimated for the auditor run; this entry corrects them. Bernie to approve — nothing has been changed. | H27: 0 | I27: 9 | J27: 0 | K27: approve adjusted | L27: Bernie Burness | M27: 2026-09-23 08:56:44 | N27: Already paid — WRONG RATE — R105,00 still due — approved amount R105,00
A28: RESOLVED | B28: 9972 | C28: John Simbarashe Mhlanga | D28: 2026-09-17 | E28: 15:00–20:00 Music Bus | F28: Manual overlap review | G28: the same employee has another overlapping entry on 2026-09-17 for 15:00-20:00. | I28: 5 | J28: 4 | K28: approve adjusted | L28: Bernie Burness | M28: 2026-09-23 08:56:08 | N28: ALREADY BILLED Thursday 2026-09-17 · 07:00–16:00 · 9.00 h Normal · FNB Stadium · Setting up R750,00 · shift #9767 · PAID in payroll 2026-09-12 → 2026-09-18 (closed)
A29: RESOLVED | B29: 10069 | C29: John Simbarashe Mhlanga | D29: 2026-09-17 | E29: 15:00–20:00 Music Bus | F29: ALREADY PAID — EXTRA HOURS | G29: John was paid Thu 17 Sep 2026 07:00–16:00 · FNB Stadium (Jhb) · Normal · "Setting up" · 9.00 h × R90,00 = R750,00 (payroll 2026-09-12). He now claims 15:00–20:00 · Music Bus (Thembisa) · Music Bus · "Missed shifts from Thursday doing music bus in Thembisa where there was a trade visit" · 5.00 h for the same day. Work type changed: Normal → Music Bus (rate R90,00 → R120,00). • Extra hours 16:00–20:00: 4.00 h → R480,00 Still due: R480,00 (full day 5.00 h at the correct rule = R1 230,00 − R750,00 already paid). Hours from Wednesday onwards are estimated for the auditor run; this entry corrects them. Bernie to approve — nothing has been changed. | H29: 4 | I29: 5 | J29: 4 | K29: approve adjusted | L29: Bernie Burness | M29: 2026-09-23 09:03:50 | N29: Already paid — EXTRA HOURS — R480,00 still due — approved amount R480,00
A30: RESOLVED | B30: 10072 | C30: John Simbarashe Mhlanga | D30: 2026-09-21 | E30: 07:00–16:00 FNB Stadium | F30: ALREADY PAID — SAME SHIFT AGAIN (duplicate) | G30: John was paid Mon 21 Sep 2026 07:00–16:00 · FNB Stadium (Soweto jhb) · Normal · "Strike down" · 9.00 h × R95,00 = R855,00 (payroll 2026-09-19). He now claims 07:00–16:00 · FNB Stadium (Soweto jhb) · Normal · "Strike down" · 9.00 h for the same day. Every hour of this claim is already paid. Nothing is due: R0,00. Hours from Wednesday onwards are estimated for the auditor run; this entry corrects them. Bernie to approve — nothing has been changed. | H30: 0 | I30: 9 | J30: 0 | K30: already paid r0 | L30: Bernie Burness | M30: 2026-09-23 09:01:41 | N30: Already paid — SAME SHIFT AGAIN (duplicate) — R0,00 still due — approved amount R0,00
A31: RESOLVED | B31: 10126 | C31: John Simbarashe Mhlanga | D31: 2026-09-21 | E31: 07:00–16:00 FNB Stadium | F31: Manual overlap review | G31: the same employee has another overlapping entry on 2026-09-21 for 07:00-16:00. | I31: 9 | J31: 0 | K31: already paid r0 | L31: Bernie Burness | M31: 2026-09-23 09:06:06 | N31: ALREADY BILLED Monday 2026-09-21 · 07:00–16:00 · 9.00 h Normal · FNB Stadium · Strike down R855,00 · shift #9857 · in THIS payroll (2026-09-19 → 2026-09-25, not yet paid)
A32: RESOLVED | B32: 10131 | C32: John Simbarashe Mhlanga | D32: 2026-09-21 | E32: 07:00–16:00 FNB Stadium | F32: ALREADY PAID — SAME SHIFT AGAIN (duplicate) | G32: John was paid Mon 21 Sep 2026 07:00–16:00 · FNB Stadium (Soweto jhb) · Normal · "Strike down" · 9.00 h × R95,00 = R855,00 (payroll 2026-09-19). He now claims 07:00–16:00 · FNB Stadium (Soweto jhb) · Normal · "Strike down" · 9.00 h for the same day. Every hour of this claim is already paid. Nothing is due: R0,00. Hours from Wednesday onwards are estimated for the auditor run; this entry corrects them. Bernie to approve — nothing has been changed. | H32: 0 | I32: 9 | J32: 0 | K32: already paid r0 | L32: Bernie Burness | M32: 2026-09-23 09:03:55 | N32: Already paid — SAME SHIFT AGAIN (duplicate) — R0,00 still due — approved amount R0,00
A33: RESOLVED | B33: 9983 | C33: John Simbarashe Mhlanga | D33: 2026-09-22 | E33: 07:00–16:00 Warehouse | F33: Rate choice: Warehouse or Event/Venue | G33: RATE CHOICE NEEDED: the wording mentions "warehouse" but the work type is Normal, so it is not clearly warehouse-only. Bernie must choose Warehouse (R81,25/h, Sunday R97,50, meeting time unpaid) or Venue/Event (R95/h, Sunday R114) before the rate is decided. Until then the shift stays at the engine amount. | I33: 9 | K33: approve original | L33: Bernie Burness | M33: 2026-09-23 09:02:31 | N33: Warehouse rate chosen — shift #9783 R750,00 → R690,63 (Warehouse: 9 h − 0.5 h staff meeting 07:00–07:30 (unpaid, R40,63) = 8.5 h × R81,25)
A34: RESOLVED | B34: 10092 | C34: John Simbarashe Mhlanga | D34: 2026-09-24 | E34: 07:00–12:00 Warehouse | F34: Rate choice: Warehouse or Event/Venue | G34: RATE CHOICE NEEDED: the wording mentions "warehouse" but the work type is Normal, so it is not clearly warehouse-only. Bernie must choose Warehouse (R81,25/h, Sunday R97,50, meeting time unpaid) or Venue/Event (R95/h, Sunday R114) before the rate is decided. Until then the shift stays at the engine amount. | I34: 5 | K34: approve original | L34: Bernie Burness | M34: 2026-09-23 09:02:56 | N34: Warehouse rate chosen — shift #9846 R900,00 → R0,00 (PUBLIC HOLIDAY — HELD for owner approval — recommended Warehouse public holiday (Heritage Day): 5 h × R162,50 (R81,25 × 2, no meeting deduction) = R812,50; R0 until approved)
A35: RESOLVED | B35: 10095 | C35: John Simbarashe Mhlanga | D35: 2026-09-24 | E35: 12:00–18:00 Music Bus | F35: Public holiday (Heritage Day) — owner to approve or decline | G35: PUBLIC HOLIDAY — OWNER APPROVAL NEEDED: John Simbarashe Mhlanga worked 12:00–18:00 on 2026-09-24 (Heritage Day) at Music Bus (Music Bus). Public-holiday work is not paid automatically. Recommended: Music Bus public holiday (Heritage Day): R750 fixed 07–16 + 2 h outside 07–16 × R180 = R1 110,00. R0 is paid until the owner approves or declines. | I35: 6 | J35: 6 | K35: approve adjusted | L35: Bernie Burness | M35: 2026-09-23 09:05:05 | N35: Public holiday (Heritage Day) approved — R1 110,00 (as recommended)
A36: RESOLVED | B36: 10144 | C36: John Simbarashe Mhlanga | D36: 2026-09-24 | E36: 07:00–12:00 Warehouse | F36: Public holiday (Heritage Day) — owner to approve or decline | G36: PUBLIC HOLIDAY — Heritage Day (24 Sep 2026): John Simbarashe Mhlanga worked 07:00–12:00. Held for owner approval. | I36: 5 | J36: 4.5 | K36: approve original | L36: Bernie Burness | M36: 2026-09-23 10:31:24 | N36: Public holiday (Heritage Day) approved by Bernie Burness 23 Sep at the holiday rate: Warehouse public holiday (Heritage Day): 5 h − 0.5 h staff meeting 07:00–07:30 (unpaid) = 4.5 h × R162,50 (R81,25 × 2) = R731,25
A37: RESOLVED | B37: 10098 | C37: John Simbarashe Mhlanga | D37: 2026-09-25 | E37: 07:00–11:00 Warehouse | F37: Rate choice: Warehouse or Event/Venue | G37: RATE CHOICE NEEDED: the wording mentions "warehouse" but the work type is Normal, so it is not clearly warehouse-only. Bernie must choose Warehouse (R81,25/h, Sunday R97,50, meeting time unpaid) or Venue/Event (R95/h, Sunday R114) before the rate is decided. Until then the shift stays at the engine amount. | I37: 4 | K37: approve original | L37: Bernie Burness | M37: 2026-09-23 09:03:07 | N37: Warehouse rate chosen — shift #9848 R750,00 → R284,38 (Warehouse: 4 h − 0.5 h staff meeting 07:00–07:30 (unpaid, R40,63) = 3.5 h × R81,25)
A38: RESOLVED | B38: 10109 | C38: Joshua Motsamai Nteo | D38: 2026-09-13 | E38: 07:00–13:00 Pastdal pretoria | F38: Manual overlap review | G38: the same employee has another overlapping entry on 2026-09-13 for 07:00-13:00. | I38: 6 | J38: 0 | K38: already paid r0 | L38: Bernie Burness | M38: 2026-09-23 09:08:42 | N38: ALREADY BILLED Sunday 2026-09-13 · 07:00–13:00 · 6.00 h Normal · Pastdal pub · Strikedown R720,00 · shift #9638 · PAID in payroll 2026-09-12 → 2026-09-18 (closed)
A39: RESOLVED | B39: 10113 | C39: Joshua Motsamai Nteo | D39: 2026-09-13 | E39: 07:00–13:00 Pastdal pretoria | F39: ALREADY PAID — this claim is covered by what was paid | G39: Joshua was paid Sun 13 Sep 2026 07:00–13:00 · Pastdal pub (Pretoria) · Normal · "Strikedown" · 6.00 h × R120,00 = R720,00 (payroll 2026-09-12). He now claims 07:00–13:00 · Pastdal pretoria (Pretoria) · Normal · "Break down" · 6.00 h for the same day. Same work type, but the rate paid (R120,00/h) differs from the rule (R114,00/h). • Rate correction on the paid hours 07:00–13:00: 6.00 h — worth R684,00 at the correct rule, R720,00 was paid → −R36,00 What was paid (R720,00) already covers this claim (R684,00 at the correct rule). Nothing more is due: R0,00. Hours from Wednesday onwards are estimated for the auditor run; this entry corrects them. Bernie to approve — nothing has been changed. | H39: 0 | I39: 6 | J39: 0 | K39: already paid r0 | L39: Bernie Burness | M39: 2026-09-23 09:21:54 | N39: Already paid — this claim is covered by what was paid — R0,00 still due — approved amount R0,00
A40: RESOLVED | B40: 9959 | C40: Joshua Motsamai Nteo | D40: 2026-09-22 | E40: 07:00–16:00 Warehouse | F40: Rate choice: Warehouse or Event/Venue | G40: RATE CHOICE NEEDED: the wording mentions "warehouse" but the work type is Normal, so it is not clearly warehouse-only. Bernie must choose Warehouse (R81,25/h, Sunday R97,50, meeting time unpaid) or Venue/Event (R95/h, Sunday R114) before the rate is decided. Until then the shift stays at the engine amount. | I40: 9 | K40: approve original | L40: Bernie Burness | M40: 2026-09-23 09:09:09 | N40: Warehouse rate chosen — shift #9774 R750,00 → R690,63 (Warehouse: 9 h − 0.5 h staff meeting 07:00–07:30 (unpaid, R40,63) = 8.5 h × R81,25)
A41: RESOLVED | B41: 9964 | C41: Joshua Motsamai Nteo | D41: 2026-09-23 | E41: 07:00–16:00 Warehouse | F41: Rate choice: Warehouse or Event/Venue | G41: RATE CHOICE NEEDED: the wording mentions "warehouse" but the work type is Normal, so it is not clearly warehouse-only. Bernie must choose Warehouse (R81,25/h, Sunday R97,50, meeting time unpaid) or Venue/Event (R95/h, Sunday R114) before the rate is decided. Until then the shift stays at the engine amount. | I41: 9 | K41: approve original | L41: Bernie Burness | M41: 2026-09-23 09:09:11 | N41: Warehouse rate chosen — shift #9778 R750,00 → R690,63 (Warehouse: 9 h − 0.5 h staff meeting 07:00–07:30 (unpaid, R40,63) = 8.5 h × R81,25)
A42: RESOLVED | B42: 10110 | C42: Joshua Motsamai Nteo | D42: 2026-09-23 | E42: 07:00–16:00 Warehouse | F42: Manual overlap review | G42: the same employee has another overlapping entry on 2026-09-23 for 07:00-16:00. | I42: 9 | J42: 0 | K42: already paid r0 | L42: Bernie Burness | M42: 2026-09-23 09:20:39 | N42: already billed
A43: RESOLVED | B43: 10111 | C43: Joshua Motsamai Nteo | D43: 2026-09-23 | E43: 07:00–16:00 Warehouse | F43: Rate choice: Warehouse or Event/Venue | G43: RATE CHOICE NEEDED: the wording mentions "warehouse" but the work type is Normal, so it is not clearly warehouse-only. Bernie must choose Warehouse (R81,25/h, Sunday R97,50, meeting time unpaid) or Venue/Event (R95/h, Sunday R114) before the rate is decided. Until then the shift stays at the engine amount. | I43: 9 | K43: approve original | L43: Bernie Burness | M43: 2026-09-23 09:22:36 | N43: Warehouse rate chosen — shift #9853 R750,00 → R690,63 (Warehouse: 9 h − 0.5 h staff meeting 07:00–07:30 (unpaid, R40,63) = 8.5 h × R81,25)
A44: RESOLVED | B44: 9977 | C44: Joshua Motsamai Nteo | D44: 2026-09-24 | E44: 07:00–15:00 Warehouse | F44: Rate choice: Warehouse or Event/Venue | G44: RATE CHOICE NEEDED: the wording mentions "warehouse" but the work type is Normal, so it is not clearly warehouse-only. Bernie must choose Warehouse (R81,25/h, Sunday R97,50, meeting time unpaid) or Venue/Event (R95/h, Sunday R114) before the rate is decided. Until then the shift stays at the engine amount. | I44: 8 | K44: approve original | L44: Bernie Burness | M44: 2026-09-23 09:21:05 | N44: Warehouse rate chosen — shift #9780 R1 620,00 → R0,00 (PUBLIC HOLIDAY — HELD for owner approval — recommended Warehouse public holiday (Heritage Day): 9 h × R162,50 (R81,25 × 2, no meeting deduction) = R1 462,50; R0 until approved)
A45: RESOLVED | B45: 10135 | C45: Joshua Motsamai Nteo | D45: 2026-09-24 | E45: 07:00–15:00 Warehouse | F45: Public holiday (Heritage Day) — owner to approve or decline | G45: PUBLIC HOLIDAY — Heritage Day (24 Sep 2026): Joshua Motsamai Nteo worked 07:00–16:00 at Warehouse (Meyerton), Cleaning warehouse. Held for owner approval. | I45: 8 | J45: 7.5 | K45: approve adjusted | L45: Bernie Burness | M45: 2026-09-23 10:29:15 | N45: Public holiday (Heritage Day) approved by Bernie Burness 23 Sep — hours set to 07:00–15:00 (no set-ups): Warehouse public holiday (Heritage Day), owner set hours 07:00–15:00: 8.0 h − 0.5 h staff meeting 07:00–07:30 (unpaid) = 7.5 h × R162,50 (R81,25 × 2) = R1218.75
A46: RESOLVED | B46: 10149 | C46: Lebo Lebo | D46: 2026-09-24 | E46: 07:00–13:25 Warehouse | F46: Rate choice: Warehouse or Event/Venue | G46: RATE CHOICE NEEDED: the wording mentions "warehouse" but the work type is Normal, so it is not clearly warehouse-only. Bernie must choose Warehouse (R81,25/h, Sunday R97,50, meeting time unpaid) or Venue/Event (R95/h, Sunday R114) before the rate is decided. Until then the shift stays at the engine amount. | I46: 6.42 | K46: approve original | L46: Bernie Burness | M46: 2026-09-25 07:18:01 | N46: Event/Venue rate chosen — shift #9861 R802,50 → R0,00 (PUBLIC HOLIDAY — HELD for owner approval — recommended Venue/event public holiday (Heritage Day): 6.42 h × R190 (R95 × 2) = R1 219,17; R0 until approved)
A47: RESOLVED | B47: 9954 | C47: Patrick Ngozo | D47: 2026-09-22 | E47: 06:30–16:00 Wearhouse | F47: Rate choice: Warehouse or Venue/Event | G47: The wording says Wearhouse — Loading but the work type is Normal. Choose Warehouse (R81,25/h, 9.5 h less 0.5 h staff meeting = R731,25) or Venue/Event (R95/h = R902,50). The shift stays at R795 until you choose. | I47: 9.5 | K47: approve original | L47: Bernie Burness | M47: 2026-09-22 12:28:15 | N47: Warehouse rate chosen — shift #9773 R795,00 → R731,25 (Warehouse: 9.5 h − 0.5 h staff meeting 07:00–07:30 (unpaid, R40,63) = 9 h × R81,25)
A48: RESOLVED | B48: 10143 | C48: Patrick Ngozo | D48: 2026-09-24 | E48: 06:30–15:00 Wearhouse | F48: Public holiday (Heritage Day) — owner to approve or decline | G48: PUBLIC HOLIDAY — Heritage Day (24 Sep 2026): Patrick Ngozo worked 06:30–15:00. Held for owner approval. | I48: 8.5 | J48: 8 | K48: approve original | L48: Bernie Burness | M48: 2026-09-23 10:30:29 | N48: Public holiday (Heritage Day) approved by Bernie Burness 23 Sep at the holiday rate: Warehouse public holiday (Heritage Day), owner set hours 06:30–15:00: 8.5 h − 0.5 h staff meeting = 8 h × R162,50 = R1 300,00
A49: RESOLVED | B49: 10063 | C49: Solomon Moyo | D49: 2026-09-22 | E49: 07:00–16:00 Warehouse | F49: Rate choice: Warehouse or Event/Venue | G49: RATE CHOICE NEEDED: the wording mentions "warehouse" but the work type is Normal, so it is not clearly warehouse-only. Bernie must choose Warehouse (R81,25/h, Sunday R97,50, meeting time unpaid) or Venue/Event (R95/h, Sunday R114) before the rate is decided. Until then the shift stays at the engine amount. | I49: 9 | K49: approve original | L49: Bernie Burness | M49: 2026-09-23 10:48:16 | N49: Warehouse rate chosen — shift #9835 R750,00 → R690,63 (Warehouse: 9 h − 0.5 h staff meeting 07:00–07:30 (unpaid, R40,63) = 8.5 h × R81,25)
A50: RESOLVED | B50: 10060 | C50: Solomon Moyo | D50: 2026-09-24 | E50: 07:00–15:00 Warehouse | F50: Public holiday (Heritage Day) — owner to approve or decline | G50: PUBLIC HOLIDAY — OWNER APPROVAL NEEDED: Solomon Moyo worked 07:00–16:00 on 2026-09-24 (Heritage Day) at Botanical Gardens (Normal). Public-holiday work is not paid automatically. Recommended: Venue/event public holiday (Heritage Day): 9 h × R190 (R95 × 2) = R1 710,00. R0 is paid until the owner approves or declines. | I50: 8 | J50: 7.5 | K50: approve adjusted | L50: Bernie Burness | M50: 2026-09-23 10:31:21 | N50: Public holiday (Heritage Day) approved by Bernie Burness 23 Sep — warehouse, hours set to 07:00–15:00 (worker wrote Botanical Gardens until 16:00): Warehouse public holiday (Heritage Day), owner set hours 07:00–15:00: 8 h − 0.5 h staff meeting 07:00–07:30 (unpaid) = 7.5 h × R162,50 (R81,25 × 2) = R1 218,75
A51: RESOLVED | B51: 10074 | C51: Takavaudza Chokuda | D51: 2026-09-17 | E51: 16:00–18:00 FNB | F51: Warehouse claimed — but the entry names “Johannesburg” | G51: WAREHOUSE CLAIMED BUT THE ENTRY NAMES “Johannesburg”: Takavaudza Chokuda selected Warehouse Team at “FNB” for 2.00 h on Thu 17 Sep 2026, but wrote “Johannesburg” — that is a venue, not the warehouse. 6 workers were at a venue that day (Additional 5 hour shift - 17/09/2026 Parys Golf Day, Botanical garden Pretoria, FNB Stadium, Parys golf & country Estate, Parys Country Club, Parys, Botanical gardens, Fnb stadium). If he was at “Johannesburg”, he is due the venue rate (R95/h); if he was really in the warehouse, R81,25/h. Choose below. | I51: 2 | K51: approve original | L51: Bernie Burness | M51: 2026-09-23 11:01:57 | N51: Event/Venue rate chosen — shift #9815 R162,50 → R190,00 (Venue/event: 2 h × R95)
A52: RESOLVED | B52: 9955 | C52: Takavaudza Chokuda | D52: 2026-09-21 | E52: 07:00–16:00 Warehouse | F52: Crew pattern — 8 of 9 at a venue, this one says Warehouse | G52: CREW PATTERN: 8 of 9 workers were at a venue on Mon 21 Sep 2026 (FNB Stadium, FNB strike down, Fnb stadium) — Takavaudza Chokuda says Warehouse for 9.00 h. Check he was not at the venue (R95/h would be due). | I52: 9 | J52: 9 | K52: approve original | L52: Bernie Burness | M52: 2026-09-23 11:01:58 | N52: WAREHOUSE — R81,25/h chosen by Bernie Burness for draft #830 — will pay R690,63 when final-submitted (Warehouse: 9 h − 0.5 h staff meeting 07:00–07:30 (unpaid, R40,63) = 8.5 h × R81,25)
A53: RESOLVED | B53: 10075 | C53: Takavaudza Chokuda | D53: 2026-09-23 | E53: 07:00–16:00 Riverside | F53: Warehouse claimed — but the entry names “The vaal” | G53: WAREHOUSE CLAIMED BUT THE ENTRY NAMES “The vaal”: Takavaudza Chokuda selected Warehouse Team at “Riverside” for 9.00 h on Wed 23 Sep 2026, but wrote “The vaal” — that is a venue, not the warehouse. 6 workers were at a venue that day (Work with the Team, wharehouse, Set up vaal Boating, Riverside sun, Vaal Boating Season, Stone Haven And Riverside Sun). If he was at “The vaal”, he is due the venue rate (R95/h); if he was really in the warehouse, R81,25/h. Choose below. | I53: 9 | K53: approve original | L53: Bernie Burness | M53: 2026-09-23 11:01:57 | N53: Event/Venue rate chosen — shift #9819 R690,63 → R855,00 (Venue/event: 9 h × R95)
A54: RESOLVED | B54: 10039 | C54: Takavaudza Chokuda | D54: 2026-09-24 | E54: 07:00–15:00 Warehouse | F54: Public holiday (Heritage Day) — owner to approve or decline | G54: PUBLIC HOLIDAY — OWNER APPROVAL NEEDED: Takavaudza Chokuda worked 07:00–16:00 on 2026-09-24 (Heritage Day) at Warehouse (Warehouse Team). Public-holiday work is not paid automatically. Recommended: Warehouse public holiday (Heritage Day): 9 h × R162,50 (R81,25 × 2, no meeting deduction) = R1 462,50. R0 is paid until the owner approves or declines. | I54: 8 | J54: 7.5 | K54: approve adjusted | L54: Bernie Burness | M54: 2026-09-23 10:32:07 | N54: Public holiday (Heritage Day) approved by Bernie Burness 23 Sep — hours set to 07:00–15:00 (no set-ups): Warehouse public holiday (Heritage Day), owner set hours 07:00–15:00: 8.0 h − 0.5 h staff meeting 07:00–07:30 (unpaid) = 7.5 h × R162,50 (R81,25 × 2) = R1218.75
A55: RESOLVED | B55: 10076 | C55: Takavaudza Chokuda | D55: 2026-09-25 | E55: 07:00–16:00 Warehouse | F55: Crew pattern — 7 of 8 at a venue, this one says Warehouse | G55: CREW PATTERN: 7 of 8 workers were at a venue on Fri 25 Sep 2026 (The Capital Sandton and Bonitical Emmarentia, Pretoria country club, Botanical, Vaal Boating, Riverside sun, Pretoria Country Club, Capital hotel / botanical gardens JHB) — Takavaudza Chokuda says Warehouse for 9.00 h. Check he was not at the venue (R95/h would be due). | I55: 9 | K55: approve original | L55: Bernie Burness | M55: 2026-09-23 11:01:58 | N55: Warehouse rate chosen — shift #9817 R690,63 → R690,63 (Warehouse: 9 h − 0.5 h staff meeting 07:00–07:30 (unpaid, R40,63) = 8.5 h × R81,25)
A56: RESOLVED | B56: 10080 | C56: Thandanani Nkala | D56: 2026-09-21 | E56: 07:00–16:00 FNB Stadium and Warehouse | F56: Rate choice: Warehouse or Event/Venue | G56: RATE CHOICE NEEDED: the wording mentions "warehouse" but the work type is Normal, so it is not clearly warehouse-only. Bernie must choose Warehouse (R81,25/h, Sunday R97,50, meeting time unpaid) or Venue/Event (R95/h, Sunday R114) before the rate is decided. Until then the shift stays at the engine amount. | I56: 9 | K56: approve original | L56: Bernie Burness | M56: 2026-09-23 09:24:21 | N56: Event/Venue rate chosen — shift #9840 R750,00 → R855,00 (Venue/event: 9 h × R95)
A57: RESOLVED | B57: 10087 | C57: Thandanani Nkala | D57: 2026-09-22 | E57: 07:00–16:00 Warehouse | F57: Rate choice: Warehouse or Event/Venue | G57: RATE CHOICE NEEDED: the wording mentions "warehouse" but the work type is Normal, so it is not clearly warehouse-only. Bernie must choose Warehouse (R81,25/h, Sunday R97,50, meeting time unpaid) or Venue/Event (R95/h, Sunday R114) before the rate is decided. Until then the shift stays at the engine amount. | I57: 9 | K57: approve original | L57: Bernie Burness | M57: 2026-09-23 09:24:24 | N57: Warehouse rate chosen — shift #9844 R750,00 → R690,63 (Warehouse: 9 h − 0.5 h staff meeting 07:00–07:30 (unpaid, R40,63) = 8.5 h × R81,25)
A58: RESOLVED | B58: 10084 | C58: Thandanani Nkala | D58: 2026-09-24 | E58: 07:00–15:00 Warehouse | F58: Rate choice: Warehouse or Event/Venue | G58: RATE CHOICE NEEDED: the wording mentions "warehouse" but the work type is Normal, so it is not clearly warehouse-only. Bernie must choose Warehouse (R81,25/h, Sunday R97,50, meeting time unpaid) or Venue/Event (R95/h, Sunday R114) before the rate is decided. Until then the shift stays at the engine amount. | I58: 8 | K58: approve original | L58: Bernie Burness | M58: 2026-09-23 09:24:33 | N58: Warehouse rate chosen — shift #9842 R1 620,00 → R0,00 (PUBLIC HOLIDAY — HELD for owner approval — recommended Warehouse public holiday (Heritage Day): 9 h × R162,50 (R81,25 × 2, no meeting deduction) = R1 462,50; R0 until approved)
A59: RESOLVED | B59: 10142 | C59: Thandanani Nkala | D59: 2026-09-24 | E59: 07:00–15:00 Warehouse | F59: Public holiday (Heritage Day) — owner to approve or decline | G59: PUBLIC HOLIDAY — Heritage Day (24 Sep 2026): Thandanani Nkala worked 07:00–15:00. Held for owner approval. | I59: 8 | J59: 7.5 | K59: approve adjusted | L59: Bernie Burness | M59: 2026-09-23 10:32:12 | N59: Public holiday (Heritage Day) approved by Bernie Burness 23 Sep — hours set to 07:00–15:00 (no set-ups): Warehouse public holiday (Heritage Day), owner set hours 07:00–15:00: 8.0 h − 0.5 h staff meeting 07:00–07:30 (unpaid) = 7.5 h × R162,50 (R81,25 × 2) = R1218.75
A60: RESOLVED | B60: 10082 | C60: Thandanani Nkala | D60: 2026-09-25 | E60: 07:00–16:00 Warehouse | F60: Rate choice: Warehouse or Event/Venue | G60: RATE CHOICE NEEDED: the wording mentions "warehouse" but the work type is Normal, so it is not clearly warehouse-only. Bernie must choose Warehouse (R81,25/h, Sunday R97,50, meeting time unpaid) or Venue/Event (R95/h, Sunday R114) before the rate is decided. Until then the shift stays at the engine amount. | I60: 9 | K60: approve original | L60: Bernie Burness | M60: 2026-09-23 09:24:36 | N60: Warehouse rate chosen — shift #9841 R750,00 → R690,63 (Warehouse: 9 h − 0.5 h staff meeting 07:00–07:30 (unpaid, R40,63) = 8.5 h × R81,25)
A61: RESOLVED | B61: 10033 | C61: Tsotlego Petrus Malakoane | D61: 2026-09-24 | E61: 06:30–14:00 Warehouse | F61: Public holiday (Heritage Day) — owner to approve or decline | G61: PUBLIC HOLIDAY — OWNER APPROVAL NEEDED: Tsotlego Petrus Malakoane worked 06:30–16:00 on 2026-09-24 (Heritage Day) at Warehouse (Normal). Public-holiday work is not paid automatically. Recommended: Petrus public holiday (Heritage Day): no fixed day — 9.5 h × R160 (R80 × 2) = R1 520,00. R0 is paid until the owner approves or declines. | I61: 7.5 | J61: 7 | K61: approve adjusted | L61: Bernie Burness | M61: 2026-09-23 11:02:04 | N61: Public holiday (Heritage Day) approved by Bernie Burness 23 Sep — hours set to 06:30–14:00, meeting deducted: 7 h × R160 = R1 120,00. Owner not 100% sure of the end time — CONFIRM NEXT WEEK.

Sheet Loans & Deductions
A1: B&W PRODUCTIONS — LOANS & DEDUCTIONS
A2: Position as at 2026-09-25. Amounts actually deducted this week are the yellow cells on Auditor Trail Linked.
A4: FIXED WEEKLY DEDUCTIONS (active this week)
B5: Employee | C5: Type | D5: Effective from | E5: Reason | F5: Amount per week | G5: Effective to
B6: Erick Mpho Molefe | C6: Car Payment | D6: 2026-08-01 | E6: Car Payments | F6: 1000 | G6: ongoing
B7: Isaac Mbele | C7: Eggs | D7: 2026-08-01 | E7: Eggs | F7: 260 | G7: ongoing
A9: ADDITIONAL LOANS
A10: Loan # | B10: Employee | C10: Date given | D10: Deductions from | E10: Reason | F10: Original amount | G10: Instalment | H10: Repaid to date | I10: Outstanding balance | J10: Due this week | K10: Frequency | L10: Status | M10: Check
A11: #5 | B11: Daniel Motaung | C11: 2026-08-23 | D11: 2026-09-05 | E11: CT SCan Hopital needs money upfront for Scan as medical aid paid the d | F11: 3000 | G11: 500 | H11: 0 | I11: 0 | J11: 0 | K11: weekly | L11: paid | M11: Marked PAID but ledger shows only R0,00 repaid of R3 000,00 — please check
A12: #1 | B12: Erick Mpho Molefe | C12: 2026-08-08 | D12: 2026-08-08 | E12: Fix car Whatsapp -- send so we need to go check first because we still | F12: 2000 | G12: 500 | H12: 1500 | I12: 500 | J12: 500 | K12: weekly | L12: active
A13: #7 | B13: Erick Mpho Molefe | C13: 2026-09-22 | D13: 2026-09-26 | E13: 22 Sep 2026 WhatsApp 07:15: "Goodmorning Mama, can I please have R600 | F13: 500 | G13: 500 | H13: 0 | I13: 500 | J13: 0 | K13: weekly | L13: active
A14: #2 | B14: Isaac Mbele | C14: 2026-08-11 | D14: 2026-08-11 | E14: 3 August Morning mother this week I spent joo aim loan 300 hundred ple | F14: 900 | G14: 250 | H14: 550 | I14: 350 | J14: 250 | K14: weekly | L14: active
A15: #3 | B15: Isaac Mbele | C15: 2026-08-16 | D15: 2026-08-17 | E15: Morning mother joo aim asking 600 hundred loan please | F15: 600 | G15: 250 | H15: 450 | I15: 150 | J15: 150 | K15: weekly | L15: active
A16: #6 | B16: Isaac Mbele | C16: 2026-09-01 | D16: 2026-09-02 | E16: Morning mother my kids are having a trip off 1500 but aim short of 600 | F16: 600 | G16: 600 | H16: 0 | I16: 600 | J16: 600 | K16: weekly | L16: active
A17: #8 | B17: Isaac Mbele | C17: 2026-09-22 | D17: 2026-09-26 | E17: 22 Sep 2026 WhatsApp 08:15: "Mother so like. Aim not well balanced abo | F17: 500 | G17: 250 | H17: 0 | I17: 500 | J17: 0 | K17: weekly | L17: active
A19: LOAN REPAYMENT HISTORY (all payrolls)
A20: Loan # | B20: Employee | C20: Payroll week | D20: Recorded at | E20: Result | F20: Scheduled | G20: Deducted | H20: Balance before | I20: Balance after
A21: #1 | B21: Erick Mpho Molefe | C21: 2026-08-08 → 2026-08-14 | D21: 2026-08-11 10:12 | E21: deducted | F21: 500 | G21: 500 | H21: 2000 | I21: 1500
A22: #1 | B22: Erick Mpho Molefe | C22: 2026-08-15 → 2026-08-21 | D22: 2026-08-16 13:37 | E22: deducted | F22: 500 | G22: 500 | H22: 1500 | I22: 1000
A23: #1 | B23: Erick Mpho Molefe | C23: 2026-09-05 → 2026-09-11 | D23: 2026-09-07 12:01 | E23: deducted | F23: 500 | G23: 500 | H23: 1000 | I23: 500
A24: #2 | B24: Isaac Mbele | C24: 2026-08-08 → 2026-08-14 | D24: 2026-08-11 09:42 | E24: deferred | F24: 300 | G24: 0 | H24: 900 | I24: 900
A25: #2 | B25: Isaac Mbele | C25: 2026-08-15 → 2026-08-21 | D25: 2026-08-16 13:37 | E25: deducted | F25: 300 | G25: 300 | H25: 900 | I25: 600
A26: #2 | B26: Isaac Mbele | C26: 2026-09-05 → 2026-09-11 | D26: 2026-09-07 12:01 | E26: deducted | F26: 250 | G26: 250 | H26: 600 | I26: 350
A27: #3 | B27: Isaac Mbele | C27: 2026-08-15 → 2026-08-21 | D27: 2026-08-16 13:37 | E27: deducted | F27: 200 | G27: 200 | H27: 600 | I27: 400
A28: #3 | B28: Isaac Mbele | C28: 2026-09-05 → 2026-09-11 | D28: 2026-09-07 12:01 | E28: deducted | F28: 250 | G28: 250 | H28: 400 | I28: 150
A29: #5 | B29: Daniel Motaung | C29: 2026-09-05 → 2026-09-11 | D29: 2026-09-07 12:01 | E29: deferred | F29: 500 | G29: 0 | H29: 3000 | I29: 3000
A30: #6 | B30: Isaac Mbele | C30: 2026-09-05 → 2026-09-11 | D30: 2026-09-07 12:01 | E30: deferred | F30: 600 | G30: 0 | H30: 600 | I30: 600

Sheet Missed Shifts
A1: B&W PRODUCTIONS — MISSED SHIFTS (previous payroll, paid in this payroll)
A2: Payroll week 2026-09-19 to 2026-09-25. Approved hours = the green review decision (claimed hours where no review was needed). YELLOW hours cells can be overtyped — the Amount next to them recalculates automatically and flows to block 6 on the Auditor Trail and to the Summary.
A4: Worker | B4: Missed shift | C4: Approved hours | D4: Amount | E4: Notes
A5: Bhekizitha Maphosa | B5: Thu 17 Sep 2026 06:00–07:00 | C5: ='Wage Detail Linked'!O5 | D5: =IF('Wage Detail Linked'!O5=0,IF(C5>0,ROUND(C5*95,2),0),ROUND('Wage Detail Linked'!R5*C5/'Wage Detail Linked'!O5,2)) | E5: Worked Thu 17 Sep 2026 (previous payroll), not captured that week; final-submitted and paid in payroll 2026-09-19 to 2026-09-25. CLEAR worked 07:00–16:00 that day (paid); these hours are outside those times
A6: Bhekizitha Maphosa | B6: Thu 17 Sep 2026 16:00–18:00 | C6: ='Wage Detail Linked'!O6 | D6: =IF('Wage Detail Linked'!O6=0,IF(C6>0,ROUND(C6*95,2),0),ROUND('Wage Detail Linked'!R6*C6/'Wage Detail Linked'!O6,2)) | E6: Worked Thu 17 Sep 2026 (previous payroll), not captured that week; final-submitted and paid in payroll 2026-09-19 to 2026-09-25. CLEAR worked 07:00–16:00 that day (paid); these hours are outside those times
A7: Bhekizitha Maphosa — missed total | C7: =SUM(C5:C6) | D7: =SUM(D5:D6)
A9: Erence Mngomezulu | B9: Wed 16 Sep 2026 16:00–18:00 | C9: ='Wage Detail Linked'!O17 | D9: =IF('Wage Detail Linked'!O17=0,IF(C9>0,ROUND(C9*95,2),0),ROUND('Wage Detail Linked'!R17*C9/'Wage Detail Linked'!O17,2)) | E9: Worked Wed 16 Sep 2026 (previous payroll), not captured that week; final-submitted and paid in payroll 2026-09-19 to 2026-09-25. CLEAR worked 07:00–16:00 that day (paid); these hours are outside those times
A10: Erence Mngomezulu | B10: Thu 17 Sep 2026 06:00–07:00 | C10: ='Wage Detail Linked'!O18 | D10: =IF('Wage Detail Linked'!O18=0,IF(C10>0,ROUND(C10*95,2),0),ROUND('Wage Detail Linked'!R18*C10/'Wage Detail Linked'!O18,2)) | E10: Worked Thu 17 Sep 2026 (previous payroll), not captured that week; final-submitted and paid in payroll 2026-09-19 to 2026-09-25. CLEAR worked 07:00–16:00 that day (paid); these hours are outside those times
A11: Erence Mngomezulu | B11: Thu 17 Sep 2026 16:00–20:00 | C11: ='Wage Detail Linked'!O19 | D11: =IF('Wage Detail Linked'!O19=0,IF(C11>0,ROUND(C11*95,2),0),ROUND('Wage Detail Linked'!R19*C11/'Wage Detail Linked'!O19,2)) | E11: Worked Thu 17 Sep 2026 (previous payroll), not captured that week; final-submitted and paid in payroll 2026-09-19 to 2026-09-25. CLEAR worked 07:00–16:00 that day (paid); these hours are outside those times
A12: Erence Mngomezulu — missed total | C12: =SUM(C9:C11) | D12: =SUM(D9:D11)
A14: Erick Mpho Molefe | B14: Thu 17 Sep 2026 16:00–18:00 | C14: ='Wage Detail Linked'!O25 | D14: =IF('Wage Detail Linked'!O25=0,IF(C14>0,ROUND(C14*95,2),0),ROUND('Wage Detail Linked'!R25*C14/'Wage Detail Linked'!O25,2)) | E14: Worked Thu 17 Sep 2026 (previous payroll), not captured that week; final-submitted and paid in payroll 2026-09-19 to 2026-09-25. CLEAR worked 07:00–16:00 that day (paid); these hours are outside those times
A15: Erick Mpho Molefe — missed total | C15: =SUM(C14:C14) | D15: =SUM(D14:D14)
A17: Givemore Chifetete Kuziwa | B17: Thu 17 Sep 2026 06:00–18:00 | C17: ='Wage Detail Linked'!O31 | D17: =IF('Wage Detail Linked'!O31=0,IF(C17>0,ROUND(C17*95,2),0),ROUND('Wage Detail Linked'!R31*C17/'Wage Detail Linked'!O31,2)) | E17: Worked Thu 17 Sep 2026 (previous payroll), not captured that week; final-submitted and paid in payroll 2026-09-19 to 2026-09-25. OVERLAP already paid 08:00–16:00 (Garden, payroll n/a)
A18: Givemore Chifetete Kuziwa — missed total | C18: =SUM(C17:C17) | D18: =SUM(D17:D17)
A20: John Simbarashe Mhlanga | B20: Wed 16 Sep 2026 07:00–16:00 | C20: ='Wage Detail Linked'!O43 | D20: =IF('Wage Detail Linked'!O43=0,IF(C20>0,ROUND(C20*95,2),0),ROUND('Wage Detail Linked'!R43*C20/'Wage Detail Linked'!O43,2)) | E20: Worked Wed 16 Sep 2026 (previous payroll), not captured that week; final-submitted and paid in payroll 2026-09-19 to 2026-09-25. OVERLAP already paid 07:00–16:00 (Botanical gardens event day, payroll n/a)
A21: John Simbarashe Mhlanga | B21: Thu 17 Sep 2026 15:00–20:00 | C21: ='Wage Detail Linked'!O44 | D21: =IF('Wage Detail Linked'!O44=0,IF(C21>0,ROUND(C21*120,2),0),ROUND('Wage Detail Linked'!R44*C21/'Wage Detail Linked'!O44,2)) | E21: Worked Thu 17 Sep 2026 (previous payroll), not captured that week; final-submitted and paid in payroll 2026-09-19 to 2026-09-25. OVERLAP already paid 07:00–16:00 (FNB Stadium, payroll n/a)
A22: John Simbarashe Mhlanga — missed total | C22: =SUM(C20:C21) | D22: =SUM(D20:D21)
A24: Joshua Motsamai Nteo | B24: Sun 13 Sep 2026 07:00–13:00 | C24: ='Wage Detail Linked'!O53 | D24: =IF('Wage Detail Linked'!O53=0,IF(C24>0,ROUND(C24*114,2),0),ROUND('Wage Detail Linked'!R53*C24/'Wage Detail Linked'!O53,2)) | E24: Worked Sun 13 Sep 2026 (previous payroll), not captured that week; final-submitted and paid in payroll 2026-09-19 to 2026-09-25. OVERLAP already paid 07:00–13:00 (Pastdal pub, payroll n/a)
A25: Joshua Motsamai Nteo | B25: Thu 17 Sep 2026 05:00–07:00 | C25: ='Wage Detail Linked'!O54 | D25: =IF('Wage Detail Linked'!O54=0,IF(C25>0,ROUND(C25*95,2),0),ROUND('Wage Detail Linked'!R54*C25/'Wage Detail Linked'!O54,2)) | E25: Worked Thu 17 Sep 2026 (previous payroll), not captured that week; final-submitted and paid in payroll 2026-09-19 to 2026-09-25. CLEAR worked 07:00–16:00 that day (paid); these hours are outside those times
A26: Joshua Motsamai Nteo | B26: Thu 17 Sep 2026 16:00–18:30 | C26: ='Wage Detail Linked'!O55 | D26: =IF('Wage Detail Linked'!O55=0,IF(C26>0,ROUND(C26*95,2),0),ROUND('Wage Detail Linked'!R55*C26/'Wage Detail Linked'!O55,2)) | E26: Worked Thu 17 Sep 2026 (previous payroll), not captured that week; final-submitted and paid in payroll 2026-09-19 to 2026-09-25. CLEAR worked 07:00–16:00 that day (paid); these hours are outside those times
A27: Joshua Motsamai Nteo — missed total | C27: =SUM(C24:C26) | D27: =SUM(D24:D26)
A29: Patrick Ngozo | B29: Wed 16 Sep 2026 16:00–18:00 | C29: ='Wage Detail Linked'!O64 | D29: =IF('Wage Detail Linked'!O64=0,IF(C29>0,ROUND(C29*95,2),0),ROUND('Wage Detail Linked'!R64*C29/'Wage Detail Linked'!O64,2)) | E29: Worked Wed 16 Sep 2026 (previous payroll), not captured that week; final-submitted and paid in payroll 2026-09-19 to 2026-09-25. CLEAR worked 06:30–16:00 that day (paid); these hours are outside those times
A30: Patrick Ngozo | B30: Thu 17 Sep 2026 06:00–07:00 | C30: ='Wage Detail Linked'!O65 | D30: =IF('Wage Detail Linked'!O65=0,IF(C30>0,ROUND(C30*95,2),0),ROUND('Wage Detail Linked'!R65*C30/'Wage Detail Linked'!O65,2)) | E30: Worked Thu 17 Sep 2026 (previous payroll), not captured that week; final-submitted and paid in payroll 2026-09-19 to 2026-09-25. CLEAR worked 07:00–16:00 that day (paid); these hours are outside those times
A31: Patrick Ngozo | B31: Thu 17 Sep 2026 16:00–20:00 | C31: ='Wage Detail Linked'!O66 | D31: =IF('Wage Detail Linked'!O66=0,IF(C31>0,ROUND(C31*95,2),0),ROUND('Wage Detail Linked'!R66*C31/'Wage Detail Linked'!O66,2)) | E31: Worked Thu 17 Sep 2026 (previous payroll), not captured that week; final-submitted and paid in payroll 2026-09-19 to 2026-09-25. CLEAR worked 07:00–16:00 that day (paid); these hours are outside those times
A32: Patrick Ngozo — missed total | C32: =SUM(C29:C31) | D32: =SUM(D29:D31)
A34: Solomon Moyo | B34: Wed 16 Sep 2026 16:00–18:00 | C34: ='Wage Detail Linked'!O72 | D34: =IF('Wage Detail Linked'!O72=0,IF(C34>0,ROUND(C34*95,2),0),ROUND('Wage Detail Linked'!R72*C34/'Wage Detail Linked'!O72,2)) | E34: Worked Wed 16 Sep 2026 (previous payroll), not captured that week; final-submitted and paid in payroll 2026-09-19 to 2026-09-25. CLEAR worked 07:00–16:00 that day (paid); these hours are outside those times
A35: Solomon Moyo | B35: Thu 17 Sep 2026 16:00–21:00 | C35: ='Wage Detail Linked'!O73 | D35: =IF('Wage Detail Linked'!O73=0,IF(C35>0,ROUND(C35*95,2),0),ROUND('Wage Detail Linked'!R73*C35/'Wage Detail Linked'!O73,2)) | E35: Worked Thu 17 Sep 2026 (previous payroll), not captured that week; final-submitted and paid in payroll 2026-09-19 to 2026-09-25. CLEAR worked 07:00–16:00 that day (paid); these hours are outside those times
A36: Solomon Moyo — missed total | C36: =SUM(C34:C35) | D36: =SUM(D34:D35)
